Workbook

Sheet Landing Page
A1: Welcome! I hope this information is useful to those viewing!
A5: Build Solvers
A6: =HYPERLINK("https://coloronx.github.io/Mycopunk_UpgradeSolver/", "Grid Solver") -> Grid Solver
A7: =HYPERLINK("https://shnst.github.io/mycopunk_find_upgrade_layout/", "Original Grid Solver") -> Original Grid Solver
A8: Builds
A9: Amalgam Builds: (by: Sparroh)
A10: =HYPERLINK("https://docs.google.com/spreadsheets/d/1m_Ry_CtkGlNhcsrz4S3AEApCHfT3CU2LwpbUTRCUVMk/edit?usp=sharing", "Amalgam Builds") -> Amalgam Builds
A11: Practical Builds: (by: CarsonSnorlax)
A12: =HYPERLINK("https://docs.google.com/spreadsheets/d/16D7SskcxR_eVl4gwiiJHAC6Uj51Nqve1ip5ZPJP40NQ/edit?gid=1719030345#gid=1719030345", "Practical Builds" ) -> Practical Builds
A13: Tierlists
A14: Weapon Tierlist: (by: CarsonSnorlax)
A15: =HYPERLINK("https://tiermaker.com/create/mycopunk-weapon-tier-list-18711617", "Weapon Tierlist" ) -> Weapon Tierlist
A16: Tierlist Templates:
A17: =HYPERLINK("https://tiermaker.com/user/18796434", "Templates") -> Templates
A18: Secret Resources
A19: Terry's Pumpkins: (by: Cepha)
A20: =HYPERLINK("https://docs.google.com/document/d/1x74JSPX16Tbw6qlqWw2fUTEz1NspO3EHgY0snxRjL-A/edit?usp=sharing", "Autumnation Skin") -> Autumnation Skin
A21: Roachard's Pumpkins: (by: Echodrache)
A22: =HYPERLINK("https://docs.google.com/document/d/1an_F7QhSnxwrNWj1CdlosIHsWi7uj63JofsUJjiHK90/edit?usp=sharing", "Pumpkin Guncrab") -> Pumpkin Guncrab
A23: Globbler Unlock:
A24: =HYPERLINK("https://steamcommunity.com/sharedfiles/filedetails/?id=3523968444", "Globbler") -> Globbler
A25: Carver Unlock:
A26: =HYPERLINK("https://steamcommunity.com/sharedfiles/filedetails/?id=3523943228", "Carver") -> Carver
A27: Pulverizer Unlock:
A28: Prism Unlock:
A29: =HYPERLINK("https://steamcommunity.com/sharedfiles/filedetails/?id=3523943228", "ERROR REDACTED") -> ERROR REDACTED
A30: Gravity Farms Crates:
A31: Gravity Farms Skins:
A32: H.U.B. Upgrades:
A33: Direct all suggestions / errors to @Sparroh in the Mycopunk Discord Mycopunk v1.2

Sheet Hashetty

Sheet Cycler
A1: Icon | B1: Name | C1: Description | D1: Turbocharge | E1: Statistic | F1: Value | G1: Min | H1: Max | I1: Statistic | J1: Value | K1: Min | L1: Max | M1: Statistic | N1: Value | O1: Min | P1: Max | Q1: Statistic | R1: Value | S1: Min | T1: Max | U1: Statistic | V1: Value | W1: Min | X1: Max | Y1: Statistic | Z1: Value | AA1: Min | AB1: Max | AC1: Statistic | AD1: Value | AE1: Min | AF1: Max | AG1: Statistic | AH1: Value | AI1: Min | AJ1: Max | AK1: Statistic | AL1: Value | AM1: Min | AN1: Max | AO1: Size | AP1: Tier
A2: {=_xlfn.XLOOKUP(B2,'Up Icon'!A:A,'Up Icon'!B:B,)} | B2: {=HYPERLINK(_xlfn.XLOOKUP('Up Names'!A38,'Up Wiki'!A:A,'Up Wiki'!B:B,),'Up Names'!A38)} -> Edge Fault | C2: {=_xlfn.XLOOKUP(B2,'Up Desc'!A:A,'Up Desc'!B:B,)} -> Increases the size of your upgrade grid. | D2: {=_xlfn.XLOOKUP(B2,'Up Turbo'!A:A,'Up Turbo'!B:B,)} -> n/a | E2: {=_xlfn.XLOOKUP(B2,'Up Stats'!A:A,'Up Stats'!B:B,)} | F2: =IFERROR(__xludf.DUMMYFUNCTION("if(AND(G2=FALSE,H2=FALSE),,if(G2=H2,JOIN("""",""Static: "",G2),JOIN("""",""Min: "",G2, CHAR(10),""Max: "",H2)))"),"") | G2: {=_xlfn.XLOOKUP(B2,'Up Min'!A:A,'Up Min'!B:B,)} | H2: {=_xlfn.XLOOKUP(B2,'Up Max'!A:A,'Up Max'!B:B,)} | I2: {=_xlfn.XLOOKUP(B2,'Up Stats'!A:A,'Up Stats'!C:C,)} | J2: =IFERROR(__xludf.DUMMYFUNCTION("if(AND(K2=FALSE,L2=FALSE),,if(K2=L2,JOIN("""",""Static: "",K2),JOIN("""",""Min: "",K2, CHAR(10),""Max: "",L2)))"),"") | K2: {=_xlfn.XLOOKUP(B2,'Up Min'!A:A,'Up Min'!C:C,)} | L2: {=_xlfn.XLOOKUP(B2,'Up Max'!A:A,'Up Max'!C:C,)} | M2: {=_xlfn.XLOOKUP(B2,'Up Stats'!A:A,'Up Stats'!D:D,)} | N2: =IFERROR(__xludf.DUMMYFUNCTION("if(AND(O2=FALSE,P2=FALSE),,if(O2=P2,JOIN("""",""Static: "",O2),JOIN("""",""Min: "",O2, CHAR(10),""Max: "",P2)))"),"") | O2: {=_xlfn.XLOOKUP(B2,'Up Min'!A:A,'Up Min'!D:D,)} | P2: {=_xlfn.XLOOKUP(B2,'Up Max'!A:A,'Up Max'!D:D,)} | Q2: {=_xlfn.XLOOKUP(B2,'Up Stats'!A:A,'Up Stats'!E:E,)} | R2: =IFERROR(__xludf.DUMMYFUNCTION("if(AND(S2=FALSE,T2=FALSE),,if(S2=T2,JOIN("""",""Static: "",S2),JOIN("""",""Min: "",S2, CHAR(10),""Max: "",T2)))"),"") | S2: {=_xlfn.XLOOKUP(B2,'Up Min'!A:A,'Up Min'!E:E,)} | T2: {=_xlfn.XLOOKUP(B2,'Up Max'!A:A,'Up Max'!E:E,)} | U2: {=_xlfn.XLOOKUP(B2,'Up Stats'!A:A,'Up Stats'!F:F,)} | V2: =IFERROR(__xludf.DUMMYFUNCTION("if(AND(W2=FALSE,X2=FALSE),,if(W2=X2,JOIN("""",""Static: "",W2),JOIN("""",""Min: "",W2, CHAR(10),""Max: "",X2)))"),"") | W2: {=_xlfn.XLOOKUP(B2,'Up Min'!A:A,'Up Min'!F:F,)} | X2: {=_xlfn.XLOOKUP(B2,'Up Max'!A:A,'Up Max'!F:F,)} | Y2: {=_xlfn.XLOOKUP(B2,'Up Stats'!A:A,'Up Stats'!G:G,)} | Z2: =IFERROR(__xludf.DUMMYFUNCTION("if(AND(AA2=FALSE,AB2=FALSE),,if(AA2=AB2,JOIN("""",""Static: "",AA2),JOIN("""",""Min: "",AA2, CHAR(10),""Max: "",AB2)))"),"") | AA2: {=_xlfn.XLOOKUP(B2,'Up Min'!A:A,'Up Min'!G:G,)} | AB2: {=_xlfn.XLOOKUP(B2,'Up Max'!A:A,'Up Max'!G:G,)} | AC2: {=_xlfn.XLOOKUP(B2,'Up Stats'!A:A,'Up Stats'!H:H,)} | AD2: =IFERROR(__xludf.DUMMYFUNCTION("if(AND(AE2=FALSE,AF2=FALSE),,if(AE2=AF2,JOIN("""",""Static: "",AE2),JOIN("""",""Min: "",AE2, CHAR(10),""Max: "",AF2)))"),"") | AE2: {=_xlfn.XLOOKUP(B2,'Up Min'!A:A,'Up Min'!H:H,)} | AF2: {=_xlfn.XLOOKUP(B2,'Up Max'!A:A,'Up Max'!H:H,)} | AG2: {=_xlfn.XLOOKUP(B2,'Up Stats'!A:A,'Up Stats'!I:I,)} | AH2: =IFERROR(__xludf.DUMMYFUNCTION("if(AND(AI2=FALSE,AJ2=FALSE),,if(AI2=AJ2,JOIN("""",""Static: "",AI2),JOIN("""",""Min: "",AI2, CHAR(10),""Max: "",AJ2)))"),"") | AI2: {=_xlfn.XLOOKUP(B2,'Up Min'!A:A,'Up Min'!I:I,)} | AJ2: {=_xlfn.XLOOKUP(B2,'Up Max'!A:A,'Up Max'!I:I,)} | AK2: {=_xlfn.XLOOKUP(B2,'Up Stats'!A:A,'Up Stats'!J:J,)} | AL2: =IFERROR(__xludf.DUMMYFUNCTION("if(AND(AM2=FALSE,AN2=FALSE),,if(AM2=AN2,JOIN("""",""Static: "",AM2),JOIN("""",""Min: "",AM2, CHAR(10),""Max: "",AN2)))"),"") | AM2: {=_xlfn.XLOOKUP(B2,'Up Min'!A:A,'Up Min'!J:J,)} | AN2: {=_xlfn.XLOOKUP(B2,'Up Max'!A:A,'Up Max'!J:J,)} | AO2: {=CONCATENATE(_xlfn.XLOOKUP(B2,'Up Cells'!A:A,'Up Cells'!B:B,))} -> 1 | AP2: {=CONCATENATE(_xlfn.XLOOKUP(B2,'Up Rarity'!A:A,'Up Rarity'!B:B,),CHAR(10),"-")} -> Contraband -
A3: {=_xlfn.XLOOKUP(B3,'Up Icon'!A:A,'Up Icon'!B:B,)} | B3: {=HYPERLINK(_xlfn.XLOOKUP('Up Names'!A39,'Up Wiki'!A:A,'Up Wiki'!B:B,),'Up Names'!A39)} -> Multiversal Thievery | C3: {=_xlfn.XLOOKUP(B3,'Up Desc'!A:A,'Up Desc'!B:B,)} -> Commandeers 1 column from each of your other upgrade grids. | D3: {=_xlfn.XLOOKUP(B3,'Up Turbo'!A:A,'Up Turbo'!B:B,)} -> n/a | E3: {=_xlfn.XLOOKUP(B3,'Up Stats'!A:A,'Up Stats'!B:B,)} | F3: =IFERROR(__xludf.DUMMYFUNCTION("if(AND(G3=FALSE,H3=FALSE),,if(G3=H3,JOIN("""",""Static: "",G3),JOIN("""",""Min: "",G3, CHAR(10),""Max: "",H3)))"),"") | G3: {=_xlfn.XLOOKUP(B3,'Up Min'!A:A,'Up Min'!B:B,)} | H3: {=_xlfn.XLOOKUP(B3,'Up Max'!A:A,'Up Max'!B:B,)} | I3: {=_xlfn.XLOOKUP(B3,'Up Stats'!A:A,'Up Stats'!C:C,)} | J3: =IFERROR(__xludf.DUMMYFUNCTION("if(AND(K3=FALSE,L3=FALSE),,if(K3=L3,JOIN("""",""Static: "",K3),JOIN("""",""Min: "",K3, CHAR(10),""Max: "",L3)))"),"") | K3: {=_xlfn.XLOOKUP(B3,'Up Min'!A:A,'Up Min'!C:C,)} | L3: {=_xlfn.XLOOKUP(B3,'Up Max'!A:A,'Up Max'!C:C,)} | M3: {=_xlfn.XLOOKUP(B3,'Up Stats'!A:A,'Up Stats'!D:D,)} | N3: =IFERROR(__xludf.DUMMYFUNCTION("if(AND(O3=FALSE,P3=FALSE),,if(O3=P3,JOIN("""",""Static: "",O3),JOIN("""",""Min: "",O3, CHAR(10),""Max: "",P3)))"),"") | O3: {=_xlfn.XLOOKUP(B3,'Up Min'!A:A,'Up Min'!D:D,)} | P3: {=_xlfn.XLOOKUP(B3,'Up Max'!A:A,'Up Max'!D:D,)} | Q3: {=_xlfn.XLOOKUP(B3,'Up Stats'!A:A,'Up Stats'!E:E,)} | R3: =IFERROR(__xludf.DUMMYFUNCTION("if(AND(S3=FALSE,T3=FALSE),,if(S3=T3,JOIN("""",""Static: "",S3),JOIN("""",""Min: "",S3, CHAR(10),""Max: "",T3)))"),"") | S3: {=_xlfn.XLOOKUP(B3,'Up Min'!A:A,'Up Min'!E:E,)} | T3: {=_xlfn.XLOOKUP(B3,'Up Max'!A:A,'Up Max'!E:E,)} | U3: {=_xlfn.XLOOKUP(B3,'Up Stats'!A:A,'Up Stats'!F:F,)} | V3: =IFERROR(__xludf.DUMMYFUNCTION("if(AND(W3=FALSE,X3=FALSE),,if(W3=X3,JOIN("""",""Static: "",W3),JOIN("""",""Min: "",W3, CHAR(10),""Max: "",X3)))"),"") | W3: {=_xlfn.XLOOKUP(B3,'Up Min'!A:A,'Up Min'!F:F,)} | X3: {=_xlfn.XLOOKUP(B3,'Up Max'!A:A,'Up Max'!F:F,)} | Y3: {=_xlfn.XLOOKUP(B3,'Up Stats'!A:A,'Up Stats'!G:G,)} | Z3: =IFERROR(__xludf.DUMMYFUNCTION("if(AND(AA3=FALSE,AB3=FALSE),,if(AA3=AB3,JOIN("""",""Static: "",AA3),JOIN("""",""Min: "",AA3, CHAR(10),""Max: "",AB3)))"),"") | AA3: {=_xlfn.XLOOKUP(B3,'Up Min'!A:A,'Up Min'!G:G,)} | AB3: {=_xlfn.XLOOKUP(B3,'Up Max'!A:A,'Up Max'!G:G,)} | AC3: {=_xlfn.XLOOKUP(B3,'Up Stats'!A:A,'Up Stats'!H:H,)} | AD3: =IFERROR(__xludf.DUMMYFUNCTION("if(AND(AE3=FALSE,AF3=FALSE),,if(AE3=AF3,JOIN("""",""Static: "",AE3),JOIN("""",""Min: "",AE3, CHAR(10),""Max: "",AF3)))"),"") | AE3: {=_xlfn.XLOOKUP(B3,'Up Min'!A:A,'Up Min'!H:H,)} | AF3: {=_xlfn.XLOOKUP(B3,'Up Max'!A:A,'Up Max'!H:H,)} | AG3: {=_xlfn.XLOOKUP(B3,'Up Stats'!A:A,'Up Stats'!I:I,)} | AH3: =IFERROR(__xludf.DUMMYFUNCTION("if(AND(AI3=FALSE,AJ3=FALSE),,if(AI3=AJ3,JOIN("""",""Static: "",AI3),JOIN("""",""Min: "",AI3, CHAR(10),""Max: "",AJ3)))"),"") | AI3: {=_xlfn.XLOOKUP(B3,'Up Min'!A:A,'Up Min'!I:I,)} | AJ3: {=_xlfn.XLOOKUP(B3,'Up Max'!A:A,'Up Max'!I:I,)} | AK3: {=_xlfn.XLOOKUP(B3,'Up Stats'!A:A,'Up Stats'!J:J,)} | AL3: =IFERROR(__xludf.DUMMYFUNCTION("if(AND(AM3=FALSE,AN3=FALSE),,if(AM3=AN3,JOIN("""",""Static: "",AM3),JOIN("""",""Min: "",AM3, CHAR(10),""Max: "",AN3)))"),"") | AM3: {=_xlfn.XLOOKUP(B3,'Up Min'!A:A,'Up Min'!J:J,)} | AN3: {=_xlfn.XLOOKUP(B3,'Up Max'!A:A,'Up Max'!J:J,)} | AO3: {=CONCATENATE(_xlfn.XLOOKUP(B3,'Up Cells'!A:A,'Up Cells'!B:B,))} -> 1 | AP3: {=CONCATENATE(_xlfn.XLOOKUP(B3,'Up Rarity'!A:A,'Up Rarity'!B:B,),CHAR(10),"-")} -> Contraband -
A4: {=_xlfn.XLOOKUP(B4,'Up Icon'!A:A,'Up Icon'!B:B,)} | B4: {=HYPERLINK(_xlfn.XLOOKUP('Up Names'!A40,'Up Wiki'!A:A,'Up Wiki'!B:B,),'Up Names'!A40)} -> Boundary Incursion | C4: {=_xlfn.XLOOKUP(B4,'Up Desc'!A:A,'Up Desc'!B:B,)} -> Increases the size of your upgrade grid. | D4: {=_xlfn.XLOOKUP(B4,'Up Turbo'!A:A,'Up Turbo'!B:B,)} -> n/a | E4: {=_xlfn.XLOOKUP(B4,'Up Stats'!A:A,'Up Stats'!B:B,)} | F4: =IFERROR(__xludf.DUMMYFUNCTION("if(AND(G4=FALSE,H4=FALSE),,if(G4=H4,JOIN("""",""Static: "",G4),JOIN("""",""Min: "",G4, CHAR(10),""Max: "",H4)))"),"") | G4: {=_xlfn.XLOOKUP(B4,'Up Min'!A:A,'Up Min'!B:B,)} | H4: {=_xlfn.XLOOKUP(B4,'Up Max'!A:A,'Up Max'!B:B,)} | I4: {=_xlfn.XLOOKUP(B4,'Up Stats'!A:A,'Up Stats'!C:C,)} | J4: =IFERROR(__xludf.DUMMYFUNCTION("if(AND(K4=FALSE,L4=FALSE),,if(K4=L4,JOIN("""",""Static: "",K4),JOIN("""",""Min: "",K4, CHAR(10),""Max: "",L4)))"),"") | K4: {=_xlfn.XLOOKUP(B4,'Up Min'!A:A,'Up Min'!C:C,)} | L4: {=_xlfn.XLOOKUP(B4,'Up Max'!A:A,'Up Max'!C:C,)} | M4: {=_xlfn.XLOOKUP(B4,'Up Stats'!A:A,'Up Stats'!D:D,)} | N4: =IFERROR(__xludf.DUMMYFUNCTION("if(AND(O4=FALSE,P4=FALSE),,if(O4=P4,JOIN("""",""Static: "",O4),JOIN("""",""Min: "",O4, CHAR(10),""Max: "",P4)))"),"") | O4: {=_xlfn.XLOOKUP(B4,'Up Min'!A:A,'Up Min'!D:D,)} | P4: {=_xlfn.XLOOKUP(B4,'Up Max'!A:A,'Up Max'!D:D,)} | Q4: {=_xlfn.XLOOKUP(B4,'Up Stats'!A:A,'Up Stats'!E:E,)} | R4: =IFERROR(__xludf.DUMMYFUNCTION("if(AND(S4=FALSE,T4=FALSE),,if(S4=T4,JOIN("""",""Static: "",S4),JOIN("""",""Min: "",S4, CHAR(10),""Max: "",T4)))"),"") | S4: {=_xlfn.XLOOKUP(B4,'Up Min'!A:A,'Up Min'!E:E,)} | T4: {=_xlfn.XLOOKUP(B4,'Up Max'!A:A,'Up Max'!E:E,)} | U4: {=_xlfn.XLOOKUP(B4,'Up Stats'!A:A,'Up Stats'!F:F,)} | V4: =IFERROR(__xludf.DUMMYFUNCTION("if(AND(W4=FALSE,X4=FALSE),,if(W4=X4,JOIN("""",""Static: "",W4),JOIN("""",""Min: "",W4, CHAR(10),""Max: "",X4)))"),"") | W4: {=_xlfn.XLOOKUP(B4,'Up Min'!A:A,'Up Min'!F:F,)} | X4: {=_xlfn.XLOOKUP(B4,'Up Max'!A:A,'Up Max'!F:F,)} | Y4: {=_xlfn.XLOOKUP(B4,'Up Stats'!A:A,'Up Stats'!G:G,)} | Z4: =IFERROR(__xludf.DUMMYFUNCTION("if(AND(AA4=FALSE,AB4=FALSE),,if(AA4=AB4,JOIN("""",""Static: "",AA4),JOIN("""",""Min: "",AA4, CHAR(10),""Max: "",AB4)))"),"") | AA4: {=_xlfn.XLOOKUP(B4,'Up Min'!A:A,'Up Min'!G:G,)} | AB4: {=_xlfn.XLOOKUP(B4,'Up Max'!A:A,'Up Max'!G:G,)} | AC4: {=_xlfn.XLOOKUP(B4,'Up Stats'!A:A,'Up Stats'!H:H,)} | AD4: =IFERROR(__xludf.DUMMYFUNCTION("if(AND(AE4=FALSE,AF4=FALSE),,if(AE4=AF4,JOIN("""",""Static: "",AE4),JOIN("""",""Min: "",AE4, CHAR(10),""Max: "",AF4)))"),"") | AE4: {=_xlfn.XLOOKUP(B4,'Up Min'!A:A,'Up Min'!H:H,)} | AF4: {=_xlfn.XLOOKUP(B4,'Up Max'!A:A,'Up Max'!H:H,)} | AG4: {=_xlfn.XLOOKUP(B4,'Up Stats'!A:A,'Up Stats'!I:I,)} | AH4: =IFERROR(__xludf.DUMMYFUNCTION("if(AND(AI4=FALSE,AJ4=FALSE),,if(AI4=AJ4,JOIN("""",""Static: "",AI4),JOIN("""",""Min: "",AI4, CHAR(10),""Max: "",AJ4)))"),"") | AI4: {=_xlfn.XLOOKUP(B4,'Up Min'!A:A,'Up Min'!I:I,)} | AJ4: {=_xlfn.XLOOKUP(B4,'Up Max'!A:A,'Up Max'!I:I,)} | AK4: {=_xlfn.XLOOKUP(B4,'Up Stats'!A:A,'Up Stats'!J:J,)} | AL4: =IFERROR(__xludf.DUMMYFUNCTION("if(AND(AM4=FALSE,AN4=FALSE),,if(AM4=AN4,JOIN("""",""Static: "",AM4),JOIN("""",""Min: "",AM4, CHAR(10),""Max: "",AN4)))"),"") | AM4: {=_xlfn.XLOOKUP(B4,'Up Min'!A:A,'Up Min'!J:J,)} | AN4: {=_xlfn.XLOOKUP(B4,'Up Max'!A:A,'Up Max'!J:J,)} | AO4: {=CONCATENATE(_xlfn.XLOOKUP(B4,'Up Cells'!A:A,'Up Cells'!B:B,))} -> 1 | AP4: {=CONCATENATE(_xlfn.XLOOKUP(B4,'Up Rarity'!A:A,'Up Rarity'!B:B,),CHAR(10),"-")} -> Oddity -
A5: {=_xlfn.XLOOKUP(B5,'Up Icon'!A:A,'Up Icon'!B:B,)} | B5: {=HYPERLINK(_xlfn.XLOOKUP('Up Names'!A2,'Up Wiki'!A:A,'Up Wiki'!B:B,),'Up Names'!A2)} -> Corrode Siphon | C5: {=_xlfn.XLOOKUP(B5,'Up Desc'!A:A,'Up Desc'!B:B,)} -> Enemies you corrode with any weapon have a chance to return ammo to the magazine over time. | D5: {=_xlfn.XLOOKUP(B5,'Up Turbo'!A:A,'Up Turbo'!B:B,)} | E5: {=_xlfn.XLOOKUP(B5,'Up Stats'!A:A,'Up Stats'!B:B,)} -> Chance | F5: =IFERROR(__xludf.DUMMYFUNCTION("if(AND(G5=FALSE,H5=FALSE),,if(G5=H5,JOIN("""",""Static: "",G5),JOIN("""",""Min: "",G5, CHAR(10),""Max: "",H5)))"),"Min: 18% Max: 24%") -> Min: 18% Max: 24% | G5: {=_xlfn.XLOOKUP(B5,'Up Min'!A:A,'Up Min'!B:B,)} -> 0.18 | H5: {=_xlfn.XLOOKUP(B5,'Up Max'!A:A,'Up Max'!B:B,)} -> 0.24 | I5: {=_xlfn.XLOOKUP(B5,'Up Stats'!A:A,'Up Stats'!C:C,)} -> Ammo Refunded | J5: =IFERROR(__xludf.DUMMYFUNCTION("if(AND(K5=FALSE,L5=FALSE),,if(K5=L5,JOIN("""",""Static: "",K5),JOIN("""",""Min: "",K5, CHAR(10),""Max: "",L5)))"),"Static: 3") -> Static: 3 | K5: {=_xlfn.XLOOKUP(B5,'Up Min'!A:A,'Up Min'!C:C,)} -> 3 | L5: {=_xlfn.XLOOKUP(B5,'Up Max'!A:A,'Up Max'!C:C,)} -> 3 | M5: {=_xlfn.XLOOKUP(B5,'Up Stats'!A:A,'Up Stats'!D:D,)} | N5: =IFERROR(__xludf.DUMMYFUNCTION("if(AND(O5=FALSE,P5=FALSE),,if(O5=P5,JOIN("""",""Static: "",O5),JOIN("""",""Min: "",O5, CHAR(10),""Max: "",P5)))"),"") | O5: {=_xlfn.XLOOKUP(B5,'Up Min'!A:A,'Up Min'!D:D,)} | P5: {=_xlfn.XLOOKUP(B5,'Up Max'!A:A,'Up Max'!D:D,)} | Q5: {=_xlfn.XLOOKUP(B5,'Up Stats'!A:A,'Up Stats'!E:E,)} | R5: =IFERROR(__xludf.DUMMYFUNCTION("if(AND(S5=FALSE,T5=FALSE),,if(S5=T5,JOIN("""",""Static: "",S5),JOIN("""",""Min: "",S5, CHAR(10),""Max: "",T5)))"),"") | S5: {=_xlfn.XLOOKUP(B5,'Up Min'!A:A,'Up Min'!E:E,)} | T5: {=_xlfn.XLOOKUP(B5,'Up Max'!A:A,'Up Max'!E:E,)} | U5: {=_xlfn.XLOOKUP(B5,'Up Stats'!A:A,'Up Stats'!F:F,)} | V5: =IFERROR(__xludf.DUMMYFUNCTION("if(AND(W5=FALSE,X5=FALSE),,if(W5=X5,JOIN("""",""Static: "",W5),JOIN("""",""Min: "",W5, CHAR(10),""Max: "",X5)))"),"") | W5: {=_xlfn.XLOOKUP(B5,'Up Min'!A:A,'Up Min'!F:F,)} | X5: {=_xlfn.XLOOKUP(B5,'Up Max'!A:A,'Up Max'!F:F,)} | Y5: {=_xlfn.XLOOKUP(B5,'Up Stats'!A:A,'Up Stats'!G:G,)} | Z5: =IFERROR(__xludf.DUMMYFUNCTION("if(AND(AA5=FALSE,AB5=FALSE),,if(AA5=AB5,JOIN("""",""Static: "",AA5),JOIN("""",""Min: "",AA5, CHAR(10),""Max: "",AB5)))"),"") | AA5: {=_xlfn.XLOOKUP(B5,'Up Min'!A:A,'Up Min'!G:G,)} | AB5: {=_xlfn.XLOOKUP(B5,'Up Max'!A:A,'Up Max'!G:G,)} | AC5: {=_xlfn.XLOOKUP(B5,'Up Stats'!A:A,'Up Stats'!H:H,)} | AD5: =IFERROR(__xludf.DUMMYFUNCTION("if(AND(AE5=FALSE,AF5=FALSE),,if(AE5=AF5,JOIN("""",""Static: "",AE5),JOIN("""",""Min: "",AE5, CHAR(10),""Max: "",AF5)))"),"") | AE5: {=_xlfn.XLOOKUP(B5,'Up Min'!A:A,'Up Min'!H:H,)} | AF5: {=_xlfn.XLOOKUP(B5,'Up Max'!A:A,'Up Max'!H:H,)} | AG5: {=_xlfn.XLOOKUP(B5,'Up Stats'!A:A,'Up Stats'!I:I,)} | AH5: =IFERROR(__xludf.DUMMYFUNCTION("if(AND(AI5=FALSE,AJ5=FALSE),,if(AI5=AJ5,JOIN("""",""Static: "",AI5),JOIN("""",""Min: "",AI5, CHAR(10),""Max: "",AJ5)))"),"") | AI5: {=_xlfn.XLOOKUP(B5,'Up Min'!A:A,'Up Min'!I:I,)} | AJ5: {=_xlfn.XLOOKUP(B5,'Up Max'!A:A,'Up Max'!I:I,)} | AK5: {=_xlfn.XLOOKUP(B5,'Up Stats'!A:A,'Up Stats'!J:J,)} | AL5: =IFERROR(__xludf.DUMMYFUNCTION("if(AND(AM5=FALSE,AN5=FALSE),,if(AM5=AN5,JOIN("""",""Static: "",AM5),JOIN("""",""Min: "",AM5, CHAR(10),""Max: "",AN5)))"),"") | AM5: {=_xlfn.XLOOKUP(B5,'Up Min'!A:A,'Up Min'!J:J,)} | AN5: {=_xlfn.XLOOKUP(B5,'Up Max'!A:A,'Up Max'!J:J,)} | AO5: {=CONCATENATE(_xlfn.XLOOKUP(B5,'Up Cells'!A:A,'Up Cells'!B:B,))} -> 6 | AP5: {=CONCATENATE(_xlfn.XLOOKUP(B5,'Up Rarity'!A:A,'Up Rarity'!B:B,),CHAR(10),"-")} -> Exotic -
A6: {=_xlfn.XLOOKUP(B6,'Up Icon'!A:A,'Up Icon'!B:B,)} | B6: {=HYPERLINK(_xlfn.XLOOKUP('Up Names'!A3,'Up Wiki'!A:A,'Up Wiki'!B:B,),'Up Names'!A3)} -> Infinity Burn | C6: {=_xlfn.XLOOKUP(B6,'Up Desc'!A:A,'Up Desc'!B:B,)} -> Gain infinite ammo. Sustained fire damages you according to this gun's element. | D6: {=_xlfn.XLOOKUP(B6,'Up Turbo'!A:A,'Up Turbo'!B:B,)} | E6: {=_xlfn.XLOOKUP(B6,'Up Stats'!A:A,'Up Stats'!B:B,)} -> Damage Threshold | F6: =IFERROR(__xludf.DUMMYFUNCTION("if(AND(G6=FALSE,H6=FALSE),,if(G6=H6,JOIN("""",""Static: "",G6),JOIN("""",""Min: "",G6, CHAR(10),""Max: "",H6)))"),"Min: 32 Max: 45") -> Min: 32 Max: 45 | G6: {=_xlfn.XLOOKUP(B6,'Up Min'!A:A,'Up Min'!B:B,)} -> 32 | H6: {=_xlfn.XLOOKUP(B6,'Up Max'!A:A,'Up Max'!B:B,)} -> 45 | I6: {=_xlfn.XLOOKUP(B6,'Up Stats'!A:A,'Up Stats'!C:C,)} -> Damage | J6: =IFERROR(__xludf.DUMMYFUNCTION("if(AND(K6=FALSE,L6=FALSE),,if(K6=L6,JOIN("""",""Static: "",K6),JOIN("""",""Min: "",K6, CHAR(10),""Max: "",L6)))"),"Min: 1.76 Max: 2.24") -> Min: 1.76 Max: 2.24 | K6: {=_xlfn.XLOOKUP(B6,'Up Min'!A:A,'Up Min'!C:C,)} -> 1.76 | L6: {=_xlfn.XLOOKUP(B6,'Up Max'!A:A,'Up Max'!C:C,)} -> 2.24 | M6: {=_xlfn.XLOOKUP(B6,'Up Stats'!A:A,'Up Stats'!D:D,)} -> Element | N6: =IFERROR(__xludf.DUMMYFUNCTION("if(AND(O6=FALSE,P6=FALSE),,if(O6=P6,JOIN("""",""Static: "",O6),JOIN("""",""Min: "",O6, CHAR(10),""Max: "",P6)))"),"Min: 0.44 Max: 0.8") -> Min: 0.44 Max: 0.8 | O6: {=_xlfn.XLOOKUP(B6,'Up Min'!A:A,'Up Min'!D:D,)} -> 0.44 | P6: {=_xlfn.XLOOKUP(B6,'Up Max'!A:A,'Up Max'!D:D,)} -> 0.8 | Q6: {=_xlfn.XLOOKUP(B6,'Up Stats'!A:A,'Up Stats'!E:E,)} | R6: =IFERROR(__xludf.DUMMYFUNCTION("if(AND(S6=FALSE,T6=FALSE),,if(S6=T6,JOIN("""",""Static: "",S6),JOIN("""",""Min: "",S6, CHAR(10),""Max: "",T6)))"),"") | S6: {=_xlfn.XLOOKUP(B6,'Up Min'!A:A,'Up Min'!E:E,)} | T6: {=_xlfn.XLOOKUP(B6,'Up Max'!A:A,'Up Max'!E:E,)} | U6: {=_xlfn.XLOOKUP(B6,'Up Stats'!A:A,'Up Stats'!F:F,)} | V6: =IFERROR(__xludf.DUMMYFUNCTION("if(AND(W6=FALSE,X6=FALSE),,if(W6=X6,JOIN("""",""Static: "",W6),JOIN("""",""Min: "",W6, CHAR(10),""Max: "",X6)))"),"") | W6: {=_xlfn.XLOOKUP(B6,'Up Min'!A:A,'Up Min'!F:F,)} | X6: {=_xlfn.XLOOKUP(B6,'Up Max'!A:A,'Up Max'!F:F,)} | Y6: {=_xlfn.XLOOKUP(B6,'Up Stats'!A:A,'Up Stats'!G:G,)} | Z6: =IFERROR(__xludf.DUMMYFUNCTION("if(AND(AA6=FALSE,AB6=FALSE),,if(AA6=AB6,JOIN("""",""Static: "",AA6),JOIN("""",""Min: "",AA6, CHAR(10),""Max: "",AB6)))"),"") | AA6: {=_xlfn.XLOOKUP(B6,'Up Min'!A:A,'Up Min'!G:G,)} | AB6: {=_xlfn.XLOOKUP(B6,'Up Max'!A:A,'Up Max'!G:G,)} | AC6: {=_xlfn.XLOOKUP(B6,'Up Stats'!A:A,'Up Stats'!H:H,)} | AD6: =IFERROR(__xludf.DUMMYFUNCTION("if(AND(AE6=FALSE,AF6=FALSE),,if(AE6=AF6,JOIN("""",""Static: "",AE6),JOIN("""",""Min: "",AE6, CHAR(10),""Max: "",AF6)))"),"") | AE6: {=_xlfn.XLOOKUP(B6,'Up Min'!A:A,'Up Min'!H:H,)} | AF6: {=_xlfn.XLOOKUP(B6,'Up Max'!A:A,'Up Max'!H:H,)} | AG6: {=_xlfn.XLOOKUP(B6,'Up Stats'!A:A,'Up Stats'!I:I,)} | AH6: =IFERROR(__xludf.DUMMYFUNCTION("if(AND(AI6=FALSE,AJ6=FALSE),,if(AI6=AJ6,JOIN("""",""Static: "",AI6),JOIN("""",""Min: "",AI6, CHAR(10),""Max: "",AJ6)))"),"") | AI6: {=_xlfn.XLOOKUP(B6,'Up Min'!A:A,'Up Min'!I:I,)} | AJ6: {=_xlfn.XLOOKUP(B6,'Up Max'!A:A,'Up Max'!I:I,)} | AK6: {=_xlfn.XLOOKUP(B6,'Up Stats'!A:A,'Up Stats'!J:J,)} | AL6: =IFERROR(__xludf.DUMMYFUNCTION("if(AND(AM6=FALSE,AN6=FALSE),,if(AM6=AN6,JOIN("""",""Static: "",AM6),JOIN("""",""Min: "",AM6, CHAR(10),""Max: "",AN6)))"),"") | AM6: {=_xlfn.XLOOKUP(B6,'Up Min'!A:A,'Up Min'!J:J,)} | AN6: {=_xlfn.XLOOKUP(B6,'Up Max'!A:A,'Up Max'!J:J,)} | AO6: {=CONCATENATE(_xlfn.XLOOKUP(B6,'Up Cells'!A:A,'Up Cells'!B:B,))} -> 10 | AP6: {=CONCATENATE(_xlfn.XLOOKUP(B6,'Up Rarity'!A:A,'Up Rarity'!B:B,),CHAR(10),"-")} -> Exotic -
A7: {=_xlfn.XLOOKUP(B7,'Up Icon'!A:A,'Up Icon'!B:B,)} | B7: {=HYPERLINK(_xlfn.XLOOKUP('Up Names'!A4,'Up Wiki'!A:A,'Up Wiki'!B:B,),'Up Names'!A4)} -> Scorching Detonation | C7: {=_xlfn.XLOOKUP(B7,'Up Desc'!A:A,'Up Desc'!B:B,)} -> Killing an ignited target causes it to explode. | D7: {=_xlfn.XLOOKUP(B7,'Up Turbo'!A:A,'Up Turbo'!B:B,)} | E7: {=_xlfn.XLOOKUP(B7,'Up Stats'!A:A,'Up Stats'!B:B,)} -> Size | F7: =IFERROR(__xludf.DUMMYFUNCTION("if(AND(G7=FALSE,H7=FALSE),,if(G7=H7,JOIN("""",""Static: "",G7),JOIN("""",""Min: "",G7, CHAR(10),""Max: "",H7)))"),"Min: 3.6 Max: 4.22") -> Min: 3.6 Max: 4.22 | G7: {=_xlfn.XLOOKUP(B7,'Up Min'!A:A,'Up Min'!B:B,)} -> 3.6 | H7: {=_xlfn.XLOOKUP(B7,'Up Max'!A:A,'Up Max'!B:B,)} -> 4.22 | I7: {=_xlfn.XLOOKUP(B7,'Up Stats'!A:A,'Up Stats'!C:C,)} -> Damage | J7: =IFERROR(__xludf.DUMMYFUNCTION("if(AND(K7=FALSE,L7=FALSE),,if(K7=L7,JOIN("""",""Static: "",K7),JOIN("""",""Min: "",K7, CHAR(10),""Max: "",L7)))"),"Min: 37.5 Max: 49.5") -> Min: 37.5 Max: 49.5 | K7: {=_xlfn.XLOOKUP(B7,'Up Min'!A:A,'Up Min'!C:C,)} -> 37.5 | L7: {=_xlfn.XLOOKUP(B7,'Up Max'!A:A,'Up Max'!C:C,)} -> 49.5 | M7: {=_xlfn.XLOOKUP(B7,'Up Stats'!A:A,'Up Stats'!D:D,)} | N7: =IFERROR(__xludf.DUMMYFUNCTION("if(AND(O7=FALSE,P7=FALSE),,if(O7=P7,JOIN("""",""Static: "",O7),JOIN("""",""Min: "",O7, CHAR(10),""Max: "",P7)))"),"") | O7: {=_xlfn.XLOOKUP(B7,'Up Min'!A:A,'Up Min'!D:D,)} | P7: {=_xlfn.XLOOKUP(B7,'Up Max'!A:A,'Up Max'!D:D,)} | Q7: {=_xlfn.XLOOKUP(B7,'Up Stats'!A:A,'Up Stats'!E:E,)} | R7: =IFERROR(__xludf.DUMMYFUNCTION("if(AND(S7=FALSE,T7=FALSE),,if(S7=T7,JOIN("""",""Static: "",S7),JOIN("""",""Min: "",S7, CHAR(10),""Max: "",T7)))"),"") | S7: {=_xlfn.XLOOKUP(B7,'Up Min'!A:A,'Up Min'!E:E,)} | T7: {=_xlfn.XLOOKUP(B7,'Up Max'!A:A,'Up Max'!E:E,)} | U7: {=_xlfn.XLOOKUP(B7,'Up Stats'!A:A,'Up Stats'!F:F,)} | V7: =IFERROR(__xludf.DUMMYFUNCTION("if(AND(W7=FALSE,X7=FALSE),,if(W7=X7,JOIN("""",""Static: "",W7),JOIN("""",""Min: "",W7, CHAR(10),""Max: "",X7)))"),"") | W7: {=_xlfn.XLOOKUP(B7,'Up Min'!A:A,'Up Min'!F:F,)} | X7: {=_xlfn.XLOOKUP(B7,'Up Max'!A:A,'Up Max'!F:F,)} | Y7: {=_xlfn.XLOOKUP(B7,'Up Stats'!A:A,'Up Stats'!G:G,)} | Z7: =IFERROR(__xludf.DUMMYFUNCTION("if(AND(AA7=FALSE,AB7=FALSE),,if(AA7=AB7,JOIN("""",""Static: "",AA7),JOIN("""",""Min: "",AA7, CHAR(10),""Max: "",AB7)))"),"") | AA7: {=_xlfn.XLOOKUP(B7,'Up Min'!A:A,'Up Min'!G:G,)} | AB7: {=_xlfn.XLOOKUP(B7,'Up Max'!A:A,'Up Max'!G:G,)} | AC7: {=_xlfn.XLOOKUP(B7,'Up Stats'!A:A,'Up Stats'!H:H,)} | AD7: =IFERROR(__xludf.DUMMYFUNCTION("if(AND(AE7=FALSE,AF7=FALSE),,if(AE7=AF7,JOIN("""",""Static: "",AE7),JOIN("""",""Min: "",AE7, CHAR(10),""Max: "",AF7)))"),"") | AE7: {=_xlfn.XLOOKUP(B7,'Up Min'!A:A,'Up Min'!H:H,)} | AF7: {=_xlfn.XLOOKUP(B7,'Up Max'!A:A,'Up Max'!H:H,)} | AG7: {=_xlfn.XLOOKUP(B7,'Up Stats'!A:A,'Up Stats'!I:I,)} | AH7: =IFERROR(__xludf.DUMMYFUNCTION("if(AND(AI7=FALSE,AJ7=FALSE),,if(AI7=AJ7,JOIN("""",""Static: "",AI7),JOIN("""",""Min: "",AI7, CHAR(10),""Max: "",AJ7)))"),"") | AI7: {=_xlfn.XLOOKUP(B7,'Up Min'!A:A,'Up Min'!I:I,)} | AJ7: {=_xlfn.XLOOKUP(B7,'Up Max'!A:A,'Up Max'!I:I,)} | AK7: {=_xlfn.XLOOKUP(B7,'Up Stats'!A:A,'Up Stats'!J:J,)} | AL7: =IFERROR(__xludf.DUMMYFUNCTION("if(AND(AM7=FALSE,AN7=FALSE),,if(AM7=AN7,JOIN("""",""Static: "",AM7),JOIN("""",""Min: "",AM7, CHAR(10),""Max: "",AN7)))"),"") | AM7: {=_xlfn.XLOOKUP(B7,'Up Min'!A:A,'Up Min'!J:J,)} | AN7: {=_xlfn.XLOOKUP(B7,'Up Max'!A:A,'Up Max'!J:J,)} | AO7: {=CONCATENATE(_xlfn.XLOOKUP(B7,'Up Cells'!A:A,'Up Cells'!B:B,))} -> 7 | AP7: {=CONCATENATE(_xlfn.XLOOKUP(B7,'Up Rarity'!A:A,'Up Rarity'!B:B,),CHAR(10),"-")} -> Exotic -
A8: {=_xlfn.XLOOKUP(B8,'Up Icon'!A:A,'Up Icon'!B:B,)} | B8: {=HYPERLINK(_xlfn.XLOOKUP('Up Names'!A5,'Up Wiki'!A:A,'Up Wiki'!B:B,),'Up Names'!A5)} -> Shock Recursion | C8: {=_xlfn.XLOOKUP(B8,'Up Desc'!A:A,'Up Desc'!B:B,)} -> Electrocuting a target returns ammo to the magazine. | D8: {=_xlfn.XLOOKUP(B8,'Up Turbo'!A:A,'Up Turbo'!B:B,)} | E8: {=_xlfn.XLOOKUP(B8,'Up Stats'!A:A,'Up Stats'!B:B,)} -> Ammo Refunded | F8: =IFERROR(__xludf.DUMMYFUNCTION("if(AND(G8=FALSE,H8=FALSE),,if(G8=H8,JOIN("""",""Static: "",G8),JOIN("""",""Min: "",G8, CHAR(10),""Max: "",H8)))"),"Min: 8 Max: 23") -> Min: 8 Max: 23 | G8: {=_xlfn.XLOOKUP(B8,'Up Min'!A:A,'Up Min'!B:B,)} -> 8 | H8: {=_xlfn.XLOOKUP(B8,'Up Max'!A:A,'Up Max'!B:B,)} -> 23 | I8: {=_xlfn.XLOOKUP(B8,'Up Stats'!A:A,'Up Stats'!C:C,)} | J8: =IFERROR(__xludf.DUMMYFUNCTION("if(AND(K8=FALSE,L8=FALSE),,if(K8=L8,JOIN("""",""Static: "",K8),JOIN("""",""Min: "",K8, CHAR(10),""Max: "",L8)))"),"") | K8: {=_xlfn.XLOOKUP(B8,'Up Min'!A:A,'Up Min'!C:C,)} | L8: {=_xlfn.XLOOKUP(B8,'Up Max'!A:A,'Up Max'!C:C,)} | M8: {=_xlfn.XLOOKUP(B8,'Up Stats'!A:A,'Up Stats'!D:D,)} | N8: =IFERROR(__xludf.DUMMYFUNCTION("if(AND(O8=FALSE,P8=FALSE),,if(O8=P8,JOIN("""",""Static: "",O8),JOIN("""",""Min: "",O8, CHAR(10),""Max: "",P8)))"),"") | O8: {=_xlfn.XLOOKUP(B8,'Up Min'!A:A,'Up Min'!D:D,)} | P8: {=_xlfn.XLOOKUP(B8,'Up Max'!A:A,'Up Max'!D:D,)} | Q8: {=_xlfn.XLOOKUP(B8,'Up Stats'!A:A,'Up Stats'!E:E,)} | R8: =IFERROR(__xludf.DUMMYFUNCTION("if(AND(S8=FALSE,T8=FALSE),,if(S8=T8,JOIN("""",""Static: "",S8),JOIN("""",""Min: "",S8, CHAR(10),""Max: "",T8)))"),"") | S8: {=_xlfn.XLOOKUP(B8,'Up Min'!A:A,'Up Min'!E:E,)} | T8: {=_xlfn.XLOOKUP(B8,'Up Max'!A:A,'Up Max'!E:E,)} | U8: {=_xlfn.XLOOKUP(B8,'Up Stats'!A:A,'Up Stats'!F:F,)} | V8: =IFERROR(__xludf.DUMMYFUNCTION("if(AND(W8=FALSE,X8=FALSE),,if(W8=X8,JOIN("""",""Static: "",W8),JOIN("""",""Min: "",W8, CHAR(10),""Max: "",X8)))"),"") | W8: {=_xlfn.XLOOKUP(B8,'Up Min'!A:A,'Up Min'!F:F,)} | X8: {=_xlfn.XLOOKUP(B8,'Up Max'!A:A,'Up Max'!F:F,)} | Y8: {=_xlfn.XLOOKUP(B8,'Up Stats'!A:A,'Up Stats'!G:G,)} | Z8: =IFERROR(__xludf.DUMMYFUNCTION("if(AND(AA8=FALSE,AB8=FALSE),,if(AA8=AB8,JOIN("""",""Static: "",AA8),JOIN("""",""Min: "",AA8, CHAR(10),""Max: "",AB8)))"),"") | AA8: {=_xlfn.XLOOKUP(B8,'Up Min'!A:A,'Up Min'!G:G,)} | AB8: {=_xlfn.XLOOKUP(B8,'Up Max'!A:A,'Up Max'!G:G,)} | AC8: {=_xlfn.XLOOKUP(B8,'Up Stats'!A:A,'Up Stats'!H:H,)} | AD8: =IFERROR(__xludf.DUMMYFUNCTION("if(AND(AE8=FALSE,AF8=FALSE),,if(AE8=AF8,JOIN("""",""Static: "",AE8),JOIN("""",""Min: "",AE8, CHAR(10),""Max: "",AF8)))"),"") | AE8: {=_xlfn.XLOOKUP(B8,'Up Min'!A:A,'Up Min'!H:H,)} | AF8: {=_xlfn.XLOOKUP(B8,'Up Max'!A:A,'Up Max'!H:H,)} | AG8: {=_xlfn.XLOOKUP(B8,'Up Stats'!A:A,'Up Stats'!I:I,)} | AH8: =IFERROR(__xludf.DUMMYFUNCTION("if(AND(AI8=FALSE,AJ8=FALSE),,if(AI8=AJ8,JOIN("""",""Static: "",AI8),JOIN("""",""Min: "",AI8, CHAR(10),""Max: "",AJ8)))"),"") | AI8: {=_xlfn.XLOOKUP(B8,'Up Min'!A:A,'Up Min'!I:I,)} | AJ8: {=_xlfn.XLOOKUP(B8,'Up Max'!A:A,'Up Max'!I:I,)} | AK8: {=_xlfn.XLOOKUP(B8,'Up Stats'!A:A,'Up Stats'!J:J,)} | AL8: =IFERROR(__xludf.DUMMYFUNCTION("if(AND(AM8=FALSE,AN8=FALSE),,if(AM8=AN8,JOIN("""",""Static: "",AM8),JOIN("""",""Min: "",AM8, CHAR(10),""Max: "",AN8)))"),"") | AM8: {=_xlfn.XLOOKUP(B8,'Up Min'!A:A,'Up Min'!J:J,)} | AN8: {=_xlfn.XLOOKUP(B8,'Up Max'!A:A,'Up Max'!J:J,)} | AO8: {=CONCATENATE(_xlfn.XLOOKUP(B8,'Up Cells'!A:A,'Up Cells'!B:B,))} -> 7 | AP8: {=CONCATENATE(_xlfn.XLOOKUP(B8,'Up Rarity'!A:A,'Up Rarity'!B:B,),CHAR(10),"-")} -> Exotic -
A9: {=_xlfn.XLOOKUP(B9,'Up Icon'!A:A,'Up Icon'!B:B,)} | B9: {=HYPERLINK(_xlfn.XLOOKUP('Up Names'!A6,'Up Wiki'!A:A,'Up Wiki'!B:B,),'Up Names'!A6)} -> Violent Ignition | C9: {=_xlfn.XLOOKUP(B9,'Up Desc'!A:A,'Up Desc'!B:B,)} -> Igniting a target applies a +5 fire to nearby targets. | D9: {=_xlfn.XLOOKUP(B9,'Up Turbo'!A:A,'Up Turbo'!B:B,)} | E9: {=_xlfn.XLOOKUP(B9,'Up Stats'!A:A,'Up Stats'!B:B,)} -> Fire Radius | F9: =IFERROR(__xludf.DUMMYFUNCTION("if(AND(G9=FALSE,H9=FALSE),,if(G9=H9,JOIN("""",""Static: "",G9),JOIN("""",""Min: "",G9, CHAR(10),""Max: "",H9)))"),"Min: 3.12 Max: 3.39") -> Min: 3.12 Max: 3.39 | G9: {=_xlfn.XLOOKUP(B9,'Up Min'!A:A,'Up Min'!B:B,)} -> 3.12 | H9: {=_xlfn.XLOOKUP(B9,'Up Max'!A:A,'Up Max'!B:B,)} -> 3.39 | I9: {=_xlfn.XLOOKUP(B9,'Up Stats'!A:A,'Up Stats'!C:C,)} -> Fire Amount | J9: =IFERROR(__xludf.DUMMYFUNCTION("if(AND(K9=FALSE,L9=FALSE),,if(K9=L9,JOIN("""",""Static: "",K9),JOIN("""",""Min: "",K9, CHAR(10),""Max: "",L9)))"),"Min: 1.8 Max: 2.19") -> Min: 1.8 Max: 2.19 | K9: {=_xlfn.XLOOKUP(B9,'Up Min'!A:A,'Up Min'!C:C,)} -> 1.8 | L9: {=_xlfn.XLOOKUP(B9,'Up Max'!A:A,'Up Max'!C:C,)} -> 2.19 | M9: {=_xlfn.XLOOKUP(B9,'Up Stats'!A:A,'Up Stats'!D:D,)} | N9: =IFERROR(__xludf.DUMMYFUNCTION("if(AND(O9=FALSE,P9=FALSE),,if(O9=P9,JOIN("""",""Static: "",O9),JOIN("""",""Min: "",O9, CHAR(10),""Max: "",P9)))"),"") | O9: {=_xlfn.XLOOKUP(B9,'Up Min'!A:A,'Up Min'!D:D,)} | P9: {=_xlfn.XLOOKUP(B9,'Up Max'!A:A,'Up Max'!D:D,)} | Q9: {=_xlfn.XLOOKUP(B9,'Up Stats'!A:A,'Up Stats'!E:E,)} | R9: =IFERROR(__xludf.DUMMYFUNCTION("if(AND(S9=FALSE,T9=FALSE),,if(S9=T9,JOIN("""",""Static: "",S9),JOIN("""",""Min: "",S9, CHAR(10),""Max: "",T9)))"),"") | S9: {=_xlfn.XLOOKUP(B9,'Up Min'!A:A,'Up Min'!E:E,)} | T9: {=_xlfn.XLOOKUP(B9,'Up Max'!A:A,'Up Max'!E:E,)} | U9: {=_xlfn.XLOOKUP(B9,'Up Stats'!A:A,'Up Stats'!F:F,)} | V9: =IFERROR(__xludf.DUMMYFUNCTION("if(AND(W9=FALSE,X9=FALSE),,if(W9=X9,JOIN("""",""Static: "",W9),JOIN("""",""Min: "",W9, CHAR(10),""Max: "",X9)))"),"") | W9: {=_xlfn.XLOOKUP(B9,'Up Min'!A:A,'Up Min'!F:F,)} | X9: {=_xlfn.XLOOKUP(B9,'Up Max'!A:A,'Up Max'!F:F,)} | Y9: {=_xlfn.XLOOKUP(B9,'Up Stats'!A:A,'Up Stats'!G:G,)} | Z9: =IFERROR(__xludf.DUMMYFUNCTION("if(AND(AA9=FALSE,AB9=FALSE),,if(AA9=AB9,JOIN("""",""Static: "",AA9),JOIN("""",""Min: "",AA9, CHAR(10),""Max: "",AB9)))"),"") | AA9: {=_xlfn.XLOOKUP(B9,'Up Min'!A:A,'Up Min'!G:G,)} | AB9: {=_xlfn.XLOOKUP(B9,'Up Max'!A:A,'Up Max'!G:G,)} | AC9: {=_xlfn.XLOOKUP(B9,'Up Stats'!A:A,'Up Stats'!H:H,)} | AD9: =IFERROR(__xludf.DUMMYFUNCTION("if(AND(AE9=FALSE,AF9=FALSE),,if(AE9=AF9,JOIN("""",""Static: "",AE9),JOIN("""",""Min: "",AE9, CHAR(10),""Max: "",AF9)))"),"") | AE9: {=_xlfn.XLOOKUP(B9,'Up Min'!A:A,'Up Min'!H:H,)} | AF9: {=_xlfn.XLOOKUP(B9,'Up Max'!A:A,'Up Max'!H:H,)} | AG9: {=_xlfn.XLOOKUP(B9,'Up Stats'!A:A,'Up Stats'!I:I,)} | AH9: =IFERROR(__xludf.DUMMYFUNCTION("if(AND(AI9=FALSE,AJ9=FALSE),,if(AI9=AJ9,JOIN("""",""Static: "",AI9),JOIN("""",""Min: "",AI9, CHAR(10),""Max: "",AJ9)))"),"") | AI9: {=_xlfn.XLOOKUP(B9,'Up Min'!A:A,'Up Min'!I:I,)} | AJ9: {=_xlfn.XLOOKUP(B9,'Up Max'!A:A,'Up Max'!I:I,)} | AK9: {=_xlfn.XLOOKUP(B9,'Up Stats'!A:A,'Up Stats'!J:J,)} | AL9: =IFERROR(__xludf.DUMMYFUNCTION("if(AND(AM9=FALSE,AN9=FALSE),,if(AM9=AN9,JOIN("""",""Static: "",AM9),JOIN("""",""Min: "",AM9, CHAR(10),""Max: "",AN9)))"),"") | AM9: {=_xlfn.XLOOKUP(B9,'Up Min'!A:A,'Up Min'!J:J,)} | AN9: {=_xlfn.XLOOKUP(B9,'Up Max'!A:A,'Up Max'!J:J,)} | AO9: {=CONCATENATE(_xlfn.XLOOKUP(B9,'Up Cells'!A:A,'Up Cells'!B:B,))} -> 7 | AP9: {=CONCATENATE(_xlfn.XLOOKUP(B9,'Up Rarity'!A:A,'Up Rarity'!B:B,),CHAR(10),"-")} -> Exotic -
A10: {=_xlfn.XLOOKUP(B10,'Up Icon'!A:A,'Up Icon'!B:B,)} | B10: {=HYPERLINK(_xlfn.XLOOKUP('Up Names'!A7,'Up Wiki'!A:A,'Up Wiki'!B:B,),'Up Names'!A7)} -> Cycling Repairs | C10: {=_xlfn.XLOOKUP(B10,'Up Desc'!A:A,'Up Desc'!B:B,)} -> While constantly shooting, every 15th bullet fired will heal you. | D10: {=_xlfn.XLOOKUP(B10,'Up Turbo'!A:A,'Up Turbo'!B:B,)} -> n/a | E10: {=_xlfn.XLOOKUP(B10,'Up Stats'!A:A,'Up Stats'!B:B,)} -> Health | F10: =IFERROR(__xludf.DUMMYFUNCTION("if(AND(G10=FALSE,H10=FALSE),,if(G10=H10,JOIN("""",""Static: "",G10),JOIN("""",""Min: "",G10, CHAR(10),""Max: "",H10)))"),"Min: 0.8 Max: 1.2") -> Min: 0.8 Max: 1.2 | G10: {=_xlfn.XLOOKUP(B10,'Up Min'!A:A,'Up Min'!B:B,)} -> 0.8 | H10: {=_xlfn.XLOOKUP(B10,'Up Max'!A:A,'Up Max'!B:B,)} -> 1.2 | I10: {=_xlfn.XLOOKUP(B10,'Up Stats'!A:A,'Up Stats'!C:C,)} | J10: =IFERROR(__xludf.DUMMYFUNCTION("if(AND(K10=FALSE,L10=FALSE),,if(K10=L10,JOIN("""",""Static: "",K10),JOIN("""",""Min: "",K10, CHAR(10),""Max: "",L10)))"),"") | K10: {=_xlfn.XLOOKUP(B10,'Up Min'!A:A,'Up Min'!C:C,)} | L10: {=_xlfn.XLOOKUP(B10,'Up Max'!A:A,'Up Max'!C:C,)} | M10: {=_xlfn.XLOOKUP(B10,'Up Stats'!A:A,'Up Stats'!D:D,)} | N10: =IFERROR(__xludf.DUMMYFUNCTION("if(AND(O10=FALSE,P10=FALSE),,if(O10=P10,JOIN("""",""Static: "",O10),JOIN("""",""Min: "",O10, CHAR(10),""Max: "",P10)))"),"") | O10: {=_xlfn.XLOOKUP(B10,'Up Min'!A:A,'Up Min'!D:D,)} | P10: {=_xlfn.XLOOKUP(B10,'Up Max'!A:A,'Up Max'!D:D,)} | Q10: {=_xlfn.XLOOKUP(B10,'Up Stats'!A:A,'Up Stats'!E:E,)} | R10: =IFERROR(__xludf.DUMMYFUNCTION("if(AND(S10=FALSE,T10=FALSE),,if(S10=T10,JOIN("""",""Static: "",S10),JOIN("""",""Min: "",S10, CHAR(10),""Max: "",T10)))"),"") | S10: {=_xlfn.XLOOKUP(B10,'Up Min'!A:A,'Up Min'!E:E,)} | T10: {=_xlfn.XLOOKUP(B10,'Up Max'!A:A,'Up Max'!E:E,)} | U10: {=_xlfn.XLOOKUP(B10,'Up Stats'!A:A,'Up Stats'!F:F,)} | V10: =IFERROR(__xludf.DUMMYFUNCTION("if(AND(W10=FALSE,X10=FALSE),,if(W10=X10,JOIN("""",""Static: "",W10),JOIN("""",""Min: "",W10, CHAR(10),""Max: "",X10)))"),"") | W10: {=_xlfn.XLOOKUP(B10,'Up Min'!A:A,'Up Min'!F:F,)} | X10: {=_xlfn.XLOOKUP(B10,'Up Max'!A:A,'Up Max'!F:F,)} | Y10: {=_xlfn.XLOOKUP(B10,'Up Stats'!A:A,'Up Stats'!G:G,)} | Z10: =IFERROR(__xludf.DUMMYFUNCTION("if(AND(AA10=FALSE,AB10=FALSE),,if(AA10=AB10,JOIN("""",""Static: "",AA10),JOIN("""",""Min: "",AA10, CHAR(10),""Max: "",AB10)))"),"") | AA10: {=_xlfn.XLOOKUP(B10,'Up Min'!A:A,'Up Min'!G:G,)} | AB10: {=_xlfn.XLOOKUP(B10,'Up Max'!A:A,'Up Max'!G:G,)} | AC10: {=_xlfn.XLOOKUP(B10,'Up Stats'!A:A,'Up Stats'!H:H,)} | AD10: =IFERROR(__xludf.DUMMYFUNCTION("if(AND(AE10=FALSE,AF10=FALSE),,if(AE10=AF10,JOIN("""",""Static: "",AE10),JOIN("""",""Min: "",AE10, CHAR(10),""Max: "",AF10)))"),"") | AE10: {=_xlfn.XLOOKUP(B10,'Up Min'!A:A,'Up Min'!H:H,)} | AF10: {=_xlfn.XLOOKUP(B10,'Up Max'!A:A,'Up Max'!H:H,)} | AG10: {=_xlfn.XLOOKUP(B10,'Up Stats'!A:A,'Up Stats'!I:I,)} | AH10: =IFERROR(__xludf.DUMMYFUNCTION("if(AND(AI10=FALSE,AJ10=FALSE),,if(AI10=AJ10,JOIN("""",""Static: "",AI10),JOIN("""",""Min: "",AI10, CHAR(10),""Max: "",AJ10)))"),"") | AI10: {=_xlfn.XLOOKUP(B10,'Up Min'!A:A,'Up Min'!I:I,)} | AJ10: {=_xlfn.XLOOKUP(B10,'Up Max'!A:A,'Up Max'!I:I,)} | AK10: {=_xlfn.XLOOKUP(B10,'Up Stats'!A:A,'Up Stats'!J:J,)} | AL10: =IFERROR(__xludf.DUMMYFUNCTION("if(AND(AM10=FALSE,AN10=FALSE),,if(AM10=AN10,JOIN("""",""Static: "",AM10),JOIN("""",""Min: "",AM10, CHAR(10),""Max: "",AN10)))"),"") | AM10: {=_xlfn.XLOOKUP(B10,'Up Min'!A:A,'Up Min'!J:J,)} | AN10: {=_xlfn.XLOOKUP(B10,'Up Max'!A:A,'Up Max'!J:J,)} | AO10: {=CONCATENATE(_xlfn.XLOOKUP(B10,'Up Cells'!A:A,'Up Cells'!B:B,))} -> 6 | AP10: {=CONCATENATE(_xlfn.XLOOKUP(B10,'Up Rarity'!A:A,'Up Rarity'!B:B,),CHAR(10),"-")} -> Epic -
A11: {=_xlfn.XLOOKUP(B11,'Up Icon'!A:A,'Up Icon'!B:B,)} | B11: {=HYPERLINK(_xlfn.XLOOKUP('Up Names'!A8,'Up Wiki'!A:A,'Up Wiki'!B:B,),'Up Names'!A8)} -> Dump Charge | C11: {=_xlfn.XLOOKUP(B11,'Up Desc'!A:A,'Up Desc'!B:B,)} -> Hold the trigger to build charge. Upon release, all prepared ammo is fired very quickly. | D11: {=_xlfn.XLOOKUP(B11,'Up Turbo'!A:A,'Up Turbo'!B:B,)} -> n/a | E11: {=_xlfn.XLOOKUP(B11,'Up Stats'!A:A,'Up Stats'!B:B,)} -> Fire Rate | F11: =IFERROR(__xludf.DUMMYFUNCTION("if(AND(G11=FALSE,H11=FALSE),,if(G11=H11,JOIN("""",""Static: "",G11),JOIN("""",""Min: "",G11, CHAR(10),""Max: "",H11)))"),"Min: 150% Max: 92.30%") -> Min: 150% Max: 92.30% | G11: {=_xlfn.XLOOKUP(B11,'Up Min'!A:A,'Up Min'!B:B,)} -> 1.5 | H11: {=_xlfn.XLOOKUP(B11,'Up Max'!A:A,'Up Max'!B:B,)} -> 0.923 | I11: {=_xlfn.XLOOKUP(B11,'Up Stats'!A:A,'Up Stats'!C:C,)} -> Charge Time | J11: =IFERROR(__xludf.DUMMYFUNCTION("if(AND(K11=FALSE,L11=FALSE),,if(K11=L11,JOIN("""",""Static: "",K11),JOIN("""",""Min: "",K11, CHAR(10),""Max: "",L11)))"),"Min: 1.35 Max: 1.65") -> Min: 1.35 Max: 1.65 | K11: {=_xlfn.XLOOKUP(B11,'Up Min'!A:A,'Up Min'!C:C,)} -> 1.35 | L11: {=_xlfn.XLOOKUP(B11,'Up Max'!A:A,'Up Max'!C:C,)} -> 1.65 | M11: {=_xlfn.XLOOKUP(B11,'Up Stats'!A:A,'Up Stats'!D:D,)} -> Horizontal Recoil | N11: =IFERROR(__xludf.DUMMYFUNCTION("if(AND(O11=FALSE,P11=FALSE),,if(O11=P11,JOIN("""",""Static: "",O11),JOIN("""",""Min: "",O11, CHAR(10),""Max: "",P11)))"),"Min: 0.75 Max: 0.85") -> Min: 0.75 Max: 0.85 | O11: {=_xlfn.XLOOKUP(B11,'Up Min'!A:A,'Up Min'!D:D,)} -> 0.75 | P11: {=_xlfn.XLOOKUP(B11,'Up Max'!A:A,'Up Max'!D:D,)} -> 0.85 | Q11: {=_xlfn.XLOOKUP(B11,'Up Stats'!A:A,'Up Stats'!E:E,)} -> Vertical Recoil | R11: =IFERROR(__xludf.DUMMYFUNCTION("if(AND(S11=FALSE,T11=FALSE),,if(S11=T11,JOIN("""",""Static: "",S11),JOIN("""",""Min: "",S11, CHAR(10),""Max: "",T11)))"),"Min: -55% Max: -45%") -> Min: -55% Max: -45% | S11: {=_xlfn.XLOOKUP(B11,'Up Min'!A:A,'Up Min'!E:E,)} -> -0.55 | T11: {=_xlfn.XLOOKUP(B11,'Up Max'!A:A,'Up Max'!E:E,)} -> -0.45 | U11: {=_xlfn.XLOOKUP(B11,'Up Stats'!A:A,'Up Stats'!F:F,)} | V11: =IFERROR(__xludf.DUMMYFUNCTION("if(AND(W11=FALSE,X11=FALSE),,if(W11=X11,JOIN("""",""Static: "",W11),JOIN("""",""Min: "",W11, CHAR(10),""Max: "",X11)))"),"") | W11: {=_xlfn.XLOOKUP(B11,'Up Min'!A:A,'Up Min'!F:F,)} | X11: {=_xlfn.XLOOKUP(B11,'Up Max'!A:A,'Up Max'!F:F,)} | Y11: {=_xlfn.XLOOKUP(B11,'Up Stats'!A:A,'Up Stats'!G:G,)} | Z11: =IFERROR(__xludf.DUMMYFUNCTION("if(AND(AA11=FALSE,AB11=FALSE),,if(AA11=AB11,JOIN("""",""Static: "",AA11),JOIN("""",""Min: "",AA11, CHAR(10),""Max: "",AB11)))"),"") | AA11: {=_xlfn.XLOOKUP(B11,'Up Min'!A:A,'Up Min'!G:G,)} | AB11: {=_xlfn.XLOOKUP(B11,'Up Max'!A:A,'Up Max'!G:G,)} | AC11: {=_xlfn.XLOOKUP(B11,'Up Stats'!A:A,'Up Stats'!H:H,)} | AD11: =IFERROR(__xludf.DUMMYFUNCTION("if(AND(AE11=FALSE,AF11=FALSE),,if(AE11=AF11,JOIN("""",""Static: "",AE11),JOIN("""",""Min: "",AE11, CHAR(10),""Max: "",AF11)))"),"") | AE11: {=_xlfn.XLOOKUP(B11,'Up Min'!A:A,'Up Min'!H:H,)} | AF11: {=_xlfn.XLOOKUP(B11,'Up Max'!A:A,'Up Max'!H:H,)} | AG11: {=_xlfn.XLOOKUP(B11,'Up Stats'!A:A,'Up Stats'!I:I,)} | AH11: =IFERROR(__xludf.DUMMYFUNCTION("if(AND(AI11=FALSE,AJ11=FALSE),,if(AI11=AJ11,JOIN("""",""Static: "",AI11),JOIN("""",""Min: "",AI11, CHAR(10),""Max: "",AJ11)))"),"") | AI11: {=_xlfn.XLOOKUP(B11,'Up Min'!A:A,'Up Min'!I:I,)} | AJ11: {=_xlfn.XLOOKUP(B11,'Up Max'!A:A,'Up Max'!I:I,)} | AK11: {=_xlfn.XLOOKUP(B11,'Up Stats'!A:A,'Up Stats'!J:J,)} | AL11: =IFERROR(__xludf.DUMMYFUNCTION("if(AND(AM11=FALSE,AN11=FALSE),,if(AM11=AN11,JOIN("""",""Static: "",AM11),JOIN("""",""Min: "",AM11, CHAR(10),""Max: "",AN11)))"),"") | AM11: {=_xlfn.XLOOKUP(B11,'Up Min'!A:A,'Up Min'!J:J,)} | AN11: {=_xlfn.XLOOKUP(B11,'Up Max'!A:A,'Up Max'!J:J,)} | AO11: {=CONCATENATE(_xlfn.XLOOKUP(B11,'Up Cells'!A:A,'Up Cells'!B:B,))} -> 5 | AP11: {=CONCATENATE(_xlfn.XLOOKUP(B11,'Up Rarity'!A:A,'Up Rarity'!B:B,),CHAR(10),"-")} -> Epic -
A12: {=_xlfn.XLOOKUP(B12,'Up Icon'!A:A,'Up Icon'!B:B,)} | B12: {=HYPERLINK(_xlfn.XLOOKUP('Up Names'!A9,'Up Wiki'!A:A,'Up Wiki'!B:B,),'Up Names'!A9)} -> Equipment Siphon | C12: {=_xlfn.XLOOKUP(B12,'Up Desc'!A:A,'Up Desc'!B:B,)} -> Dealing damage with other gear returns ammo to the magazine. Reload speed is slightly decreased. | D12: {=_xlfn.XLOOKUP(B12,'Up Turbo'!A:A,'Up Turbo'!B:B,)} -> n/a | E12: {=_xlfn.XLOOKUP(B12,'Up Stats'!A:A,'Up Stats'!B:B,)} -> Ammo Efficiency | F12: =IFERROR(__xludf.DUMMYFUNCTION("if(AND(G12=FALSE,H12=FALSE),,if(G12=H12,JOIN("""",""Static: "",G12),JOIN("""",""Min: "",G12, CHAR(10),""Max: "",H12)))"),"Min: 1.06 Max: 1.5") -> Min: 1.06 Max: 1.5 | G12: {=_xlfn.XLOOKUP(B12,'Up Min'!A:A,'Up Min'!B:B,)} -> 1.06 | H12: {=_xlfn.XLOOKUP(B12,'Up Max'!A:A,'Up Max'!B:B,)} -> 1.5 | I12: {=_xlfn.XLOOKUP(B12,'Up Stats'!A:A,'Up Stats'!C:C,)} -> Reload Speed | J12: =IFERROR(__xludf.DUMMYFUNCTION("if(AND(K12=FALSE,L12=FALSE),,if(K12=L12,JOIN("""",""Static: "",K12),JOIN("""",""Min: "",K12, CHAR(10),""Max: "",L12)))"),"Min: -8.26% Max: -16.67%") -> Min: -8.26% Max: -16.67% | K12: {=_xlfn.XLOOKUP(B12,'Up Min'!A:A,'Up Min'!C:C,)} -> -0.0826 | L12: {=_xlfn.XLOOKUP(B12,'Up Max'!A:A,'Up Max'!C:C,)} -> -0.1667 | M12: {=_xlfn.XLOOKUP(B12,'Up Stats'!A:A,'Up Stats'!D:D,)} | N12: =IFERROR(__xludf.DUMMYFUNCTION("if(AND(O12=FALSE,P12=FALSE),,if(O12=P12,JOIN("""",""Static: "",O12),JOIN("""",""Min: "",O12, CHAR(10),""Max: "",P12)))"),"") | O12: {=_xlfn.XLOOKUP(B12,'Up Min'!A:A,'Up Min'!D:D,)} | P12: {=_xlfn.XLOOKUP(B12,'Up Max'!A:A,'Up Max'!D:D,)} | Q12: {=_xlfn.XLOOKUP(B12,'Up Stats'!A:A,'Up Stats'!E:E,)} | R12: =IFERROR(__xludf.DUMMYFUNCTION("if(AND(S12=FALSE,T12=FALSE),,if(S12=T12,JOIN("""",""Static: "",S12),JOIN("""",""Min: "",S12, CHAR(10),""Max: "",T12)))"),"") | S12: {=_xlfn.XLOOKUP(B12,'Up Min'!A:A,'Up Min'!E:E,)} | T12: {=_xlfn.XLOOKUP(B12,'Up Max'!A:A,'Up Max'!E:E,)} | U12: {=_xlfn.XLOOKUP(B12,'Up Stats'!A:A,'Up Stats'!F:F,)} | V12: =IFERROR(__xludf.DUMMYFUNCTION("if(AND(W12=FALSE,X12=FALSE),,if(W12=X12,JOIN("""",""Static: "",W12),JOIN("""",""Min: "",W12, CHAR(10),""Max: "",X12)))"),"") | W12: {=_xlfn.XLOOKUP(B12,'Up Min'!A:A,'Up Min'!F:F,)} | X12: {=_xlfn.XLOOKUP(B12,'Up Max'!A:A,'Up Max'!F:F,)} | Y12: {=_xlfn.XLOOKUP(B12,'Up Stats'!A:A,'Up Stats'!G:G,)} | Z12: =IFERROR(__xludf.DUMMYFUNCTION("if(AND(AA12=FALSE,AB12=FALSE),,if(AA12=AB12,JOIN("""",""Static: "",AA12),JOIN("""",""Min: "",AA12, CHAR(10),""Max: "",AB12)))"),"") | AA12: {=_xlfn.XLOOKUP(B12,'Up Min'!A:A,'Up Min'!G:G,)} | AB12: {=_xlfn.XLOOKUP(B12,'Up Max'!A:A,'Up Max'!G:G,)} | AC12: {=_xlfn.XLOOKUP(B12,'Up Stats'!A:A,'Up Stats'!H:H,)} | AD12: =IFERROR(__xludf.DUMMYFUNCTION("if(AND(AE12=FALSE,AF12=FALSE),,if(AE12=AF12,JOIN("""",""Static: "",AE12),JOIN("""",""Min: "",AE12, CHAR(10),""Max: "",AF12)))"),"") | AE12: {=_xlfn.XLOOKUP(B12,'Up Min'!A:A,'Up Min'!H:H,)} | AF12: {=_xlfn.XLOOKUP(B12,'Up Max'!A:A,'Up Max'!H:H,)} | AG12: {=_xlfn.XLOOKUP(B12,'Up Stats'!A:A,'Up Stats'!I:I,)} | AH12: =IFERROR(__xludf.DUMMYFUNCTION("if(AND(AI12=FALSE,AJ12=FALSE),,if(AI12=AJ12,JOIN("""",""Static: "",AI12),JOIN("""",""Min: "",AI12, CHAR(10),""Max: "",AJ12)))"),"") | AI12: {=_xlfn.XLOOKUP(B12,'Up Min'!A:A,'Up Min'!I:I,)} | AJ12: {=_xlfn.XLOOKUP(B12,'Up Max'!A:A,'Up Max'!I:I,)} | AK12: {=_xlfn.XLOOKUP(B12,'Up Stats'!A:A,'Up Stats'!J:J,)} | AL12: =IFERROR(__xludf.DUMMYFUNCTION("if(AND(AM12=FALSE,AN12=FALSE),,if(AM12=AN12,JOIN("""",""Static: "",AM12),JOIN("""",""Min: "",AM12, CHAR(10),""Max: "",AN12)))"),"") | AM12: {=_xlfn.XLOOKUP(B12,'Up Min'!A:A,'Up Min'!J:J,)} | AN12: {=_xlfn.XLOOKUP(B12,'Up Max'!A:A,'Up Max'!J:J,)} | AO12: {=CONCATENATE(_xlfn.XLOOKUP(B12,'Up Cells'!A:A,'Up Cells'!B:B,))} -> 4 | AP12: {=CONCATENATE(_xlfn.XLOOKUP(B12,'Up Rarity'!A:A,'Up Rarity'!B:B,),CHAR(10),"-")} -> Epic -
A13: {=_xlfn.XLOOKUP(B13,'Up Icon'!A:A,'Up Icon'!B:B,)} | B13: {=HYPERLINK(_xlfn.XLOOKUP('Up Names'!A10,'Up Wiki'!A:A,'Up Wiki'!B:B,),'Up Names'!A10)} -> Extralight Frame | C13: {=_xlfn.XLOOKUP(B13,'Up Desc'!A:A,'Up Desc'!B:B,)} -> Fire while sprinting. | D13: {=_xlfn.XLOOKUP(B13,'Up Turbo'!A:A,'Up Turbo'!B:B,)} -> n/a | E13: {=_xlfn.XLOOKUP(B13,'Up Stats'!A:A,'Up Stats'!B:B,)} | F13: =IFERROR(__xludf.DUMMYFUNCTION("if(AND(G13=FALSE,H13=FALSE),,if(G13=H13,JOIN("""",""Static: "",G13),JOIN("""",""Min: "",G13, CHAR(10),""Max: "",H13)))"),"") | G13: {=_xlfn.XLOOKUP(B13,'Up Min'!A:A,'Up Min'!B:B,)} | H13: {=_xlfn.XLOOKUP(B13,'Up Max'!A:A,'Up Max'!B:B,)} | I13: {=_xlfn.XLOOKUP(B13,'Up Stats'!A:A,'Up Stats'!C:C,)} | J13: =IFERROR(__xludf.DUMMYFUNCTION("if(AND(K13=FALSE,L13=FALSE),,if(K13=L13,JOIN("""",""Static: "",K13),JOIN("""",""Min: "",K13, CHAR(10),""Max: "",L13)))"),"") | K13: {=_xlfn.XLOOKUP(B13,'Up Min'!A:A,'Up Min'!C:C,)} | L13: {=_xlfn.XLOOKUP(B13,'Up Max'!A:A,'Up Max'!C:C,)} | M13: {=_xlfn.XLOOKUP(B13,'Up Stats'!A:A,'Up Stats'!D:D,)} | N13: =IFERROR(__xludf.DUMMYFUNCTION("if(AND(O13=FALSE,P13=FALSE),,if(O13=P13,JOIN("""",""Static: "",O13),JOIN("""",""Min: "",O13, CHAR(10),""Max: "",P13)))"),"") | O13: {=_xlfn.XLOOKUP(B13,'Up Min'!A:A,'Up Min'!D:D,)} | P13: {=_xlfn.XLOOKUP(B13,'Up Max'!A:A,'Up Max'!D:D,)} | Q13: {=_xlfn.XLOOKUP(B13,'Up Stats'!A:A,'Up Stats'!E:E,)} | R13: =IFERROR(__xludf.DUMMYFUNCTION("if(AND(S13=FALSE,T13=FALSE),,if(S13=T13,JOIN("""",""Static: "",S13),JOIN("""",""Min: "",S13, CHAR(10),""Max: "",T13)))"),"") | S13: {=_xlfn.XLOOKUP(B13,'Up Min'!A:A,'Up Min'!E:E,)} | T13: {=_xlfn.XLOOKUP(B13,'Up Max'!A:A,'Up Max'!E:E,)} | U13: {=_xlfn.XLOOKUP(B13,'Up Stats'!A:A,'Up Stats'!F:F,)} | V13: =IFERROR(__xludf.DUMMYFUNCTION("if(AND(W13=FALSE,X13=FALSE),,if(W13=X13,JOIN("""",""Static: "",W13),JOIN("""",""Min: "",W13, CHAR(10),""Max: "",X13)))"),"") | W13: {=_xlfn.XLOOKUP(B13,'Up Min'!A:A,'Up Min'!F:F,)} | X13: {=_xlfn.XLOOKUP(B13,'Up Max'!A:A,'Up Max'!F:F,)} | Y13: {=_xlfn.XLOOKUP(B13,'Up Stats'!A:A,'Up Stats'!G:G,)} | Z13: =IFERROR(__xludf.DUMMYFUNCTION("if(AND(AA13=FALSE,AB13=FALSE),,if(AA13=AB13,JOIN("""",""Static: "",AA13),JOIN("""",""Min: "",AA13, CHAR(10),""Max: "",AB13)))"),"") | AA13: {=_xlfn.XLOOKUP(B13,'Up Min'!A:A,'Up Min'!G:G,)} | AB13: {=_xlfn.XLOOKUP(B13,'Up Max'!A:A,'Up Max'!G:G,)} | AC13: {=_xlfn.XLOOKUP(B13,'Up Stats'!A:A,'Up Stats'!H:H,)} | AD13: =IFERROR(__xludf.DUMMYFUNCTION("if(AND(AE13=FALSE,AF13=FALSE),,if(AE13=AF13,JOIN("""",""Static: "",AE13),JOIN("""",""Min: "",AE13, CHAR(10),""Max: "",AF13)))"),"") | AE13: {=_xlfn.XLOOKUP(B13,'Up Min'!A:A,'Up Min'!H:H,)} | AF13: {=_xlfn.XLOOKUP(B13,'Up Max'!A:A,'Up Max'!H:H,)} | AG13: {=_xlfn.XLOOKUP(B13,'Up Stats'!A:A,'Up Stats'!I:I,)} | AH13: =IFERROR(__xludf.DUMMYFUNCTION("if(AND(AI13=FALSE,AJ13=FALSE),,if(AI13=AJ13,JOIN("""",""Static: "",AI13),JOIN("""",""Min: "",AI13, CHAR(10),""Max: "",AJ13)))"),"") | AI13: {=_xlfn.XLOOKUP(B13,'Up Min'!A:A,'Up Min'!I:I,)} | AJ13: {=_xlfn.XLOOKUP(B13,'Up Max'!A:A,'Up Max'!I:I,)} | AK13: {=_xlfn.XLOOKUP(B13,'Up Stats'!A:A,'Up Stats'!J:J,)} | AL13: =IFERROR(__xludf.DUMMYFUNCTION("if(AND(AM13=FALSE,AN13=FALSE),,if(AM13=AN13,JOIN("""",""Static: "",AM13),JOIN("""",""Min: "",AM13, CHAR(10),""Max: "",AN13)))"),"") | AM13: {=_xlfn.XLOOKUP(B13,'Up Min'!A:A,'Up Min'!J:J,)} | AN13: {=_xlfn.XLOOKUP(B13,'Up Max'!A:A,'Up Max'!J:J,)} | AO13: {=CONCATENATE(_xlfn.XLOOKUP(B13,'Up Cells'!A:A,'Up Cells'!B:B,))} -> 5 | AP13: {=CONCATENATE(_xlfn.XLOOKUP(B13,'Up Rarity'!A:A,'Up Rarity'!B:B,),CHAR(10),"-")} -> Epic -
A14: {=_xlfn.XLOOKUP(B14,'Up Icon'!A:A,'Up Icon'!B:B,)} | B14: {=HYPERLINK(_xlfn.XLOOKUP('Up Names'!A11,'Up Wiki'!A:A,'Up Wiki'!B:B,),'Up Names'!A11)} -> Intense Reaction | C14: {=_xlfn.XLOOKUP(B14,'Up Desc'!A:A,'Up Desc'!B:B,)} -> Increases potency of the applied element. Horizontal spread is greatly increased. | D14: {=_xlfn.XLOOKUP(B14,'Up Turbo'!A:A,'Up Turbo'!B:B,)} -> n/a | E14: {=_xlfn.XLOOKUP(B14,'Up Stats'!A:A,'Up Stats'!B:B,)} -> Horizontal Spread | F14: =IFERROR(__xludf.DUMMYFUNCTION("if(AND(G14=FALSE,H14=FALSE),,if(G14=H14,JOIN("""",""Static: "",G14),JOIN("""",""Min: "",G14, CHAR(10),""Max: "",H14)))"),"Min: 300% Max: 400%") -> Min: 300% Max: 400% | G14: {=_xlfn.XLOOKUP(B14,'Up Min'!A:A,'Up Min'!B:B,)} -> 3 | H14: {=_xlfn.XLOOKUP(B14,'Up Max'!A:A,'Up Max'!B:B,)} -> 4 | I14: {=_xlfn.XLOOKUP(B14,'Up Stats'!A:A,'Up Stats'!C:C,)} -> Element | J14: =IFERROR(__xludf.DUMMYFUNCTION("if(AND(K14=FALSE,L14=FALSE),,if(K14=L14,JOIN("""",""Static: "",K14),JOIN("""",""Min: "",K14, CHAR(10),""Max: "",L14)))"),"Min: 40% Max: 110%") -> Min: 40% Max: 110% | K14: {=_xlfn.XLOOKUP(B14,'Up Min'!A:A,'Up Min'!C:C,)} -> 0.4 | L14: {=_xlfn.XLOOKUP(B14,'Up Max'!A:A,'Up Max'!C:C,)} -> 1.1 | M14: {=_xlfn.XLOOKUP(B14,'Up Stats'!A:A,'Up Stats'!D:D,)} | N14: =IFERROR(__xludf.DUMMYFUNCTION("if(AND(O14=FALSE,P14=FALSE),,if(O14=P14,JOIN("""",""Static: "",O14),JOIN("""",""Min: "",O14, CHAR(10),""Max: "",P14)))"),"") | O14: {=_xlfn.XLOOKUP(B14,'Up Min'!A:A,'Up Min'!D:D,)} | P14: {=_xlfn.XLOOKUP(B14,'Up Max'!A:A,'Up Max'!D:D,)} | Q14: {=_xlfn.XLOOKUP(B14,'Up Stats'!A:A,'Up Stats'!E:E,)} | R14: =IFERROR(__xludf.DUMMYFUNCTION("if(AND(S14=FALSE,T14=FALSE),,if(S14=T14,JOIN("""",""Static: "",S14),JOIN("""",""Min: "",S14, CHAR(10),""Max: "",T14)))"),"") | S14: {=_xlfn.XLOOKUP(B14,'Up Min'!A:A,'Up Min'!E:E,)} | T14: {=_xlfn.XLOOKUP(B14,'Up Max'!A:A,'Up Max'!E:E,)} | U14: {=_xlfn.XLOOKUP(B14,'Up Stats'!A:A,'Up Stats'!F:F,)} | V14: =IFERROR(__xludf.DUMMYFUNCTION("if(AND(W14=FALSE,X14=FALSE),,if(W14=X14,JOIN("""",""Static: "",W14),JOIN("""",""Min: "",W14, CHAR(10),""Max: "",X14)))"),"") | W14: {=_xlfn.XLOOKUP(B14,'Up Min'!A:A,'Up Min'!F:F,)} | X14: {=_xlfn.XLOOKUP(B14,'Up Max'!A:A,'Up Max'!F:F,)} | Y14: {=_xlfn.XLOOKUP(B14,'Up Stats'!A:A,'Up Stats'!G:G,)} | Z14: =IFERROR(__xludf.DUMMYFUNCTION("if(AND(AA14=FALSE,AB14=FALSE),,if(AA14=AB14,JOIN("""",""Static: "",AA14),JOIN("""",""Min: "",AA14, CHAR(10),""Max: "",AB14)))"),"") | AA14: {=_xlfn.XLOOKUP(B14,'Up Min'!A:A,'Up Min'!G:G,)} | AB14: {=_xlfn.XLOOKUP(B14,'Up Max'!A:A,'Up Max'!G:G,)} | AC14: {=_xlfn.XLOOKUP(B14,'Up Stats'!A:A,'Up Stats'!H:H,)} | AD14: =IFERROR(__xludf.DUMMYFUNCTION("if(AND(AE14=FALSE,AF14=FALSE),,if(AE14=AF14,JOIN("""",""Static: "",AE14),JOIN("""",""Min: "",AE14, CHAR(10),""Max: "",AF14)))"),"") | AE14: {=_xlfn.XLOOKUP(B14,'Up Min'!A:A,'Up Min'!H:H,)} | AF14: {=_xlfn.XLOOKUP(B14,'Up Max'!A:A,'Up Max'!H:H,)} | AG14: {=_xlfn.XLOOKUP(B14,'Up Stats'!A:A,'Up Stats'!I:I,)} | AH14: =IFERROR(__xludf.DUMMYFUNCTION("if(AND(AI14=FALSE,AJ14=FALSE),,if(AI14=AJ14,JOIN("""",""Static: "",AI14),JOIN("""",""Min: "",AI14, CHAR(10),""Max: "",AJ14)))"),"") | AI14: {=_xlfn.XLOOKUP(B14,'Up Min'!A:A,'Up Min'!I:I,)} | AJ14: {=_xlfn.XLOOKUP(B14,'Up Max'!A:A,'Up Max'!I:I,)} | AK14: {=_xlfn.XLOOKUP(B14,'Up Stats'!A:A,'Up Stats'!J:J,)} | AL14: =IFERROR(__xludf.DUMMYFUNCTION("if(AND(AM14=FALSE,AN14=FALSE),,if(AM14=AN14,JOIN("""",""Static: "",AM14),JOIN("""",""Min: "",AM14, CHAR(10),""Max: "",AN14)))"),"") | AM14: {=_xlfn.XLOOKUP(B14,'Up Min'!A:A,'Up Min'!J:J,)} | AN14: {=_xlfn.XLOOKUP(B14,'Up Max'!A:A,'Up Max'!J:J,)} | AO14: {=CONCATENATE(_xlfn.XLOOKUP(B14,'Up Cells'!A:A,'Up Cells'!B:B,))} -> 5 | AP14: {=CONCATENATE(_xlfn.XLOOKUP(B14,'Up Rarity'!A:A,'Up Rarity'!B:B,),CHAR(10),"-")} -> Epic -
A15: {=_xlfn.XLOOKUP(B15,'Up Icon'!A:A,'Up Icon'!B:B,)} | B15: {=HYPERLINK(_xlfn.XLOOKUP('Up Names'!A12,'Up Wiki'!A:A,'Up Wiki'!B:B,),'Up Names'!A12)} -> Mass Acceleration | C15: {=_xlfn.XLOOKUP(B15,'Up Desc'!A:A,'Up Desc'!B:B,)} -> Fire rate is increased for each bullet that's loaded into the magazine. Base fire rate is decreased. | D15: {=_xlfn.XLOOKUP(B15,'Up Turbo'!A:A,'Up Turbo'!B:B,)} -> n/a | E15: {=_xlfn.XLOOKUP(B15,'Up Stats'!A:A,'Up Stats'!B:B,)} -> Efficiency | F15: =IFERROR(__xludf.DUMMYFUNCTION("if(AND(G15=FALSE,H15=FALSE),,if(G15=H15,JOIN("""",""Static: "",G15),JOIN("""",""Min: "",G15, CHAR(10),""Max: "",H15)))"),"Min: 90% Max: 110%") -> Min: 90% Max: 110% | G15: {=_xlfn.XLOOKUP(B15,'Up Min'!A:A,'Up Min'!B:B,)} -> 0.9 | H15: {=_xlfn.XLOOKUP(B15,'Up Max'!A:A,'Up Max'!B:B,)} -> 1.1 | I15: {=_xlfn.XLOOKUP(B15,'Up Stats'!A:A,'Up Stats'!C:C,)} -> Fire Rate | J15: =IFERROR(__xludf.DUMMYFUNCTION("if(AND(K15=FALSE,L15=FALSE),,if(K15=L15,JOIN("""",""Static: "",K15),JOIN("""",""Min: "",K15, CHAR(10),""Max: "",L15)))"),"Min: -31.03% Max: -35.48%") -> Min: -31.03% Max: -35.48% | K15: {=_xlfn.XLOOKUP(B15,'Up Min'!A:A,'Up Min'!C:C,)} -> -0.3103 | L15: {=_xlfn.XLOOKUP(B15,'Up Max'!A:A,'Up Max'!C:C,)} -> -0.3548 | M15: {=_xlfn.XLOOKUP(B15,'Up Stats'!A:A,'Up Stats'!D:D,)} | N15: =IFERROR(__xludf.DUMMYFUNCTION("if(AND(O15=FALSE,P15=FALSE),,if(O15=P15,JOIN("""",""Static: "",O15),JOIN("""",""Min: "",O15, CHAR(10),""Max: "",P15)))"),"") | O15: {=_xlfn.XLOOKUP(B15,'Up Min'!A:A,'Up Min'!D:D,)} | P15: {=_xlfn.XLOOKUP(B15,'Up Max'!A:A,'Up Max'!D:D,)} | Q15: {=_xlfn.XLOOKUP(B15,'Up Stats'!A:A,'Up Stats'!E:E,)} | R15: =IFERROR(__xludf.DUMMYFUNCTION("if(AND(S15=FALSE,T15=FALSE),,if(S15=T15,JOIN("""",""Static: "",S15),JOIN("""",""Min: "",S15, CHAR(10),""Max: "",T15)))"),"") | S15: {=_xlfn.XLOOKUP(B15,'Up Min'!A:A,'Up Min'!E:E,)} | T15: {=_xlfn.XLOOKUP(B15,'Up Max'!A:A,'Up Max'!E:E,)} | U15: {=_xlfn.XLOOKUP(B15,'Up Stats'!A:A,'Up Stats'!F:F,)} | V15: =IFERROR(__xludf.DUMMYFUNCTION("if(AND(W15=FALSE,X15=FALSE),,if(W15=X15,JOIN("""",""Static: "",W15),JOIN("""",""Min: "",W15, CHAR(10),""Max: "",X15)))"),"") | W15: {=_xlfn.XLOOKUP(B15,'Up Min'!A:A,'Up Min'!F:F,)} | X15: {=_xlfn.XLOOKUP(B15,'Up Max'!A:A,'Up Max'!F:F,)} | Y15: {=_xlfn.XLOOKUP(B15,'Up Stats'!A:A,'Up Stats'!G:G,)} | Z15: =IFERROR(__xludf.DUMMYFUNCTION("if(AND(AA15=FALSE,AB15=FALSE),,if(AA15=AB15,JOIN("""",""Static: "",AA15),JOIN("""",""Min: "",AA15, CHAR(10),""Max: "",AB15)))"),"") | AA15: {=_xlfn.XLOOKUP(B15,'Up Min'!A:A,'Up Min'!G:G,)} | AB15: {=_xlfn.XLOOKUP(B15,'Up Max'!A:A,'Up Max'!G:G,)} | AC15: {=_xlfn.XLOOKUP(B15,'Up Stats'!A:A,'Up Stats'!H:H,)} | AD15: =IFERROR(__xludf.DUMMYFUNCTION("if(AND(AE15=FALSE,AF15=FALSE),,if(AE15=AF15,JOIN("""",""Static: "",AE15),JOIN("""",""Min: "",AE15, CHAR(10),""Max: "",AF15)))"),"") | AE15: {=_xlfn.XLOOKUP(B15,'Up Min'!A:A,'Up Min'!H:H,)} | AF15: {=_xlfn.XLOOKUP(B15,'Up Max'!A:A,'Up Max'!H:H,)} | AG15: {=_xlfn.XLOOKUP(B15,'Up Stats'!A:A,'Up Stats'!I:I,)} | AH15: =IFERROR(__xludf.DUMMYFUNCTION("if(AND(AI15=FALSE,AJ15=FALSE),,if(AI15=AJ15,JOIN("""",""Static: "",AI15),JOIN("""",""Min: "",AI15, CHAR(10),""Max: "",AJ15)))"),"") | AI15: {=_xlfn.XLOOKUP(B15,'Up Min'!A:A,'Up Min'!I:I,)} | AJ15: {=_xlfn.XLOOKUP(B15,'Up Max'!A:A,'Up Max'!I:I,)} | AK15: {=_xlfn.XLOOKUP(B15,'Up Stats'!A:A,'Up Stats'!J:J,)} | AL15: =IFERROR(__xludf.DUMMYFUNCTION("if(AND(AM15=FALSE,AN15=FALSE),,if(AM15=AN15,JOIN("""",""Static: "",AM15),JOIN("""",""Min: "",AM15, CHAR(10),""Max: "",AN15)))"),"") | AM15: {=_xlfn.XLOOKUP(B15,'Up Min'!A:A,'Up Min'!J:J,)} | AN15: {=_xlfn.XLOOKUP(B15,'Up Max'!A:A,'Up Max'!J:J,)} | AO15: {=CONCATENATE(_xlfn.XLOOKUP(B15,'Up Cells'!A:A,'Up Cells'!B:B,))} -> 4 | AP15: {=CONCATENATE(_xlfn.XLOOKUP(B15,'Up Rarity'!A:A,'Up Rarity'!B:B,),CHAR(10),"-")} -> Epic -
A16: {=_xlfn.XLOOKUP(B16,'Up Icon'!A:A,'Up Icon'!B:B,)} | B16: {=HYPERLINK(_xlfn.XLOOKUP('Up Names'!A13,'Up Wiki'!A:A,'Up Wiki'!B:B,),'Up Names'!A13)} -> Momentum Overload | C16: {=_xlfn.XLOOKUP(B16,'Up Desc'!A:A,'Up Desc'!B:B,)} -> Electrocuting a target increases move speed for a short time. | D16: {=_xlfn.XLOOKUP(B16,'Up Turbo'!A:A,'Up Turbo'!B:B,)} -> n/a | E16: {=_xlfn.XLOOKUP(B16,'Up Stats'!A:A,'Up Stats'!B:B,)} -> Speed | F16: =IFERROR(__xludf.DUMMYFUNCTION("if(AND(G16=FALSE,H16=FALSE),,if(G16=H16,JOIN("""",""Static: "",G16),JOIN("""",""Min: "",G16, CHAR(10),""Max: "",H16)))"),"Min: 3.75 Max: 5") -> Min: 3.75 Max: 5 | G16: {=_xlfn.XLOOKUP(B16,'Up Min'!A:A,'Up Min'!B:B,)} -> 3.75 | H16: {=_xlfn.XLOOKUP(B16,'Up Max'!A:A,'Up Max'!B:B,)} -> 5 | I16: {=_xlfn.XLOOKUP(B16,'Up Stats'!A:A,'Up Stats'!C:C,)} -> Duration | J16: =IFERROR(__xludf.DUMMYFUNCTION("if(AND(K16=FALSE,L16=FALSE),,if(K16=L16,JOIN("""",""Static: "",K16),JOIN("""",""Min: "",K16, CHAR(10),""Max: "",L16)))"),"Min: 3.6 Max: 4.4") -> Min: 3.6 Max: 4.4 | K16: {=_xlfn.XLOOKUP(B16,'Up Min'!A:A,'Up Min'!C:C,)} -> 3.6 | L16: {=_xlfn.XLOOKUP(B16,'Up Max'!A:A,'Up Max'!C:C,)} -> 4.4 | M16: {=_xlfn.XLOOKUP(B16,'Up Stats'!A:A,'Up Stats'!D:D,)} | N16: =IFERROR(__xludf.DUMMYFUNCTION("if(AND(O16=FALSE,P16=FALSE),,if(O16=P16,JOIN("""",""Static: "",O16),JOIN("""",""Min: "",O16, CHAR(10),""Max: "",P16)))"),"") | O16: {=_xlfn.XLOOKUP(B16,'Up Min'!A:A,'Up Min'!D:D,)} | P16: {=_xlfn.XLOOKUP(B16,'Up Max'!A:A,'Up Max'!D:D,)} | Q16: {=_xlfn.XLOOKUP(B16,'Up Stats'!A:A,'Up Stats'!E:E,)} | R16: =IFERROR(__xludf.DUMMYFUNCTION("if(AND(S16=FALSE,T16=FALSE),,if(S16=T16,JOIN("""",""Static: "",S16),JOIN("""",""Min: "",S16, CHAR(10),""Max: "",T16)))"),"") | S16: {=_xlfn.XLOOKUP(B16,'Up Min'!A:A,'Up Min'!E:E,)} | T16: {=_xlfn.XLOOKUP(B16,'Up Max'!A:A,'Up Max'!E:E,)} | U16: {=_xlfn.XLOOKUP(B16,'Up Stats'!A:A,'Up Stats'!F:F,)} | V16: =IFERROR(__xludf.DUMMYFUNCTION("if(AND(W16=FALSE,X16=FALSE),,if(W16=X16,JOIN("""",""Static: "",W16),JOIN("""",""Min: "",W16, CHAR(10),""Max: "",X16)))"),"") | W16: {=_xlfn.XLOOKUP(B16,'Up Min'!A:A,'Up Min'!F:F,)} | X16: {=_xlfn.XLOOKUP(B16,'Up Max'!A:A,'Up Max'!F:F,)} | Y16: {=_xlfn.XLOOKUP(B16,'Up Stats'!A:A,'Up Stats'!G:G,)} | Z16: =IFERROR(__xludf.DUMMYFUNCTION("if(AND(AA16=FALSE,AB16=FALSE),,if(AA16=AB16,JOIN("""",""Static: "",AA16),JOIN("""",""Min: "",AA16, CHAR(10),""Max: "",AB16)))"),"") | AA16: {=_xlfn.XLOOKUP(B16,'Up Min'!A:A,'Up Min'!G:G,)} | AB16: {=_xlfn.XLOOKUP(B16,'Up Max'!A:A,'Up Max'!G:G,)} | AC16: {=_xlfn.XLOOKUP(B16,'Up Stats'!A:A,'Up Stats'!H:H,)} | AD16: =IFERROR(__xludf.DUMMYFUNCTION("if(AND(AE16=FALSE,AF16=FALSE),,if(AE16=AF16,JOIN("""",""Static: "",AE16),JOIN("""",""Min: "",AE16, CHAR(10),""Max: "",AF16)))"),"") | AE16: {=_xlfn.XLOOKUP(B16,'Up Min'!A:A,'Up Min'!H:H,)} | AF16: {=_xlfn.XLOOKUP(B16,'Up Max'!A:A,'Up Max'!H:H,)} | AG16: {=_xlfn.XLOOKUP(B16,'Up Stats'!A:A,'Up Stats'!I:I,)} | AH16: =IFERROR(__xludf.DUMMYFUNCTION("if(AND(AI16=FALSE,AJ16=FALSE),,if(AI16=AJ16,JOIN("""",""Static: "",AI16),JOIN("""",""Min: "",AI16, CHAR(10),""Max: "",AJ16)))"),"") | AI16: {=_xlfn.XLOOKUP(B16,'Up Min'!A:A,'Up Min'!I:I,)} | AJ16: {=_xlfn.XLOOKUP(B16,'Up Max'!A:A,'Up Max'!I:I,)} | AK16: {=_xlfn.XLOOKUP(B16,'Up Stats'!A:A,'Up Stats'!J:J,)} | AL16: =IFERROR(__xludf.DUMMYFUNCTION("if(AND(AM16=FALSE,AN16=FALSE),,if(AM16=AN16,JOIN("""",""Static: "",AM16),JOIN("""",""Min: "",AM16, CHAR(10),""Max: "",AN16)))"),"") | AM16: {=_xlfn.XLOOKUP(B16,'Up Min'!A:A,'Up Min'!J:J,)} | AN16: {=_xlfn.XLOOKUP(B16,'Up Max'!A:A,'Up Max'!J:J,)} | AO16: {=CONCATENATE(_xlfn.XLOOKUP(B16,'Up Cells'!A:A,'Up Cells'!B:B,))} -> 4 | AP16: {=CONCATENATE(_xlfn.XLOOKUP(B16,'Up Rarity'!A:A,'Up Rarity'!B:B,),CHAR(10),"-")} -> Epic -
A17: {=_xlfn.XLOOKUP(B17,'Up Icon'!A:A,'Up Icon'!B:B,)} | B17: {=HYPERLINK(_xlfn.XLOOKUP('Up Names'!A14,'Up Wiki'!A:A,'Up Wiki'!B:B,),'Up Names'!A14)} -> Superheat Reaction | C17: {=_xlfn.XLOOKUP(B17,'Up Desc'!A:A,'Up Desc'!B:B,)} -> Rapidly igniting multiple targets increases the amount of fire per shot. | D17: {=_xlfn.XLOOKUP(B17,'Up Turbo'!A:A,'Up Turbo'!B:B,)} -> n/a | E17: {=_xlfn.XLOOKUP(B17,'Up Stats'!A:A,'Up Stats'!B:B,)} -> Increased Fire | F17: =IFERROR(__xludf.DUMMYFUNCTION("if(AND(G17=FALSE,H17=FALSE),,if(G17=H17,JOIN("""",""Static: "",G17),JOIN("""",""Min: "",G17, CHAR(10),""Max: "",H17)))"),"Min: 1.69 Max: 1.9") -> Min: 1.69 Max: 1.9 | G17: {=_xlfn.XLOOKUP(B17,'Up Min'!A:A,'Up Min'!B:B,)} -> 1.69 | H17: {=_xlfn.XLOOKUP(B17,'Up Max'!A:A,'Up Max'!B:B,)} -> 1.9 | I17: {=_xlfn.XLOOKUP(B17,'Up Stats'!A:A,'Up Stats'!C:C,)} | J17: =IFERROR(__xludf.DUMMYFUNCTION("if(AND(K17=FALSE,L17=FALSE),,if(K17=L17,JOIN("""",""Static: "",K17),JOIN("""",""Min: "",K17, CHAR(10),""Max: "",L17)))"),"") | K17: {=_xlfn.XLOOKUP(B17,'Up Min'!A:A,'Up Min'!C:C,)} | L17: {=_xlfn.XLOOKUP(B17,'Up Max'!A:A,'Up Max'!C:C,)} | M17: {=_xlfn.XLOOKUP(B17,'Up Stats'!A:A,'Up Stats'!D:D,)} | N17: =IFERROR(__xludf.DUMMYFUNCTION("if(AND(O17=FALSE,P17=FALSE),,if(O17=P17,JOIN("""",""Static: "",O17),JOIN("""",""Min: "",O17, CHAR(10),""Max: "",P17)))"),"") | O17: {=_xlfn.XLOOKUP(B17,'Up Min'!A:A,'Up Min'!D:D,)} | P17: {=_xlfn.XLOOKUP(B17,'Up Max'!A:A,'Up Max'!D:D,)} | Q17: {=_xlfn.XLOOKUP(B17,'Up Stats'!A:A,'Up Stats'!E:E,)} | R17: =IFERROR(__xludf.DUMMYFUNCTION("if(AND(S17=FALSE,T17=FALSE),,if(S17=T17,JOIN("""",""Static: "",S17),JOIN("""",""Min: "",S17, CHAR(10),""Max: "",T17)))"),"") | S17: {=_xlfn.XLOOKUP(B17,'Up Min'!A:A,'Up Min'!E:E,)} | T17: {=_xlfn.XLOOKUP(B17,'Up Max'!A:A,'Up Max'!E:E,)} | U17: {=_xlfn.XLOOKUP(B17,'Up Stats'!A:A,'Up Stats'!F:F,)} | V17: =IFERROR(__xludf.DUMMYFUNCTION("if(AND(W17=FALSE,X17=FALSE),,if(W17=X17,JOIN("""",""Static: "",W17),JOIN("""",""Min: "",W17, CHAR(10),""Max: "",X17)))"),"") | W17: {=_xlfn.XLOOKUP(B17,'Up Min'!A:A,'Up Min'!F:F,)} | X17: {=_xlfn.XLOOKUP(B17,'Up Max'!A:A,'Up Max'!F:F,)} | Y17: {=_xlfn.XLOOKUP(B17,'Up Stats'!A:A,'Up Stats'!G:G,)} | Z17: =IFERROR(__xludf.DUMMYFUNCTION("if(AND(AA17=FALSE,AB17=FALSE),,if(AA17=AB17,JOIN("""",""Static: "",AA17),JOIN("""",""Min: "",AA17, CHAR(10),""Max: "",AB17)))"),"") | AA17: {=_xlfn.XLOOKUP(B17,'Up Min'!A:A,'Up Min'!G:G,)} | AB17: {=_xlfn.XLOOKUP(B17,'Up Max'!A:A,'Up Max'!G:G,)} | AC17: {=_xlfn.XLOOKUP(B17,'Up Stats'!A:A,'Up Stats'!H:H,)} | AD17: =IFERROR(__xludf.DUMMYFUNCTION("if(AND(AE17=FALSE,AF17=FALSE),,if(AE17=AF17,JOIN("""",""Static: "",AE17),JOIN("""",""Min: "",AE17, CHAR(10),""Max: "",AF17)))"),"") | AE17: {=_xlfn.XLOOKUP(B17,'Up Min'!A:A,'Up Min'!H:H,)} | AF17: {=_xlfn.XLOOKUP(B17,'Up Max'!A:A,'Up Max'!H:H,)} | AG17: {=_xlfn.XLOOKUP(B17,'Up Stats'!A:A,'Up Stats'!I:I,)} | AH17: =IFERROR(__xludf.DUMMYFUNCTION("if(AND(AI17=FALSE,AJ17=FALSE),,if(AI17=AJ17,JOIN("""",""Static: "",AI17),JOIN("""",""Min: "",AI17, CHAR(10),""Max: "",AJ17)))"),"") | AI17: {=_xlfn.XLOOKUP(B17,'Up Min'!A:A,'Up Min'!I:I,)} | AJ17: {=_xlfn.XLOOKUP(B17,'Up Max'!A:A,'Up Max'!I:I,)} | AK17: {=_xlfn.XLOOKUP(B17,'Up Stats'!A:A,'Up Stats'!J:J,)} | AL17: =IFERROR(__xludf.DUMMYFUNCTION("if(AND(AM17=FALSE,AN17=FALSE),,if(AM17=AN17,JOIN("""",""Static: "",AM17),JOIN("""",""Min: "",AM17, CHAR(10),""Max: "",AN17)))"),"") | AM17: {=_xlfn.XLOOKUP(B17,'Up Min'!A:A,'Up Min'!J:J,)} | AN17: {=_xlfn.XLOOKUP(B17,'Up Max'!A:A,'Up Max'!J:J,)} | AO17: {=CONCATENATE(_xlfn.XLOOKUP(B17,'Up Cells'!A:A,'Up Cells'!B:B,))} -> 4 | AP17: {=CONCATENATE(_xlfn.XLOOKUP(B17,'Up Rarity'!A:A,'Up Rarity'!B:B,),CHAR(10),"-")} -> Epic -
A18: {=_xlfn.XLOOKUP(B18,'Up Icon'!A:A,'Up Icon'!B:B,)} | B18: {=HYPERLINK(_xlfn.XLOOKUP('Up Names'!A15,'Up Wiki'!A:A,'Up Wiki'!B:B,),'Up Names'!A15)} -> Toxin Recycling | C18: {=_xlfn.XLOOKUP(B18,'Up Desc'!A:A,'Up Desc'!B:B,)} -> Sustained damage increases amount of applied acid and damage as well as recoil. | D18: {=_xlfn.XLOOKUP(B18,'Up Turbo'!A:A,'Up Turbo'!B:B,)} -> n/a | E18: {=_xlfn.XLOOKUP(B18,'Up Stats'!A:A,'Up Stats'!B:B,)} -> Acid per Second | F18: =IFERROR(__xludf.DUMMYFUNCTION("if(AND(G18=FALSE,H18=FALSE),,if(G18=H18,JOIN("""",""Static: "",G18),JOIN("""",""Min: "",G18, CHAR(10),""Max: "",H18)))"),"Min: 2.5 Max: 3.5") -> Min: 2.5 Max: 3.5 | G18: {=_xlfn.XLOOKUP(B18,'Up Min'!A:A,'Up Min'!B:B,)} -> 2.5 | H18: {=_xlfn.XLOOKUP(B18,'Up Max'!A:A,'Up Max'!B:B,)} -> 3.5 | I18: {=_xlfn.XLOOKUP(B18,'Up Stats'!A:A,'Up Stats'!C:C,)} -> Recoil per Second | J18: =IFERROR(__xludf.DUMMYFUNCTION("if(AND(K18=FALSE,L18=FALSE),,if(K18=L18,JOIN("""",""Static: "",K18),JOIN("""",""Min: "",K18, CHAR(10),""Max: "",L18)))"),"Min: 0.7 Max: 0.8") -> Min: 0.7 Max: 0.8 | K18: {=_xlfn.XLOOKUP(B18,'Up Min'!A:A,'Up Min'!C:C,)} -> 0.7 | L18: {=_xlfn.XLOOKUP(B18,'Up Max'!A:A,'Up Max'!C:C,)} -> 0.8 | M18: {=_xlfn.XLOOKUP(B18,'Up Stats'!A:A,'Up Stats'!D:D,)} -> Max Damage | N18: =IFERROR(__xludf.DUMMYFUNCTION("if(AND(O18=FALSE,P18=FALSE),,if(O18=P18,JOIN("""",""Static: "",O18),JOIN("""",""Min: "",O18, CHAR(10),""Max: "",P18)))"),"Min: 65% Max: 80%") -> Min: 65% Max: 80% | O18: {=_xlfn.XLOOKUP(B18,'Up Min'!A:A,'Up Min'!D:D,)} -> 0.65 | P18: {=_xlfn.XLOOKUP(B18,'Up Max'!A:A,'Up Max'!D:D,)} -> 0.8 | Q18: {=_xlfn.XLOOKUP(B18,'Up Stats'!A:A,'Up Stats'!E:E,)} | R18: =IFERROR(__xludf.DUMMYFUNCTION("if(AND(S18=FALSE,T18=FALSE),,if(S18=T18,JOIN("""",""Static: "",S18),JOIN("""",""Min: "",S18, CHAR(10),""Max: "",T18)))"),"") | S18: {=_xlfn.XLOOKUP(B18,'Up Min'!A:A,'Up Min'!E:E,)} | T18: {=_xlfn.XLOOKUP(B18,'Up Max'!A:A,'Up Max'!E:E,)} | U18: {=_xlfn.XLOOKUP(B18,'Up Stats'!A:A,'Up Stats'!F:F,)} | V18: =IFERROR(__xludf.DUMMYFUNCTION("if(AND(W18=FALSE,X18=FALSE),,if(W18=X18,JOIN("""",""Static: "",W18),JOIN("""",""Min: "",W18, CHAR(10),""Max: "",X18)))"),"") | W18: {=_xlfn.XLOOKUP(B18,'Up Min'!A:A,'Up Min'!F:F,)} | X18: {=_xlfn.XLOOKUP(B18,'Up Max'!A:A,'Up Max'!F:F,)} | Y18: {=_xlfn.XLOOKUP(B18,'Up Stats'!A:A,'Up Stats'!G:G,)} | Z18: =IFERROR(__xludf.DUMMYFUNCTION("if(AND(AA18=FALSE,AB18=FALSE),,if(AA18=AB18,JOIN("""",""Static: "",AA18),JOIN("""",""Min: "",AA18, CHAR(10),""Max: "",AB18)))"),"") | AA18: {=_xlfn.XLOOKUP(B18,'Up Min'!A:A,'Up Min'!G:G,)} | AB18: {=_xlfn.XLOOKUP(B18,'Up Max'!A:A,'Up Max'!G:G,)} | AC18: {=_xlfn.XLOOKUP(B18,'Up Stats'!A:A,'Up Stats'!H:H,)} | AD18: =IFERROR(__xludf.DUMMYFUNCTION("if(AND(AE18=FALSE,AF18=FALSE),,if(AE18=AF18,JOIN("""",""Static: "",AE18),JOIN("""",""Min: "",AE18, CHAR(10),""Max: "",AF18)))"),"") | AE18: {=_xlfn.XLOOKUP(B18,'Up Min'!A:A,'Up Min'!H:H,)} | AF18: {=_xlfn.XLOOKUP(B18,'Up Max'!A:A,'Up Max'!H:H,)} | AG18: {=_xlfn.XLOOKUP(B18,'Up Stats'!A:A,'Up Stats'!I:I,)} | AH18: =IFERROR(__xludf.DUMMYFUNCTION("if(AND(AI18=FALSE,AJ18=FALSE),,if(AI18=AJ18,JOIN("""",""Static: "",AI18),JOIN("""",""Min: "",AI18, CHAR(10),""Max: "",AJ18)))"),"") | AI18: {=_xlfn.XLOOKUP(B18,'Up Min'!A:A,'Up Min'!I:I,)} | AJ18: {=_xlfn.XLOOKUP(B18,'Up Max'!A:A,'Up Max'!I:I,)} | AK18: {=_xlfn.XLOOKUP(B18,'Up Stats'!A:A,'Up Stats'!J:J,)} | AL18: =IFERROR(__xludf.DUMMYFUNCTION("if(AND(AM18=FALSE,AN18=FALSE),,if(AM18=AN18,JOIN("""",""Static: "",AM18),JOIN("""",""Min: "",AM18, CHAR(10),""Max: "",AN18)))"),"") | AM18: {=_xlfn.XLOOKUP(B18,'Up Min'!A:A,'Up Min'!J:J,)} | AN18: {=_xlfn.XLOOKUP(B18,'Up Max'!A:A,'Up Max'!J:J,)} | AO18: {=CONCATENATE(_xlfn.XLOOKUP(B18,'Up Cells'!A:A,'Up Cells'!B:B,))} -> 5 | AP18: {=CONCATENATE(_xlfn.XLOOKUP(B18,'Up Rarity'!A:A,'Up Rarity'!B:B,),CHAR(10),"-")} -> Epic -
A19: {=_xlfn.XLOOKUP(B19,'Up Icon'!A:A,'Up Icon'!B:B,)} | B19: {=HYPERLINK(_xlfn.XLOOKUP('Up Names'!A16,'Up Wiki'!A:A,'Up Wiki'!B:B,),'Up Names'!A16)} -> Charge Shield | C19: {=_xlfn.XLOOKUP(B19,'Up Desc'!A:A,'Up Desc'!B:B,)} -> Take reduced damage while charging. Charge time is increased. | D19: {=_xlfn.XLOOKUP(B19,'Up Turbo'!A:A,'Up Turbo'!B:B,)} -> n/a | E19: {=_xlfn.XLOOKUP(B19,'Up Stats'!A:A,'Up Stats'!B:B,)} -> Charge Time | F19: =IFERROR(__xludf.DUMMYFUNCTION("if(AND(G19=FALSE,H19=FALSE),,if(G19=H19,JOIN("""",""Static: "",G19),JOIN("""",""Min: "",G19, CHAR(10),""Max: "",H19)))"),"Min: 0.3 Max: 0.34") -> Min: 0.3 Max: 0.34 | G19: {=_xlfn.XLOOKUP(B19,'Up Min'!A:A,'Up Min'!B:B,)} -> 0.3 | H19: {=_xlfn.XLOOKUP(B19,'Up Max'!A:A,'Up Max'!B:B,)} -> 0.34 | I19: {=_xlfn.XLOOKUP(B19,'Up Stats'!A:A,'Up Stats'!C:C,)} -> Damage Resistance | J19: =IFERROR(__xludf.DUMMYFUNCTION("if(AND(K19=FALSE,L19=FALSE),,if(K19=L19,JOIN("""",""Static: "",K19),JOIN("""",""Min: "",K19, CHAR(10),""Max: "",L19)))"),"Min: 75% Max: 85%") -> Min: 75% Max: 85% | K19: {=_xlfn.XLOOKUP(B19,'Up Min'!A:A,'Up Min'!C:C,)} -> 0.75 | L19: {=_xlfn.XLOOKUP(B19,'Up Max'!A:A,'Up Max'!C:C,)} -> 0.85 | M19: {=_xlfn.XLOOKUP(B19,'Up Stats'!A:A,'Up Stats'!D:D,)} | N19: =IFERROR(__xludf.DUMMYFUNCTION("if(AND(O19=FALSE,P19=FALSE),,if(O19=P19,JOIN("""",""Static: "",O19),JOIN("""",""Min: "",O19, CHAR(10),""Max: "",P19)))"),"") | O19: {=_xlfn.XLOOKUP(B19,'Up Min'!A:A,'Up Min'!D:D,)} | P19: {=_xlfn.XLOOKUP(B19,'Up Max'!A:A,'Up Max'!D:D,)} | Q19: {=_xlfn.XLOOKUP(B19,'Up Stats'!A:A,'Up Stats'!E:E,)} | R19: =IFERROR(__xludf.DUMMYFUNCTION("if(AND(S19=FALSE,T19=FALSE),,if(S19=T19,JOIN("""",""Static: "",S19),JOIN("""",""Min: "",S19, CHAR(10),""Max: "",T19)))"),"") | S19: {=_xlfn.XLOOKUP(B19,'Up Min'!A:A,'Up Min'!E:E,)} | T19: {=_xlfn.XLOOKUP(B19,'Up Max'!A:A,'Up Max'!E:E,)} | U19: {=_xlfn.XLOOKUP(B19,'Up Stats'!A:A,'Up Stats'!F:F,)} | V19: =IFERROR(__xludf.DUMMYFUNCTION("if(AND(W19=FALSE,X19=FALSE),,if(W19=X19,JOIN("""",""Static: "",W19),JOIN("""",""Min: "",W19, CHAR(10),""Max: "",X19)))"),"") | W19: {=_xlfn.XLOOKUP(B19,'Up Min'!A:A,'Up Min'!F:F,)} | X19: {=_xlfn.XLOOKUP(B19,'Up Max'!A:A,'Up Max'!F:F,)} | Y19: {=_xlfn.XLOOKUP(B19,'Up Stats'!A:A,'Up Stats'!G:G,)} | Z19: =IFERROR(__xludf.DUMMYFUNCTION("if(AND(AA19=FALSE,AB19=FALSE),,if(AA19=AB19,JOIN("""",""Static: "",AA19),JOIN("""",""Min: "",AA19, CHAR(10),""Max: "",AB19)))"),"") | AA19: {=_xlfn.XLOOKUP(B19,'Up Min'!A:A,'Up Min'!G:G,)} | AB19: {=_xlfn.XLOOKUP(B19,'Up Max'!A:A,'Up Max'!G:G,)} | AC19: {=_xlfn.XLOOKUP(B19,'Up Stats'!A:A,'Up Stats'!H:H,)} | AD19: =IFERROR(__xludf.DUMMYFUNCTION("if(AND(AE19=FALSE,AF19=FALSE),,if(AE19=AF19,JOIN("""",""Static: "",AE19),JOIN("""",""Min: "",AE19, CHAR(10),""Max: "",AF19)))"),"") | AE19: {=_xlfn.XLOOKUP(B19,'Up Min'!A:A,'Up Min'!H:H,)} | AF19: {=_xlfn.XLOOKUP(B19,'Up Max'!A:A,'Up Max'!H:H,)} | AG19: {=_xlfn.XLOOKUP(B19,'Up Stats'!A:A,'Up Stats'!I:I,)} | AH19: =IFERROR(__xludf.DUMMYFUNCTION("if(AND(AI19=FALSE,AJ19=FALSE),,if(AI19=AJ19,JOIN("""",""Static: "",AI19),JOIN("""",""Min: "",AI19, CHAR(10),""Max: "",AJ19)))"),"") | AI19: {=_xlfn.XLOOKUP(B19,'Up Min'!A:A,'Up Min'!I:I,)} | AJ19: {=_xlfn.XLOOKUP(B19,'Up Max'!A:A,'Up Max'!I:I,)} | AK19: {=_xlfn.XLOOKUP(B19,'Up Stats'!A:A,'Up Stats'!J:J,)} | AL19: =IFERROR(__xludf.DUMMYFUNCTION("if(AND(AM19=FALSE,AN19=FALSE),,if(AM19=AN19,JOIN("""",""Static: "",AM19),JOIN("""",""Min: "",AM19, CHAR(10),""Max: "",AN19)))"),"") | AM19: {=_xlfn.XLOOKUP(B19,'Up Min'!A:A,'Up Min'!J:J,)} | AN19: {=_xlfn.XLOOKUP(B19,'Up Max'!A:A,'Up Max'!J:J,)} | AO19: {=CONCATENATE(_xlfn.XLOOKUP(B19,'Up Cells'!A:A,'Up Cells'!B:B,))} -> 2 | AP19: {=CONCATENATE(_xlfn.XLOOKUP(B19,'Up Rarity'!A:A,'Up Rarity'!B:B,),CHAR(10),"-")} -> Rare -
A20: {=_xlfn.XLOOKUP(B20,'Up Icon'!A:A,'Up Icon'!B:B,)} | B20: {=HYPERLINK(_xlfn.XLOOKUP('Up Names'!A17,'Up Wiki'!A:A,'Up Wiki'!B:B,),'Up Names'!A17)} -> Charged Cartridges | C20: {=_xlfn.XLOOKUP(B20,'Up Desc'!A:A,'Up Desc'!B:B,)} -> Bullets apply shock. | D20: {=_xlfn.XLOOKUP(B20,'Up Turbo'!A:A,'Up Turbo'!B:B,)} -> n/a | E20: {=_xlfn.XLOOKUP(B20,'Up Stats'!A:A,'Up Stats'!B:B,)} -> Element | F20: =IFERROR(__xludf.DUMMYFUNCTION("if(AND(G20=FALSE,H20=FALSE),,if(G20=H20,JOIN("""",""Static: "",G20),JOIN("""",""Min: "",G20, CHAR(10),""Max: "",H20)))"),"Min: 1.85 Max: 2.15") -> Min: 1.85 Max: 2.15 | G20: {=_xlfn.XLOOKUP(B20,'Up Min'!A:A,'Up Min'!B:B,)} -> 1.85 | H20: {=_xlfn.XLOOKUP(B20,'Up Max'!A:A,'Up Max'!B:B,)} -> 2.15 | I20: {=_xlfn.XLOOKUP(B20,'Up Stats'!A:A,'Up Stats'!C:C,)} | J20: =IFERROR(__xludf.DUMMYFUNCTION("if(AND(K20=FALSE,L20=FALSE),,if(K20=L20,JOIN("""",""Static: "",K20),JOIN("""",""Min: "",K20, CHAR(10),""Max: "",L20)))"),"") | K20: {=_xlfn.XLOOKUP(B20,'Up Min'!A:A,'Up Min'!C:C,)} | L20: {=_xlfn.XLOOKUP(B20,'Up Max'!A:A,'Up Max'!C:C,)} | M20: {=_xlfn.XLOOKUP(B20,'Up Stats'!A:A,'Up Stats'!D:D,)} | N20: =IFERROR(__xludf.DUMMYFUNCTION("if(AND(O20=FALSE,P20=FALSE),,if(O20=P20,JOIN("""",""Static: "",O20),JOIN("""",""Min: "",O20, CHAR(10),""Max: "",P20)))"),"") | O20: {=_xlfn.XLOOKUP(B20,'Up Min'!A:A,'Up Min'!D:D,)} | P20: {=_xlfn.XLOOKUP(B20,'Up Max'!A:A,'Up Max'!D:D,)} | Q20: {=_xlfn.XLOOKUP(B20,'Up Stats'!A:A,'Up Stats'!E:E,)} | R20: =IFERROR(__xludf.DUMMYFUNCTION("if(AND(S20=FALSE,T20=FALSE),,if(S20=T20,JOIN("""",""Static: "",S20),JOIN("""",""Min: "",S20, CHAR(10),""Max: "",T20)))"),"") | S20: {=_xlfn.XLOOKUP(B20,'Up Min'!A:A,'Up Min'!E:E,)} | T20: {=_xlfn.XLOOKUP(B20,'Up Max'!A:A,'Up Max'!E:E,)} | U20: {=_xlfn.XLOOKUP(B20,'Up Stats'!A:A,'Up Stats'!F:F,)} | V20: =IFERROR(__xludf.DUMMYFUNCTION("if(AND(W20=FALSE,X20=FALSE),,if(W20=X20,JOIN("""",""Static: "",W20),JOIN("""",""Min: "",W20, CHAR(10),""Max: "",X20)))"),"") | W20: {=_xlfn.XLOOKUP(B20,'Up Min'!A:A,'Up Min'!F:F,)} | X20: {=_xlfn.XLOOKUP(B20,'Up Max'!A:A,'Up Max'!F:F,)} | Y20: {=_xlfn.XLOOKUP(B20,'Up Stats'!A:A,'Up Stats'!G:G,)} | Z20: =IFERROR(__xludf.DUMMYFUNCTION("if(AND(AA20=FALSE,AB20=FALSE),,if(AA20=AB20,JOIN("""",""Static: "",AA20),JOIN("""",""Min: "",AA20, CHAR(10),""Max: "",AB20)))"),"") | AA20: {=_xlfn.XLOOKUP(B20,'Up Min'!A:A,'Up Min'!G:G,)} | AB20: {=_xlfn.XLOOKUP(B20,'Up Max'!A:A,'Up Max'!G:G,)} | AC20: {=_xlfn.XLOOKUP(B20,'Up Stats'!A:A,'Up Stats'!H:H,)} | AD20: =IFERROR(__xludf.DUMMYFUNCTION("if(AND(AE20=FALSE,AF20=FALSE),,if(AE20=AF20,JOIN("""",""Static: "",AE20),JOIN("""",""Min: "",AE20, CHAR(10),""Max: "",AF20)))"),"") | AE20: {=_xlfn.XLOOKUP(B20,'Up Min'!A:A,'Up Min'!H:H,)} | AF20: {=_xlfn.XLOOKUP(B20,'Up Max'!A:A,'Up Max'!H:H,)} | AG20: {=_xlfn.XLOOKUP(B20,'Up Stats'!A:A,'Up Stats'!I:I,)} | AH20: =IFERROR(__xludf.DUMMYFUNCTION("if(AND(AI20=FALSE,AJ20=FALSE),,if(AI20=AJ20,JOIN("""",""Static: "",AI20),JOIN("""",""Min: "",AI20, CHAR(10),""Max: "",AJ20)))"),"") | AI20: {=_xlfn.XLOOKUP(B20,'Up Min'!A:A,'Up Min'!I:I,)} | AJ20: {=_xlfn.XLOOKUP(B20,'Up Max'!A:A,'Up Max'!I:I,)} | AK20: {=_xlfn.XLOOKUP(B20,'Up Stats'!A:A,'Up Stats'!J:J,)} | AL20: =IFERROR(__xludf.DUMMYFUNCTION("if(AND(AM20=FALSE,AN20=FALSE),,if(AM20=AN20,JOIN("""",""Static: "",AM20),JOIN("""",""Min: "",AM20, CHAR(10),""Max: "",AN20)))"),"") | AM20: {=_xlfn.XLOOKUP(B20,'Up Min'!A:A,'Up Min'!J:J,)} | AN20: {=_xlfn.XLOOKUP(B20,'Up Max'!A:A,'Up Max'!J:J,)} | AO20: {=CONCATENATE(_xlfn.XLOOKUP(B20,'Up Cells'!A:A,'Up Cells'!B:B,))} -> 3 | AP20: {=CONCATENATE(_xlfn.XLOOKUP(B20,'Up Rarity'!A:A,'Up Rarity'!B:B,),CHAR(10),"-")} -> Rare -
A21: {=_xlfn.XLOOKUP(B21,'Up Icon'!A:A,'Up Icon'!B:B,)} | B21: {=HYPERLINK(_xlfn.XLOOKUP('Up Names'!A18,'Up Wiki'!A:A,'Up Wiki'!B:B,),'Up Names'!A18)} -> Condensed Ejection | C21: {=_xlfn.XLOOKUP(B21,'Up Desc'!A:A,'Up Desc'!B:B,)} -> Fires slow-moving plasma that deals increased damage. | D21: {=_xlfn.XLOOKUP(B21,'Up Turbo'!A:A,'Up Turbo'!B:B,)} -> n/a | E21: {=_xlfn.XLOOKUP(B21,'Up Stats'!A:A,'Up Stats'!B:B,)} -> Damage | F21: =IFERROR(__xludf.DUMMYFUNCTION("if(AND(G21=FALSE,H21=FALSE),,if(G21=H21,JOIN("""",""Static: "",G21),JOIN("""",""Min: "",G21, CHAR(10),""Max: "",H21)))"),"Min: 16% Max: 24%") -> Min: 16% Max: 24% | G21: {=_xlfn.XLOOKUP(B21,'Up Min'!A:A,'Up Min'!B:B,)} -> 0.16 | H21: {=_xlfn.XLOOKUP(B21,'Up Max'!A:A,'Up Max'!B:B,)} -> 0.24 | I21: {=_xlfn.XLOOKUP(B21,'Up Stats'!A:A,'Up Stats'!C:C,)} -> Bullet Speed | J21: =IFERROR(__xludf.DUMMYFUNCTION("if(AND(K21=FALSE,L21=FALSE),,if(K21=L21,JOIN("""",""Static: "",K21),JOIN("""",""Min: "",K21, CHAR(10),""Max: "",L21)))"),"Min: 17 Max: 23") -> Min: 17 Max: 23 | K21: {=_xlfn.XLOOKUP(B21,'Up Min'!A:A,'Up Min'!C:C,)} -> 17 | L21: {=_xlfn.XLOOKUP(B21,'Up Max'!A:A,'Up Max'!C:C,)} -> 23 | M21: {=_xlfn.XLOOKUP(B21,'Up Stats'!A:A,'Up Stats'!D:D,)} -> Bullet Size | N21: =IFERROR(__xludf.DUMMYFUNCTION("if(AND(O21=FALSE,P21=FALSE),,if(O21=P21,JOIN("""",""Static: "",O21),JOIN("""",""Min: "",O21, CHAR(10),""Max: "",P21)))"),"Static: 0.5") -> Static: 0.5 | O21: {=_xlfn.XLOOKUP(B21,'Up Min'!A:A,'Up Min'!D:D,)} -> 0.5 | P21: {=_xlfn.XLOOKUP(B21,'Up Max'!A:A,'Up Max'!D:D,)} -> 0.5 | Q21: {=_xlfn.XLOOKUP(B21,'Up Stats'!A:A,'Up Stats'!E:E,)} -> Falloff Start | R21: =IFERROR(__xludf.DUMMYFUNCTION("if(AND(S21=FALSE,T21=FALSE),,if(S21=T21,JOIN("""",""Static: "",S21),JOIN("""",""Min: "",S21, CHAR(10),""Max: "",T21)))"),"Static: 60") -> Static: 60 | S21: {=_xlfn.XLOOKUP(B21,'Up Min'!A:A,'Up Min'!E:E,)} -> 60 | T21: {=_xlfn.XLOOKUP(B21,'Up Max'!A:A,'Up Max'!E:E,)} -> 60 | U21: {=_xlfn.XLOOKUP(B21,'Up Stats'!A:A,'Up Stats'!F:F,)} -> Falloff End | V21: =IFERROR(__xludf.DUMMYFUNCTION("if(AND(W21=FALSE,X21=FALSE),,if(W21=X21,JOIN("""",""Static: "",W21),JOIN("""",""Min: "",W21, CHAR(10),""Max: "",X21)))"),"Static: 70") -> Static: 70 | W21: {=_xlfn.XLOOKUP(B21,'Up Min'!A:A,'Up Min'!F:F,)} -> 70 | X21: {=_xlfn.XLOOKUP(B21,'Up Max'!A:A,'Up Max'!F:F,)} -> 70 | Y21: {=_xlfn.XLOOKUP(B21,'Up Stats'!A:A,'Up Stats'!G:G,)} -> Range | Z21: =IFERROR(__xludf.DUMMYFUNCTION("if(AND(AA21=FALSE,AB21=FALSE),,if(AA21=AB21,JOIN("""",""Static: "",AA21),JOIN("""",""Min: "",AA21, CHAR(10),""Max: "",AB21)))"),"Static: 80") -> Static: 80 | AA21: {=_xlfn.XLOOKUP(B21,'Up Min'!A:A,'Up Min'!G:G,)} -> 80 | AB21: {=_xlfn.XLOOKUP(B21,'Up Max'!A:A,'Up Max'!G:G,)} -> 80 | AC21: {=_xlfn.XLOOKUP(B21,'Up Stats'!A:A,'Up Stats'!H:H,)} -> Horizontal Spread | AD21: =IFERROR(__xludf.DUMMYFUNCTION("if(AND(AE21=FALSE,AF21=FALSE),,if(AE21=AF21,JOIN("""",""Static: "",AE21),JOIN("""",""Min: "",AE21, CHAR(10),""Max: "",AF21)))"),"Min: 1.75 Max: 2.2") -> Min: 1.75 Max: 2.2 | AE21: {=_xlfn.XLOOKUP(B21,'Up Min'!A:A,'Up Min'!H:H,)} -> 1.75 | AF21: {=_xlfn.XLOOKUP(B21,'Up Max'!A:A,'Up Max'!H:H,)} -> 2.2 | AG21: {=_xlfn.XLOOKUP(B21,'Up Stats'!A:A,'Up Stats'!I:I,)} -> Vertical Spread | AH21: =IFERROR(__xludf.DUMMYFUNCTION("if(AND(AI21=FALSE,AJ21=FALSE),,if(AI21=AJ21,JOIN("""",""Static: "",AI21),JOIN("""",""Min: "",AI21, CHAR(10),""Max: "",AJ21)))"),"Min: 1.75 Max: 2.2") -> Min: 1.75 Max: 2.2 | AI21: {=_xlfn.XLOOKUP(B21,'Up Min'!A:A,'Up Min'!I:I,)} -> 1.75 | AJ21: {=_xlfn.XLOOKUP(B21,'Up Max'!A:A,'Up Max'!I:I,)} -> 2.2 | AK21: {=_xlfn.XLOOKUP(B21,'Up Stats'!A:A,'Up Stats'!J:J,)} | AL21: =IFERROR(__xludf.DUMMYFUNCTION("if(AND(AM21=FALSE,AN21=FALSE),,if(AM21=AN21,JOIN("""",""Static: "",AM21),JOIN("""",""Min: "",AM21, CHAR(10),""Max: "",AN21)))"),"") | AM21: {=_xlfn.XLOOKUP(B21,'Up Min'!A:A,'Up Min'!J:J,)} | AN21: {=_xlfn.XLOOKUP(B21,'Up Max'!A:A,'Up Max'!J:J,)} | AO21: {=CONCATENATE(_xlfn.XLOOKUP(B21,'Up Cells'!A:A,'Up Cells'!B:B,))} -> 5 | AP21: {=CONCATENATE(_xlfn.XLOOKUP(B21,'Up Rarity'!A:A,'Up Rarity'!B:B,),CHAR(10),"-")} -> Rare -
A22: {=_xlfn.XLOOKUP(B22,'Up Icon'!A:A,'Up Icon'!B:B,)} | B22: {=HYPERLINK(_xlfn.XLOOKUP('Up Names'!A19,'Up Wiki'!A:A,'Up Wiki'!B:B,),'Up Names'!A19)} -> Corrosive Plasma | C22: {=_xlfn.XLOOKUP(B22,'Up Desc'!A:A,'Up Desc'!B:B,)} -> Bullets apply acid. | D22: {=_xlfn.XLOOKUP(B22,'Up Turbo'!A:A,'Up Turbo'!B:B,)} -> n/a | E22: {=_xlfn.XLOOKUP(B22,'Up Stats'!A:A,'Up Stats'!B:B,)} -> Element | F22: =IFERROR(__xludf.DUMMYFUNCTION("if(AND(G22=FALSE,H22=FALSE),,if(G22=H22,JOIN("""",""Static: "",G22),JOIN("""",""Min: "",G22, CHAR(10),""Max: "",H22)))"),"Min: 1.85 Max: 2.15") -> Min: 1.85 Max: 2.15 | G22: {=_xlfn.XLOOKUP(B22,'Up Min'!A:A,'Up Min'!B:B,)} -> 1.85 | H22: {=_xlfn.XLOOKUP(B22,'Up Max'!A:A,'Up Max'!B:B,)} -> 2.15 | I22: {=_xlfn.XLOOKUP(B22,'Up Stats'!A:A,'Up Stats'!C:C,)} | J22: =IFERROR(__xludf.DUMMYFUNCTION("if(AND(K22=FALSE,L22=FALSE),,if(K22=L22,JOIN("""",""Static: "",K22),JOIN("""",""Min: "",K22, CHAR(10),""Max: "",L22)))"),"") | K22: {=_xlfn.XLOOKUP(B22,'Up Min'!A:A,'Up Min'!C:C,)} | L22: {=_xlfn.XLOOKUP(B22,'Up Max'!A:A,'Up Max'!C:C,)} | M22: {=_xlfn.XLOOKUP(B22,'Up Stats'!A:A,'Up Stats'!D:D,)} | N22: =IFERROR(__xludf.DUMMYFUNCTION("if(AND(O22=FALSE,P22=FALSE),,if(O22=P22,JOIN("""",""Static: "",O22),JOIN("""",""Min: "",O22, CHAR(10),""Max: "",P22)))"),"") | O22: {=_xlfn.XLOOKUP(B22,'Up Min'!A:A,'Up Min'!D:D,)} | P22: {=_xlfn.XLOOKUP(B22,'Up Max'!A:A,'Up Max'!D:D,)} | Q22: {=_xlfn.XLOOKUP(B22,'Up Stats'!A:A,'Up Stats'!E:E,)} | R22: =IFERROR(__xludf.DUMMYFUNCTION("if(AND(S22=FALSE,T22=FALSE),,if(S22=T22,JOIN("""",""Static: "",S22),JOIN("""",""Min: "",S22, CHAR(10),""Max: "",T22)))"),"") | S22: {=_xlfn.XLOOKUP(B22,'Up Min'!A:A,'Up Min'!E:E,)} | T22: {=_xlfn.XLOOKUP(B22,'Up Max'!A:A,'Up Max'!E:E,)} | U22: {=_xlfn.XLOOKUP(B22,'Up Stats'!A:A,'Up Stats'!F:F,)} | V22: =IFERROR(__xludf.DUMMYFUNCTION("if(AND(W22=FALSE,X22=FALSE),,if(W22=X22,JOIN("""",""Static: "",W22),JOIN("""",""Min: "",W22, CHAR(10),""Max: "",X22)))"),"") | W22: {=_xlfn.XLOOKUP(B22,'Up Min'!A:A,'Up Min'!F:F,)} | X22: {=_xlfn.XLOOKUP(B22,'Up Max'!A:A,'Up Max'!F:F,)} | Y22: {=_xlfn.XLOOKUP(B22,'Up Stats'!A:A,'Up Stats'!G:G,)} | Z22: =IFERROR(__xludf.DUMMYFUNCTION("if(AND(AA22=FALSE,AB22=FALSE),,if(AA22=AB22,JOIN("""",""Static: "",AA22),JOIN("""",""Min: "",AA22, CHAR(10),""Max: "",AB22)))"),"") | AA22: {=_xlfn.XLOOKUP(B22,'Up Min'!A:A,'Up Min'!G:G,)} | AB22: {=_xlfn.XLOOKUP(B22,'Up Max'!A:A,'Up Max'!G:G,)} | AC22: {=_xlfn.XLOOKUP(B22,'Up Stats'!A:A,'Up Stats'!H:H,)} | AD22: =IFERROR(__xludf.DUMMYFUNCTION("if(AND(AE22=FALSE,AF22=FALSE),,if(AE22=AF22,JOIN("""",""Static: "",AE22),JOIN("""",""Min: "",AE22, CHAR(10),""Max: "",AF22)))"),"") | AE22: {=_xlfn.XLOOKUP(B22,'Up Min'!A:A,'Up Min'!H:H,)} | AF22: {=_xlfn.XLOOKUP(B22,'Up Max'!A:A,'Up Max'!H:H,)} | AG22: {=_xlfn.XLOOKUP(B22,'Up Stats'!A:A,'Up Stats'!I:I,)} | AH22: =IFERROR(__xludf.DUMMYFUNCTION("if(AND(AI22=FALSE,AJ22=FALSE),,if(AI22=AJ22,JOIN("""",""Static: "",AI22),JOIN("""",""Min: "",AI22, CHAR(10),""Max: "",AJ22)))"),"") | AI22: {=_xlfn.XLOOKUP(B22,'Up Min'!A:A,'Up Min'!I:I,)} | AJ22: {=_xlfn.XLOOKUP(B22,'Up Max'!A:A,'Up Max'!I:I,)} | AK22: {=_xlfn.XLOOKUP(B22,'Up Stats'!A:A,'Up Stats'!J:J,)} | AL22: =IFERROR(__xludf.DUMMYFUNCTION("if(AND(AM22=FALSE,AN22=FALSE),,if(AM22=AN22,JOIN("""",""Static: "",AM22),JOIN("""",""Min: "",AM22, CHAR(10),""Max: "",AN22)))"),"") | AM22: {=_xlfn.XLOOKUP(B22,'Up Min'!A:A,'Up Min'!J:J,)} | AN22: {=_xlfn.XLOOKUP(B22,'Up Max'!A:A,'Up Max'!J:J,)} | AO22: {=CONCATENATE(_xlfn.XLOOKUP(B22,'Up Cells'!A:A,'Up Cells'!B:B,))} -> 3 | AP22: {=CONCATENATE(_xlfn.XLOOKUP(B22,'Up Rarity'!A:A,'Up Rarity'!B:B,),CHAR(10),"-")} -> Rare -
A23: {=_xlfn.XLOOKUP(B23,'Up Icon'!A:A,'Up Icon'!B:B,)} | B23: {=HYPERLINK(_xlfn.XLOOKUP('Up Names'!A20,'Up Wiki'!A:A,'Up Wiki'!B:B,),'Up Names'!A20)} -> Decay Energy | C23: {=_xlfn.XLOOKUP(B23,'Up Desc'!A:A,'Up Desc'!B:B,)} -> Bullets apply decay. | D23: {=_xlfn.XLOOKUP(B23,'Up Turbo'!A:A,'Up Turbo'!B:B,)} -> n/a | E23: {=_xlfn.XLOOKUP(B23,'Up Stats'!A:A,'Up Stats'!B:B,)} -> Element | F23: =IFERROR(__xludf.DUMMYFUNCTION("if(AND(G23=FALSE,H23=FALSE),,if(G23=H23,JOIN("""",""Static: "",G23),JOIN("""",""Min: "",G23, CHAR(10),""Max: "",H23)))"),"Min: 1.85 Max: 2.15") -> Min: 1.85 Max: 2.15 | G23: {=_xlfn.XLOOKUP(B23,'Up Min'!A:A,'Up Min'!B:B,)} -> 1.85 | H23: {=_xlfn.XLOOKUP(B23,'Up Max'!A:A,'Up Max'!B:B,)} -> 2.15 | I23: {=_xlfn.XLOOKUP(B23,'Up Stats'!A:A,'Up Stats'!C:C,)} | J23: =IFERROR(__xludf.DUMMYFUNCTION("if(AND(K23=FALSE,L23=FALSE),,if(K23=L23,JOIN("""",""Static: "",K23),JOIN("""",""Min: "",K23, CHAR(10),""Max: "",L23)))"),"") | K23: {=_xlfn.XLOOKUP(B23,'Up Min'!A:A,'Up Min'!C:C,)} | L23: {=_xlfn.XLOOKUP(B23,'Up Max'!A:A,'Up Max'!C:C,)} | M23: {=_xlfn.XLOOKUP(B23,'Up Stats'!A:A,'Up Stats'!D:D,)} | N23: =IFERROR(__xludf.DUMMYFUNCTION("if(AND(O23=FALSE,P23=FALSE),,if(O23=P23,JOIN("""",""Static: "",O23),JOIN("""",""Min: "",O23, CHAR(10),""Max: "",P23)))"),"") | O23: {=_xlfn.XLOOKUP(B23,'Up Min'!A:A,'Up Min'!D:D,)} | P23: {=_xlfn.XLOOKUP(B23,'Up Max'!A:A,'Up Max'!D:D,)} | Q23: {=_xlfn.XLOOKUP(B23,'Up Stats'!A:A,'Up Stats'!E:E,)} | R23: =IFERROR(__xludf.DUMMYFUNCTION("if(AND(S23=FALSE,T23=FALSE),,if(S23=T23,JOIN("""",""Static: "",S23),JOIN("""",""Min: "",S23, CHAR(10),""Max: "",T23)))"),"") | S23: {=_xlfn.XLOOKUP(B23,'Up Min'!A:A,'Up Min'!E:E,)} | T23: {=_xlfn.XLOOKUP(B23,'Up Max'!A:A,'Up Max'!E:E,)} | U23: {=_xlfn.XLOOKUP(B23,'Up Stats'!A:A,'Up Stats'!F:F,)} | V23: =IFERROR(__xludf.DUMMYFUNCTION("if(AND(W23=FALSE,X23=FALSE),,if(W23=X23,JOIN("""",""Static: "",W23),JOIN("""",""Min: "",W23, CHAR(10),""Max: "",X23)))"),"") | W23: {=_xlfn.XLOOKUP(B23,'Up Min'!A:A,'Up Min'!F:F,)} | X23: {=_xlfn.XLOOKUP(B23,'Up Max'!A:A,'Up Max'!F:F,)} | Y23: {=_xlfn.XLOOKUP(B23,'Up Stats'!A:A,'Up Stats'!G:G,)} | Z23: =IFERROR(__xludf.DUMMYFUNCTION("if(AND(AA23=FALSE,AB23=FALSE),,if(AA23=AB23,JOIN("""",""Static: "",AA23),JOIN("""",""Min: "",AA23, CHAR(10),""Max: "",AB23)))"),"") | AA23: {=_xlfn.XLOOKUP(B23,'Up Min'!A:A,'Up Min'!G:G,)} | AB23: {=_xlfn.XLOOKUP(B23,'Up Max'!A:A,'Up Max'!G:G,)} | AC23: {=_xlfn.XLOOKUP(B23,'Up Stats'!A:A,'Up Stats'!H:H,)} | AD23: =IFERROR(__xludf.DUMMYFUNCTION("if(AND(AE23=FALSE,AF23=FALSE),,if(AE23=AF23,JOIN("""",""Static: "",AE23),JOIN("""",""Min: "",AE23, CHAR(10),""Max: "",AF23)))"),"") | AE23: {=_xlfn.XLOOKUP(B23,'Up Min'!A:A,'Up Min'!H:H,)} | AF23: {=_xlfn.XLOOKUP(B23,'Up Max'!A:A,'Up Max'!H:H,)} | AG23: {=_xlfn.XLOOKUP(B23,'Up Stats'!A:A,'Up Stats'!I:I,)} | AH23: =IFERROR(__xludf.DUMMYFUNCTION("if(AND(AI23=FALSE,AJ23=FALSE),,if(AI23=AJ23,JOIN("""",""Static: "",AI23),JOIN("""",""Min: "",AI23, CHAR(10),""Max: "",AJ23)))"),"") | AI23: {=_xlfn.XLOOKUP(B23,'Up Min'!A:A,'Up Min'!I:I,)} | AJ23: {=_xlfn.XLOOKUP(B23,'Up Max'!A:A,'Up Max'!I:I,)} | AK23: {=_xlfn.XLOOKUP(B23,'Up Stats'!A:A,'Up Stats'!J:J,)} | AL23: =IFERROR(__xludf.DUMMYFUNCTION("if(AND(AM23=FALSE,AN23=FALSE),,if(AM23=AN23,JOIN("""",""Static: "",AM23),JOIN("""",""Min: "",AM23, CHAR(10),""Max: "",AN23)))"),"") | AM23: {=_xlfn.XLOOKUP(B23,'Up Min'!A:A,'Up Min'!J:J,)} | AN23: {=_xlfn.XLOOKUP(B23,'Up Max'!A:A,'Up Max'!J:J,)} | AO23: {=CONCATENATE(_xlfn.XLOOKUP(B23,'Up Cells'!A:A,'Up Cells'!B:B,))} -> 3 | AP23: {=CONCATENATE(_xlfn.XLOOKUP(B23,'Up Rarity'!A:A,'Up Rarity'!B:B,),CHAR(10),"-")} -> Rare -
A24: {=_xlfn.XLOOKUP(B24,'Up Icon'!A:A,'Up Icon'!B:B,)} | B24: {=HYPERLINK(_xlfn.XLOOKUP('Up Names'!A21,'Up Wiki'!A:A,'Up Wiki'!B:B,),'Up Names'!A21)} -> Double Shot | C24: {=_xlfn.XLOOKUP(B24,'Up Desc'!A:A,'Up Desc'!B:B,)} -> Fires two bullets at once. Magazine size and fire rate are decreased. | D24: {=_xlfn.XLOOKUP(B24,'Up Turbo'!A:A,'Up Turbo'!B:B,)} -> n/a | E24: {=_xlfn.XLOOKUP(B24,'Up Stats'!A:A,'Up Stats'!B:B,)} -> Bullets per Shot | F24: =IFERROR(__xludf.DUMMYFUNCTION("if(AND(G24=FALSE,H24=FALSE),,if(G24=H24,JOIN("""",""Static: "",G24),JOIN("""",""Min: "",G24, CHAR(10),""Max: "",H24)))"),"Static: 1") -> Static: 1 | G24: {=_xlfn.XLOOKUP(B24,'Up Min'!A:A,'Up Min'!B:B,)} -> 1 | H24: {=_xlfn.XLOOKUP(B24,'Up Max'!A:A,'Up Max'!B:B,)} -> 1 | I24: {=_xlfn.XLOOKUP(B24,'Up Stats'!A:A,'Up Stats'!C:C,)} -> Magazine Size | J24: =IFERROR(__xludf.DUMMYFUNCTION("if(AND(K24=FALSE,L24=FALSE),,if(K24=L24,JOIN("""",""Static: "",K24),JOIN("""",""Min: "",K24, CHAR(10),""Max: "",L24)))"),"Min: -40% Max: -20%") -> Min: -40% Max: -20% | K24: {=_xlfn.XLOOKUP(B24,'Up Min'!A:A,'Up Min'!C:C,)} -> -0.4 | L24: {=_xlfn.XLOOKUP(B24,'Up Max'!A:A,'Up Max'!C:C,)} -> -0.2 | M24: {=_xlfn.XLOOKUP(B24,'Up Stats'!A:A,'Up Stats'!D:D,)} -> Fire Rate | N24: =IFERROR(__xludf.DUMMYFUNCTION("if(AND(O24=FALSE,P24=FALSE),,if(O24=P24,JOIN("""",""Static: "",O24),JOIN("""",""Min: "",O24, CHAR(10),""Max: "",P24)))"),"Min: -23.08% Max: -31.74%") -> Min: -23.08% Max: -31.74% | O24: {=_xlfn.XLOOKUP(B24,'Up Min'!A:A,'Up Min'!D:D,)} -> -0.2308 | P24: {=_xlfn.XLOOKUP(B24,'Up Max'!A:A,'Up Max'!D:D,)} -> -0.3174 | Q24: {=_xlfn.XLOOKUP(B24,'Up Stats'!A:A,'Up Stats'!E:E,)} -> Horizontal Spread | R24: =IFERROR(__xludf.DUMMYFUNCTION("if(AND(S24=FALSE,T24=FALSE),,if(S24=T24,JOIN("""",""Static: "",S24),JOIN("""",""Min: "",S24, CHAR(10),""Max: "",T24)))"),"Min: 3 Max: 5") -> Min: 3 Max: 5 | S24: {=_xlfn.XLOOKUP(B24,'Up Min'!A:A,'Up Min'!E:E,)} -> 3 | T24: {=_xlfn.XLOOKUP(B24,'Up Max'!A:A,'Up Max'!E:E,)} -> 5 | U24: {=_xlfn.XLOOKUP(B24,'Up Stats'!A:A,'Up Stats'!F:F,)} | V24: =IFERROR(__xludf.DUMMYFUNCTION("if(AND(W24=FALSE,X24=FALSE),,if(W24=X24,JOIN("""",""Static: "",W24),JOIN("""",""Min: "",W24, CHAR(10),""Max: "",X24)))"),"") | W24: {=_xlfn.XLOOKUP(B24,'Up Min'!A:A,'Up Min'!F:F,)} | X24: {=_xlfn.XLOOKUP(B24,'Up Max'!A:A,'Up Max'!F:F,)} | Y24: {=_xlfn.XLOOKUP(B24,'Up Stats'!A:A,'Up Stats'!G:G,)} | Z24: =IFERROR(__xludf.DUMMYFUNCTION("if(AND(AA24=FALSE,AB24=FALSE),,if(AA24=AB24,JOIN("""",""Static: "",AA24),JOIN("""",""Min: "",AA24, CHAR(10),""Max: "",AB24)))"),"") | AA24: {=_xlfn.XLOOKUP(B24,'Up Min'!A:A,'Up Min'!G:G,)} | AB24: {=_xlfn.XLOOKUP(B24,'Up Max'!A:A,'Up Max'!G:G,)} | AC24: {=_xlfn.XLOOKUP(B24,'Up Stats'!A:A,'Up Stats'!H:H,)} | AD24: =IFERROR(__xludf.DUMMYFUNCTION("if(AND(AE24=FALSE,AF24=FALSE),,if(AE24=AF24,JOIN("""",""Static: "",AE24),JOIN("""",""Min: "",AE24, CHAR(10),""Max: "",AF24)))"),"") | AE24: {=_xlfn.XLOOKUP(B24,'Up Min'!A:A,'Up Min'!H:H,)} | AF24: {=_xlfn.XLOOKUP(B24,'Up Max'!A:A,'Up Max'!H:H,)} | AG24: {=_xlfn.XLOOKUP(B24,'Up Stats'!A:A,'Up Stats'!I:I,)} | AH24: =IFERROR(__xludf.DUMMYFUNCTION("if(AND(AI24=FALSE,AJ24=FALSE),,if(AI24=AJ24,JOIN("""",""Static: "",AI24),JOIN("""",""Min: "",AI24, CHAR(10),""Max: "",AJ24)))"),"") | AI24: {=_xlfn.XLOOKUP(B24,'Up Min'!A:A,'Up Min'!I:I,)} | AJ24: {=_xlfn.XLOOKUP(B24,'Up Max'!A:A,'Up Max'!I:I,)} | AK24: {=_xlfn.XLOOKUP(B24,'Up Stats'!A:A,'Up Stats'!J:J,)} | AL24: =IFERROR(__xludf.DUMMYFUNCTION("if(AND(AM24=FALSE,AN24=FALSE),,if(AM24=AN24,JOIN("""",""Static: "",AM24),JOIN("""",""Min: "",AM24, CHAR(10),""Max: "",AN24)))"),"") | AM24: {=_xlfn.XLOOKUP(B24,'Up Min'!A:A,'Up Min'!J:J,)} | AN24: {=_xlfn.XLOOKUP(B24,'Up Max'!A:A,'Up Max'!J:J,)} | AO24: {=CONCATENATE(_xlfn.XLOOKUP(B24,'Up Cells'!A:A,'Up Cells'!B:B,))} -> 5 | AP24: {=CONCATENATE(_xlfn.XLOOKUP(B24,'Up Rarity'!A:A,'Up Rarity'!B:B,),CHAR(10),"-")} -> Rare -
A25: {=_xlfn.XLOOKUP(B25,'Up Icon'!A:A,'Up Icon'!B:B,)} | B25: {=HYPERLINK(_xlfn.XLOOKUP('Up Names'!A22,'Up Wiki'!A:A,'Up Wiki'!B:B,),'Up Names'!A22)} -> Elemental Discharge | C25: {=_xlfn.XLOOKUP(B25,'Up Desc'!A:A,'Up Desc'!B:B,)} -> Charges up to release an elemental discharge that damages any nearby targets. | D25: {=_xlfn.XLOOKUP(B25,'Up Turbo'!A:A,'Up Turbo'!B:B,)} -> n/a | E25: {=_xlfn.XLOOKUP(B25,'Up Stats'!A:A,'Up Stats'!B:B,)} -> Charge Time | F25: =IFERROR(__xludf.DUMMYFUNCTION("if(AND(G25=FALSE,H25=FALSE),,if(G25=H25,JOIN("""",""Static: "",G25),JOIN("""",""Min: "",G25, CHAR(10),""Max: "",H25)))"),"Min: 0.5 Max: 0.68") -> Min: 0.5 Max: 0.68 | G25: {=_xlfn.XLOOKUP(B25,'Up Min'!A:A,'Up Min'!B:B,)} -> 0.5 | H25: {=_xlfn.XLOOKUP(B25,'Up Max'!A:A,'Up Max'!B:B,)} -> 0.68 | I25: {=_xlfn.XLOOKUP(B25,'Up Stats'!A:A,'Up Stats'!C:C,)} -> Size | J25: =IFERROR(__xludf.DUMMYFUNCTION("if(AND(K25=FALSE,L25=FALSE),,if(K25=L25,JOIN("""",""Static: "",K25),JOIN("""",""Min: "",K25, CHAR(10),""Max: "",L25)))"),"Min: 4 Max: 5") -> Min: 4 Max: 5 | K25: {=_xlfn.XLOOKUP(B25,'Up Min'!A:A,'Up Min'!C:C,)} -> 4 | L25: {=_xlfn.XLOOKUP(B25,'Up Max'!A:A,'Up Max'!C:C,)} -> 5 | M25: {=_xlfn.XLOOKUP(B25,'Up Stats'!A:A,'Up Stats'!D:D,)} -> Damage | N25: =IFERROR(__xludf.DUMMYFUNCTION("if(AND(O25=FALSE,P25=FALSE),,if(O25=P25,JOIN("""",""Static: "",O25),JOIN("""",""Min: "",O25, CHAR(10),""Max: "",P25)))"),"Min: 26 Max: 63") -> Min: 26 Max: 63 | O25: {=_xlfn.XLOOKUP(B25,'Up Min'!A:A,'Up Min'!D:D,)} -> 26 | P25: {=_xlfn.XLOOKUP(B25,'Up Max'!A:A,'Up Max'!D:D,)} -> 63 | Q25: {=_xlfn.XLOOKUP(B25,'Up Stats'!A:A,'Up Stats'!E:E,)} | R25: =IFERROR(__xludf.DUMMYFUNCTION("if(AND(S25=FALSE,T25=FALSE),,if(S25=T25,JOIN("""",""Static: "",S25),JOIN("""",""Min: "",S25, CHAR(10),""Max: "",T25)))"),"") | S25: {=_xlfn.XLOOKUP(B25,'Up Min'!A:A,'Up Min'!E:E,)} | T25: {=_xlfn.XLOOKUP(B25,'Up Max'!A:A,'Up Max'!E:E,)} | U25: {=_xlfn.XLOOKUP(B25,'Up Stats'!A:A,'Up Stats'!F:F,)} | V25: =IFERROR(__xludf.DUMMYFUNCTION("if(AND(W25=FALSE,X25=FALSE),,if(W25=X25,JOIN("""",""Static: "",W25),JOIN("""",""Min: "",W25, CHAR(10),""Max: "",X25)))"),"") | W25: {=_xlfn.XLOOKUP(B25,'Up Min'!A:A,'Up Min'!F:F,)} | X25: {=_xlfn.XLOOKUP(B25,'Up Max'!A:A,'Up Max'!F:F,)} | Y25: {=_xlfn.XLOOKUP(B25,'Up Stats'!A:A,'Up Stats'!G:G,)} | Z25: =IFERROR(__xludf.DUMMYFUNCTION("if(AND(AA25=FALSE,AB25=FALSE),,if(AA25=AB25,JOIN("""",""Static: "",AA25),JOIN("""",""Min: "",AA25, CHAR(10),""Max: "",AB25)))"),"") | AA25: {=_xlfn.XLOOKUP(B25,'Up Min'!A:A,'Up Min'!G:G,)} | AB25: {=_xlfn.XLOOKUP(B25,'Up Max'!A:A,'Up Max'!G:G,)} | AC25: {=_xlfn.XLOOKUP(B25,'Up Stats'!A:A,'Up Stats'!H:H,)} | AD25: =IFERROR(__xludf.DUMMYFUNCTION("if(AND(AE25=FALSE,AF25=FALSE),,if(AE25=AF25,JOIN("""",""Static: "",AE25),JOIN("""",""Min: "",AE25, CHAR(10),""Max: "",AF25)))"),"") | AE25: {=_xlfn.XLOOKUP(B25,'Up Min'!A:A,'Up Min'!H:H,)} | AF25: {=_xlfn.XLOOKUP(B25,'Up Max'!A:A,'Up Max'!H:H,)} | AG25: {=_xlfn.XLOOKUP(B25,'Up Stats'!A:A,'Up Stats'!I:I,)} | AH25: =IFERROR(__xludf.DUMMYFUNCTION("if(AND(AI25=FALSE,AJ25=FALSE),,if(AI25=AJ25,JOIN("""",""Static: "",AI25),JOIN("""",""Min: "",AI25, CHAR(10),""Max: "",AJ25)))"),"") | AI25: {=_xlfn.XLOOKUP(B25,'Up Min'!A:A,'Up Min'!I:I,)} | AJ25: {=_xlfn.XLOOKUP(B25,'Up Max'!A:A,'Up Max'!I:I,)} | AK25: {=_xlfn.XLOOKUP(B25,'Up Stats'!A:A,'Up Stats'!J:J,)} | AL25: =IFERROR(__xludf.DUMMYFUNCTION("if(AND(AM25=FALSE,AN25=FALSE),,if(AM25=AN25,JOIN("""",""Static: "",AM25),JOIN("""",""Min: "",AM25, CHAR(10),""Max: "",AN25)))"),"") | AM25: {=_xlfn.XLOOKUP(B25,'Up Min'!A:A,'Up Min'!J:J,)} | AN25: {=_xlfn.XLOOKUP(B25,'Up Max'!A:A,'Up Max'!J:J,)} | AO25: {=CONCATENATE(_xlfn.XLOOKUP(B25,'Up Cells'!A:A,'Up Cells'!B:B,))} -> 4 | AP25: {=CONCATENATE(_xlfn.XLOOKUP(B25,'Up Rarity'!A:A,'Up Rarity'!B:B,),CHAR(10),"-")} -> Rare -
A26: {=_xlfn.XLOOKUP(B26,'Up Icon'!A:A,'Up Icon'!B:B,)} | B26: {=HYPERLINK(_xlfn.XLOOKUP('Up Names'!A23,'Up Wiki'!A:A,'Up Wiki'!B:B,),'Up Names'!A23)} -> Energy Convergence | C26: {=_xlfn.XLOOKUP(B26,'Up Desc'!A:A,'Up Desc'!B:B,)} -> Targets taking damage over time from your ignition, electrocution, or corrosion give you stacks of Power. Hold RELOAD to convert all Power stacks into overflow ammo. | D26: {=_xlfn.XLOOKUP(B26,'Up Turbo'!A:A,'Up Turbo'!B:B,)} -> n/a | E26: {=_xlfn.XLOOKUP(B26,'Up Stats'!A:A,'Up Stats'!B:B,)} -> Ammo per Stack | F26: =IFERROR(__xludf.DUMMYFUNCTION("if(AND(G26=FALSE,H26=FALSE),,if(G26=H26,JOIN("""",""Static: "",G26),JOIN("""",""Min: "",G26, CHAR(10),""Max: "",H26)))"),"Min: 0.75 Max: 1.2") -> Min: 0.75 Max: 1.2 | G26: {=_xlfn.XLOOKUP(B26,'Up Min'!A:A,'Up Min'!B:B,)} -> 0.75 | H26: {=_xlfn.XLOOKUP(B26,'Up Max'!A:A,'Up Max'!B:B,)} -> 1.2 | I26: {=_xlfn.XLOOKUP(B26,'Up Stats'!A:A,'Up Stats'!C:C,)} | J26: =IFERROR(__xludf.DUMMYFUNCTION("if(AND(K26=FALSE,L26=FALSE),,if(K26=L26,JOIN("""",""Static: "",K26),JOIN("""",""Min: "",K26, CHAR(10),""Max: "",L26)))"),"") | K26: {=_xlfn.XLOOKUP(B26,'Up Min'!A:A,'Up Min'!C:C,)} | L26: {=_xlfn.XLOOKUP(B26,'Up Max'!A:A,'Up Max'!C:C,)} | M26: {=_xlfn.XLOOKUP(B26,'Up Stats'!A:A,'Up Stats'!D:D,)} | N26: =IFERROR(__xludf.DUMMYFUNCTION("if(AND(O26=FALSE,P26=FALSE),,if(O26=P26,JOIN("""",""Static: "",O26),JOIN("""",""Min: "",O26, CHAR(10),""Max: "",P26)))"),"") | O26: {=_xlfn.XLOOKUP(B26,'Up Min'!A:A,'Up Min'!D:D,)} | P26: {=_xlfn.XLOOKUP(B26,'Up Max'!A:A,'Up Max'!D:D,)} | Q26: {=_xlfn.XLOOKUP(B26,'Up Stats'!A:A,'Up Stats'!E:E,)} | R26: =IFERROR(__xludf.DUMMYFUNCTION("if(AND(S26=FALSE,T26=FALSE),,if(S26=T26,JOIN("""",""Static: "",S26),JOIN("""",""Min: "",S26, CHAR(10),""Max: "",T26)))"),"") | S26: {=_xlfn.XLOOKUP(B26,'Up Min'!A:A,'Up Min'!E:E,)} | T26: {=_xlfn.XLOOKUP(B26,'Up Max'!A:A,'Up Max'!E:E,)} | U26: {=_xlfn.XLOOKUP(B26,'Up Stats'!A:A,'Up Stats'!F:F,)} | V26: =IFERROR(__xludf.DUMMYFUNCTION("if(AND(W26=FALSE,X26=FALSE),,if(W26=X26,JOIN("""",""Static: "",W26),JOIN("""",""Min: "",W26, CHAR(10),""Max: "",X26)))"),"") | W26: {=_xlfn.XLOOKUP(B26,'Up Min'!A:A,'Up Min'!F:F,)} | X26: {=_xlfn.XLOOKUP(B26,'Up Max'!A:A,'Up Max'!F:F,)} | Y26: {=_xlfn.XLOOKUP(B26,'Up Stats'!A:A,'Up Stats'!G:G,)} | Z26: =IFERROR(__xludf.DUMMYFUNCTION("if(AND(AA26=FALSE,AB26=FALSE),,if(AA26=AB26,JOIN("""",""Static: "",AA26),JOIN("""",""Min: "",AA26, CHAR(10),""Max: "",AB26)))"),"") | AA26: {=_xlfn.XLOOKUP(B26,'Up Min'!A:A,'Up Min'!G:G,)} | AB26: {=_xlfn.XLOOKUP(B26,'Up Max'!A:A,'Up Max'!G:G,)} | AC26: {=_xlfn.XLOOKUP(B26,'Up Stats'!A:A,'Up Stats'!H:H,)} | AD26: =IFERROR(__xludf.DUMMYFUNCTION("if(AND(AE26=FALSE,AF26=FALSE),,if(AE26=AF26,JOIN("""",""Static: "",AE26),JOIN("""",""Min: "",AE26, CHAR(10),""Max: "",AF26)))"),"") | AE26: {=_xlfn.XLOOKUP(B26,'Up Min'!A:A,'Up Min'!H:H,)} | AF26: {=_xlfn.XLOOKUP(B26,'Up Max'!A:A,'Up Max'!H:H,)} | AG26: {=_xlfn.XLOOKUP(B26,'Up Stats'!A:A,'Up Stats'!I:I,)} | AH26: =IFERROR(__xludf.DUMMYFUNCTION("if(AND(AI26=FALSE,AJ26=FALSE),,if(AI26=AJ26,JOIN("""",""Static: "",AI26),JOIN("""",""Min: "",AI26, CHAR(10),""Max: "",AJ26)))"),"") | AI26: {=_xlfn.XLOOKUP(B26,'Up Min'!A:A,'Up Min'!I:I,)} | AJ26: {=_xlfn.XLOOKUP(B26,'Up Max'!A:A,'Up Max'!I:I,)} | AK26: {=_xlfn.XLOOKUP(B26,'Up Stats'!A:A,'Up Stats'!J:J,)} | AL26: =IFERROR(__xludf.DUMMYFUNCTION("if(AND(AM26=FALSE,AN26=FALSE),,if(AM26=AN26,JOIN("""",""Static: "",AM26),JOIN("""",""Min: "",AM26, CHAR(10),""Max: "",AN26)))"),"") | AM26: {=_xlfn.XLOOKUP(B26,'Up Min'!A:A,'Up Min'!J:J,)} | AN26: {=_xlfn.XLOOKUP(B26,'Up Max'!A:A,'Up Max'!J:J,)} | AO26: {=CONCATENATE(_xlfn.XLOOKUP(B26,'Up Cells'!A:A,'Up Cells'!B:B,))} -> 4 | AP26: {=CONCATENATE(_xlfn.XLOOKUP(B26,'Up Rarity'!A:A,'Up Rarity'!B:B,),CHAR(10),"-")} -> Rare -
A27: {=_xlfn.XLOOKUP(B27,'Up Icon'!A:A,'Up Icon'!B:B,)} | B27: {=HYPERLINK(_xlfn.XLOOKUP('Up Names'!A24,'Up Wiki'!A:A,'Up Wiki'!B:B,),'Up Names'!A24)} -> Full Range | C27: {=_xlfn.XLOOKUP(B27,'Up Desc'!A:A,'Up Desc'!B:B,)} -> Increases range for each upgrade of a different rarity that's touching this one. | D27: {=_xlfn.XLOOKUP(B27,'Up Turbo'!A:A,'Up Turbo'!B:B,)} -> n/a | E27: {=_xlfn.XLOOKUP(B27,'Up Stats'!A:A,'Up Stats'!B:B,)} -> Range per Rarity | F27: =IFERROR(__xludf.DUMMYFUNCTION("if(AND(G27=FALSE,H27=FALSE),,if(G27=H27,JOIN("""",""Static: "",G27),JOIN("""",""Min: "",G27, CHAR(10),""Max: "",H27)))"),"Min: 9 Max: 13") -> Min: 9 Max: 13 | G27: {=_xlfn.XLOOKUP(B27,'Up Min'!A:A,'Up Min'!B:B,)} -> 9 | H27: {=_xlfn.XLOOKUP(B27,'Up Max'!A:A,'Up Max'!B:B,)} -> 13 | I27: {=_xlfn.XLOOKUP(B27,'Up Stats'!A:A,'Up Stats'!C:C,)} | J27: =IFERROR(__xludf.DUMMYFUNCTION("if(AND(K27=FALSE,L27=FALSE),,if(K27=L27,JOIN("""",""Static: "",K27),JOIN("""",""Min: "",K27, CHAR(10),""Max: "",L27)))"),"") | K27: {=_xlfn.XLOOKUP(B27,'Up Min'!A:A,'Up Min'!C:C,)} | L27: {=_xlfn.XLOOKUP(B27,'Up Max'!A:A,'Up Max'!C:C,)} | M27: {=_xlfn.XLOOKUP(B27,'Up Stats'!A:A,'Up Stats'!D:D,)} | N27: =IFERROR(__xludf.DUMMYFUNCTION("if(AND(O27=FALSE,P27=FALSE),,if(O27=P27,JOIN("""",""Static: "",O27),JOIN("""",""Min: "",O27, CHAR(10),""Max: "",P27)))"),"") | O27: {=_xlfn.XLOOKUP(B27,'Up Min'!A:A,'Up Min'!D:D,)} | P27: {=_xlfn.XLOOKUP(B27,'Up Max'!A:A,'Up Max'!D:D,)} | Q27: {=_xlfn.XLOOKUP(B27,'Up Stats'!A:A,'Up Stats'!E:E,)} | R27: =IFERROR(__xludf.DUMMYFUNCTION("if(AND(S27=FALSE,T27=FALSE),,if(S27=T27,JOIN("""",""Static: "",S27),JOIN("""",""Min: "",S27, CHAR(10),""Max: "",T27)))"),"") | S27: {=_xlfn.XLOOKUP(B27,'Up Min'!A:A,'Up Min'!E:E,)} | T27: {=_xlfn.XLOOKUP(B27,'Up Max'!A:A,'Up Max'!E:E,)} | U27: {=_xlfn.XLOOKUP(B27,'Up Stats'!A:A,'Up Stats'!F:F,)} | V27: =IFERROR(__xludf.DUMMYFUNCTION("if(AND(W27=FALSE,X27=FALSE),,if(W27=X27,JOIN("""",""Static: "",W27),JOIN("""",""Min: "",W27, CHAR(10),""Max: "",X27)))"),"") | W27: {=_xlfn.XLOOKUP(B27,'Up Min'!A:A,'Up Min'!F:F,)} | X27: {=_xlfn.XLOOKUP(B27,'Up Max'!A:A,'Up Max'!F:F,)} | Y27: {=_xlfn.XLOOKUP(B27,'Up Stats'!A:A,'Up Stats'!G:G,)} | Z27: =IFERROR(__xludf.DUMMYFUNCTION("if(AND(AA27=FALSE,AB27=FALSE),,if(AA27=AB27,JOIN("""",""Static: "",AA27),JOIN("""",""Min: "",AA27, CHAR(10),""Max: "",AB27)))"),"") | AA27: {=_xlfn.XLOOKUP(B27,'Up Min'!A:A,'Up Min'!G:G,)} | AB27: {=_xlfn.XLOOKUP(B27,'Up Max'!A:A,'Up Max'!G:G,)} | AC27: {=_xlfn.XLOOKUP(B27,'Up Stats'!A:A,'Up Stats'!H:H,)} | AD27: =IFERROR(__xludf.DUMMYFUNCTION("if(AND(AE27=FALSE,AF27=FALSE),,if(AE27=AF27,JOIN("""",""Static: "",AE27),JOIN("""",""Min: "",AE27, CHAR(10),""Max: "",AF27)))"),"") | AE27: {=_xlfn.XLOOKUP(B27,'Up Min'!A:A,'Up Min'!H:H,)} | AF27: {=_xlfn.XLOOKUP(B27,'Up Max'!A:A,'Up Max'!H:H,)} | AG27: {=_xlfn.XLOOKUP(B27,'Up Stats'!A:A,'Up Stats'!I:I,)} | AH27: =IFERROR(__xludf.DUMMYFUNCTION("if(AND(AI27=FALSE,AJ27=FALSE),,if(AI27=AJ27,JOIN("""",""Static: "",AI27),JOIN("""",""Min: "",AI27, CHAR(10),""Max: "",AJ27)))"),"") | AI27: {=_xlfn.XLOOKUP(B27,'Up Min'!A:A,'Up Min'!I:I,)} | AJ27: {=_xlfn.XLOOKUP(B27,'Up Max'!A:A,'Up Max'!I:I,)} | AK27: {=_xlfn.XLOOKUP(B27,'Up Stats'!A:A,'Up Stats'!J:J,)} | AL27: =IFERROR(__xludf.DUMMYFUNCTION("if(AND(AM27=FALSE,AN27=FALSE),,if(AM27=AN27,JOIN("""",""Static: "",AM27),JOIN("""",""Min: "",AM27, CHAR(10),""Max: "",AN27)))"),"") | AM27: {=_xlfn.XLOOKUP(B27,'Up Min'!A:A,'Up Min'!J:J,)} | AN27: {=_xlfn.XLOOKUP(B27,'Up Max'!A:A,'Up Max'!J:J,)} | AO27: {=CONCATENATE(_xlfn.XLOOKUP(B27,'Up Cells'!A:A,'Up Cells'!B:B,))} -> 4 | AP27: {=CONCATENATE(_xlfn.XLOOKUP(B27,'Up Rarity'!A:A,'Up Rarity'!B:B,),CHAR(10),"-")} -> Rare -
A28: {=_xlfn.XLOOKUP(B28,'Up Icon'!A:A,'Up Icon'!B:B,)} | B28: {=HYPERLINK(_xlfn.XLOOKUP('Up Names'!A25,'Up Wiki'!A:A,'Up Wiki'!B:B,),'Up Names'!A25)} -> Heated Battery | C28: {=_xlfn.XLOOKUP(B28,'Up Desc'!A:A,'Up Desc'!B:B,)} -> Bullets apply fire. | D28: {=_xlfn.XLOOKUP(B28,'Up Turbo'!A:A,'Up Turbo'!B:B,)} -> n/a | E28: {=_xlfn.XLOOKUP(B28,'Up Stats'!A:A,'Up Stats'!B:B,)} -> Element | F28: =IFERROR(__xludf.DUMMYFUNCTION("if(AND(G28=FALSE,H28=FALSE),,if(G28=H28,JOIN("""",""Static: "",G28),JOIN("""",""Min: "",G28, CHAR(10),""Max: "",H28)))"),"Min: 1.85 Max: 2.15") -> Min: 1.85 Max: 2.15 | G28: {=_xlfn.XLOOKUP(B28,'Up Min'!A:A,'Up Min'!B:B,)} -> 1.85 | H28: {=_xlfn.XLOOKUP(B28,'Up Max'!A:A,'Up Max'!B:B,)} -> 2.15 | I28: {=_xlfn.XLOOKUP(B28,'Up Stats'!A:A,'Up Stats'!C:C,)} | J28: =IFERROR(__xludf.DUMMYFUNCTION("if(AND(K28=FALSE,L28=FALSE),,if(K28=L28,JOIN("""",""Static: "",K28),JOIN("""",""Min: "",K28, CHAR(10),""Max: "",L28)))"),"") | K28: {=_xlfn.XLOOKUP(B28,'Up Min'!A:A,'Up Min'!C:C,)} | L28: {=_xlfn.XLOOKUP(B28,'Up Max'!A:A,'Up Max'!C:C,)} | M28: {=_xlfn.XLOOKUP(B28,'Up Stats'!A:A,'Up Stats'!D:D,)} | N28: =IFERROR(__xludf.DUMMYFUNCTION("if(AND(O28=FALSE,P28=FALSE),,if(O28=P28,JOIN("""",""Static: "",O28),JOIN("""",""Min: "",O28, CHAR(10),""Max: "",P28)))"),"") | O28: {=_xlfn.XLOOKUP(B28,'Up Min'!A:A,'Up Min'!D:D,)} | P28: {=_xlfn.XLOOKUP(B28,'Up Max'!A:A,'Up Max'!D:D,)} | Q28: {=_xlfn.XLOOKUP(B28,'Up Stats'!A:A,'Up Stats'!E:E,)} | R28: =IFERROR(__xludf.DUMMYFUNCTION("if(AND(S28=FALSE,T28=FALSE),,if(S28=T28,JOIN("""",""Static: "",S28),JOIN("""",""Min: "",S28, CHAR(10),""Max: "",T28)))"),"") | S28: {=_xlfn.XLOOKUP(B28,'Up Min'!A:A,'Up Min'!E:E,)} | T28: {=_xlfn.XLOOKUP(B28,'Up Max'!A:A,'Up Max'!E:E,)} | U28: {=_xlfn.XLOOKUP(B28,'Up Stats'!A:A,'Up Stats'!F:F,)} | V28: =IFERROR(__xludf.DUMMYFUNCTION("if(AND(W28=FALSE,X28=FALSE),,if(W28=X28,JOIN("""",""Static: "",W28),JOIN("""",""Min: "",W28, CHAR(10),""Max: "",X28)))"),"") | W28: {=_xlfn.XLOOKUP(B28,'Up Min'!A:A,'Up Min'!F:F,)} | X28: {=_xlfn.XLOOKUP(B28,'Up Max'!A:A,'Up Max'!F:F,)} | Y28: {=_xlfn.XLOOKUP(B28,'Up Stats'!A:A,'Up Stats'!G:G,)} | Z28: =IFERROR(__xludf.DUMMYFUNCTION("if(AND(AA28=FALSE,AB28=FALSE),,if(AA28=AB28,JOIN("""",""Static: "",AA28),JOIN("""",""Min: "",AA28, CHAR(10),""Max: "",AB28)))"),"") | AA28: {=_xlfn.XLOOKUP(B28,'Up Min'!A:A,'Up Min'!G:G,)} | AB28: {=_xlfn.XLOOKUP(B28,'Up Max'!A:A,'Up Max'!G:G,)} | AC28: {=_xlfn.XLOOKUP(B28,'Up Stats'!A:A,'Up Stats'!H:H,)} | AD28: =IFERROR(__xludf.DUMMYFUNCTION("if(AND(AE28=FALSE,AF28=FALSE),,if(AE28=AF28,JOIN("""",""Static: "",AE28),JOIN("""",""Min: "",AE28, CHAR(10),""Max: "",AF28)))"),"") | AE28: {=_xlfn.XLOOKUP(B28,'Up Min'!A:A,'Up Min'!H:H,)} | AF28: {=_xlfn.XLOOKUP(B28,'Up Max'!A:A,'Up Max'!H:H,)} | AG28: {=_xlfn.XLOOKUP(B28,'Up Stats'!A:A,'Up Stats'!I:I,)} | AH28: =IFERROR(__xludf.DUMMYFUNCTION("if(AND(AI28=FALSE,AJ28=FALSE),,if(AI28=AJ28,JOIN("""",""Static: "",AI28),JOIN("""",""Min: "",AI28, CHAR(10),""Max: "",AJ28)))"),"") | AI28: {=_xlfn.XLOOKUP(B28,'Up Min'!A:A,'Up Min'!I:I,)} | AJ28: {=_xlfn.XLOOKUP(B28,'Up Max'!A:A,'Up Max'!I:I,)} | AK28: {=_xlfn.XLOOKUP(B28,'Up Stats'!A:A,'Up Stats'!J:J,)} | AL28: =IFERROR(__xludf.DUMMYFUNCTION("if(AND(AM28=FALSE,AN28=FALSE),,if(AM28=AN28,JOIN("""",""Static: "",AM28),JOIN("""",""Min: "",AM28, CHAR(10),""Max: "",AN28)))"),"") | AM28: {=_xlfn.XLOOKUP(B28,'Up Min'!A:A,'Up Min'!J:J,)} | AN28: {=_xlfn.XLOOKUP(B28,'Up Max'!A:A,'Up Max'!J:J,)} | AO28: {=CONCATENATE(_xlfn.XLOOKUP(B28,'Up Cells'!A:A,'Up Cells'!B:B,))} -> 3 | AP28: {=CONCATENATE(_xlfn.XLOOKUP(B28,'Up Rarity'!A:A,'Up Rarity'!B:B,),CHAR(10),"-")} -> Rare -
A29: {=_xlfn.XLOOKUP(B29,'Up Icon'!A:A,'Up Icon'!B:B,)} | B29: {=HYPERLINK(_xlfn.XLOOKUP('Up Names'!A26,'Up Wiki'!A:A,'Up Wiki'!B:B,),'Up Names'!A26)} -> Overclocked Firing Mechanism | C29: {=_xlfn.XLOOKUP(B29,'Up Desc'!A:A,'Up Desc'!B:B,)} -> Fire faster in a larger spread. | D29: {=_xlfn.XLOOKUP(B29,'Up Turbo'!A:A,'Up Turbo'!B:B,)} -> n/a | E29: {=_xlfn.XLOOKUP(B29,'Up Stats'!A:A,'Up Stats'!B:B,)} -> Horizontal Spread | F29: =IFERROR(__xludf.DUMMYFUNCTION("if(AND(G29=FALSE,H29=FALSE),,if(G29=H29,JOIN("""",""Static: "",G29),JOIN("""",""Min: "",G29, CHAR(10),""Max: "",H29)))"),"Min: 4.5 Max: 5.8") -> Min: 4.5 Max: 5.8 | G29: {=_xlfn.XLOOKUP(B29,'Up Min'!A:A,'Up Min'!B:B,)} -> 4.5 | H29: {=_xlfn.XLOOKUP(B29,'Up Max'!A:A,'Up Max'!B:B,)} -> 5.8 | I29: {=_xlfn.XLOOKUP(B29,'Up Stats'!A:A,'Up Stats'!C:C,)} -> Vertical Spread | J29: =IFERROR(__xludf.DUMMYFUNCTION("if(AND(K29=FALSE,L29=FALSE),,if(K29=L29,JOIN("""",""Static: "",K29),JOIN("""",""Min: "",K29, CHAR(10),""Max: "",L29)))"),"Min: 4.5 Max: 5.8") -> Min: 4.5 Max: 5.8 | K29: {=_xlfn.XLOOKUP(B29,'Up Min'!A:A,'Up Min'!C:C,)} -> 4.5 | L29: {=_xlfn.XLOOKUP(B29,'Up Max'!A:A,'Up Max'!C:C,)} -> 5.8 | M29: {=_xlfn.XLOOKUP(B29,'Up Stats'!A:A,'Up Stats'!D:D,)} -> Fire Rate | N29: =IFERROR(__xludf.DUMMYFUNCTION("if(AND(O29=FALSE,P29=FALSE),,if(O29=P29,JOIN("""",""Static: "",O29),JOIN("""",""Min: "",O29, CHAR(10),""Max: "",P29)))"),"Min: 25% Max: 11.11%") -> Min: 25% Max: 11.11% | O29: {=_xlfn.XLOOKUP(B29,'Up Min'!A:A,'Up Min'!D:D,)} -> 0.25 | P29: {=_xlfn.XLOOKUP(B29,'Up Max'!A:A,'Up Max'!D:D,)} -> 0.1111 | Q29: {=_xlfn.XLOOKUP(B29,'Up Stats'!A:A,'Up Stats'!E:E,)} | R29: =IFERROR(__xludf.DUMMYFUNCTION("if(AND(S29=FALSE,T29=FALSE),,if(S29=T29,JOIN("""",""Static: "",S29),JOIN("""",""Min: "",S29, CHAR(10),""Max: "",T29)))"),"") | S29: {=_xlfn.XLOOKUP(B29,'Up Min'!A:A,'Up Min'!E:E,)} | T29: {=_xlfn.XLOOKUP(B29,'Up Max'!A:A,'Up Max'!E:E,)} | U29: {=_xlfn.XLOOKUP(B29,'Up Stats'!A:A,'Up Stats'!F:F,)} | V29: =IFERROR(__xludf.DUMMYFUNCTION("if(AND(W29=FALSE,X29=FALSE),,if(W29=X29,JOIN("""",""Static: "",W29),JOIN("""",""Min: "",W29, CHAR(10),""Max: "",X29)))"),"") | W29: {=_xlfn.XLOOKUP(B29,'Up Min'!A:A,'Up Min'!F:F,)} | X29: {=_xlfn.XLOOKUP(B29,'Up Max'!A:A,'Up Max'!F:F,)} | Y29: {=_xlfn.XLOOKUP(B29,'Up Stats'!A:A,'Up Stats'!G:G,)} | Z29: =IFERROR(__xludf.DUMMYFUNCTION("if(AND(AA29=FALSE,AB29=FALSE),,if(AA29=AB29,JOIN("""",""Static: "",AA29),JOIN("""",""Min: "",AA29, CHAR(10),""Max: "",AB29)))"),"") | AA29: {=_xlfn.XLOOKUP(B29,'Up Min'!A:A,'Up Min'!G:G,)} | AB29: {=_xlfn.XLOOKUP(B29,'Up Max'!A:A,'Up Max'!G:G,)} | AC29: {=_xlfn.XLOOKUP(B29,'Up Stats'!A:A,'Up Stats'!H:H,)} | AD29: =IFERROR(__xludf.DUMMYFUNCTION("if(AND(AE29=FALSE,AF29=FALSE),,if(AE29=AF29,JOIN("""",""Static: "",AE29),JOIN("""",""Min: "",AE29, CHAR(10),""Max: "",AF29)))"),"") | AE29: {=_xlfn.XLOOKUP(B29,'Up Min'!A:A,'Up Min'!H:H,)} | AF29: {=_xlfn.XLOOKUP(B29,'Up Max'!A:A,'Up Max'!H:H,)} | AG29: {=_xlfn.XLOOKUP(B29,'Up Stats'!A:A,'Up Stats'!I:I,)} | AH29: =IFERROR(__xludf.DUMMYFUNCTION("if(AND(AI29=FALSE,AJ29=FALSE),,if(AI29=AJ29,JOIN("""",""Static: "",AI29),JOIN("""",""Min: "",AI29, CHAR(10),""Max: "",AJ29)))"),"") | AI29: {=_xlfn.XLOOKUP(B29,'Up Min'!A:A,'Up Min'!I:I,)} | AJ29: {=_xlfn.XLOOKUP(B29,'Up Max'!A:A,'Up Max'!I:I,)} | AK29: {=_xlfn.XLOOKUP(B29,'Up Stats'!A:A,'Up Stats'!J:J,)} | AL29: =IFERROR(__xludf.DUMMYFUNCTION("if(AND(AM29=FALSE,AN29=FALSE),,if(AM29=AN29,JOIN("""",""Static: "",AM29),JOIN("""",""Min: "",AM29, CHAR(10),""Max: "",AN29)))"),"") | AM29: {=_xlfn.XLOOKUP(B29,'Up Min'!A:A,'Up Min'!J:J,)} | AN29: {=_xlfn.XLOOKUP(B29,'Up Max'!A:A,'Up Max'!J:J,)} | AO29: {=CONCATENATE(_xlfn.XLOOKUP(B29,'Up Cells'!A:A,'Up Cells'!B:B,))} -> 5 | AP29: {=CONCATENATE(_xlfn.XLOOKUP(B29,'Up Rarity'!A:A,'Up Rarity'!B:B,),CHAR(10),"-")} -> Rare -
A30: {=_xlfn.XLOOKUP(B30,'Up Icon'!A:A,'Up Icon'!B:B,)} | B30: {=HYPERLINK(_xlfn.XLOOKUP('Up Names'!A27,'Up Wiki'!A:A,'Up Wiki'!B:B,),'Up Names'!A27)} -> Rocket Burst | C30: {=_xlfn.XLOOKUP(B30,'Up Desc'!A:A,'Up Desc'!B:B,)} -> Fire a four-round burst. The last bullet in each burst is replaced with a tracking missile. | D30: {=_xlfn.XLOOKUP(B30,'Up Turbo'!A:A,'Up Turbo'!B:B,)} -> n/a | E30: {=_xlfn.XLOOKUP(B30,'Up Stats'!A:A,'Up Stats'!B:B,)} -> Burst Size | F30: =IFERROR(__xludf.DUMMYFUNCTION("if(AND(G30=FALSE,H30=FALSE),,if(G30=H30,JOIN("""",""Static: "",G30),JOIN("""",""Min: "",G30, CHAR(10),""Max: "",H30)))"),"Static: 4") -> Static: 4 | G30: {=_xlfn.XLOOKUP(B30,'Up Min'!A:A,'Up Min'!B:B,)} -> 4 | H30: {=_xlfn.XLOOKUP(B30,'Up Max'!A:A,'Up Max'!B:B,)} -> 4 | I30: {=_xlfn.XLOOKUP(B30,'Up Stats'!A:A,'Up Stats'!C:C,)} -> Burst Interval | J30: =IFERROR(__xludf.DUMMYFUNCTION("if(AND(K30=FALSE,L30=FALSE),,if(K30=L30,JOIN("""",""Static: "",K30),JOIN("""",""Min: "",K30, CHAR(10),""Max: "",L30)))"),"Static: 0.17") -> Static: 0.17 | K30: {=_xlfn.XLOOKUP(B30,'Up Min'!A:A,'Up Min'!C:C,)} -> 0.17 | L30: {=_xlfn.XLOOKUP(B30,'Up Max'!A:A,'Up Max'!C:C,)} -> 0.17 | M30: {=_xlfn.XLOOKUP(B30,'Up Stats'!A:A,'Up Stats'!D:D,)} -> Explosion Size | N30: =IFERROR(__xludf.DUMMYFUNCTION("if(AND(O30=FALSE,P30=FALSE),,if(O30=P30,JOIN("""",""Static: "",O30),JOIN("""",""Min: "",O30, CHAR(10),""Max: "",P30)))"),"Min: 1.2 Max: 2") -> Min: 1.2 Max: 2 | O30: {=_xlfn.XLOOKUP(B30,'Up Min'!A:A,'Up Min'!D:D,)} -> 1.2 | P30: {=_xlfn.XLOOKUP(B30,'Up Max'!A:A,'Up Max'!D:D,)} -> 2 | Q30: {=_xlfn.XLOOKUP(B30,'Up Stats'!A:A,'Up Stats'!E:E,)} | R30: =IFERROR(__xludf.DUMMYFUNCTION("if(AND(S30=FALSE,T30=FALSE),,if(S30=T30,JOIN("""",""Static: "",S30),JOIN("""",""Min: "",S30, CHAR(10),""Max: "",T30)))"),"") | S30: {=_xlfn.XLOOKUP(B30,'Up Min'!A:A,'Up Min'!E:E,)} | T30: {=_xlfn.XLOOKUP(B30,'Up Max'!A:A,'Up Max'!E:E,)} | U30: {=_xlfn.XLOOKUP(B30,'Up Stats'!A:A,'Up Stats'!F:F,)} | V30: =IFERROR(__xludf.DUMMYFUNCTION("if(AND(W30=FALSE,X30=FALSE),,if(W30=X30,JOIN("""",""Static: "",W30),JOIN("""",""Min: "",W30, CHAR(10),""Max: "",X30)))"),"") | W30: {=_xlfn.XLOOKUP(B30,'Up Min'!A:A,'Up Min'!F:F,)} | X30: {=_xlfn.XLOOKUP(B30,'Up Max'!A:A,'Up Max'!F:F,)} | Y30: {=_xlfn.XLOOKUP(B30,'Up Stats'!A:A,'Up Stats'!G:G,)} | Z30: =IFERROR(__xludf.DUMMYFUNCTION("if(AND(AA30=FALSE,AB30=FALSE),,if(AA30=AB30,JOIN("""",""Static: "",AA30),JOIN("""",""Min: "",AA30, CHAR(10),""Max: "",AB30)))"),"") | AA30: {=_xlfn.XLOOKUP(B30,'Up Min'!A:A,'Up Min'!G:G,)} | AB30: {=_xlfn.XLOOKUP(B30,'Up Max'!A:A,'Up Max'!G:G,)} | AC30: {=_xlfn.XLOOKUP(B30,'Up Stats'!A:A,'Up Stats'!H:H,)} | AD30: =IFERROR(__xludf.DUMMYFUNCTION("if(AND(AE30=FALSE,AF30=FALSE),,if(AE30=AF30,JOIN("""",""Static: "",AE30),JOIN("""",""Min: "",AE30, CHAR(10),""Max: "",AF30)))"),"") | AE30: {=_xlfn.XLOOKUP(B30,'Up Min'!A:A,'Up Min'!H:H,)} | AF30: {=_xlfn.XLOOKUP(B30,'Up Max'!A:A,'Up Max'!H:H,)} | AG30: {=_xlfn.XLOOKUP(B30,'Up Stats'!A:A,'Up Stats'!I:I,)} | AH30: =IFERROR(__xludf.DUMMYFUNCTION("if(AND(AI30=FALSE,AJ30=FALSE),,if(AI30=AJ30,JOIN("""",""Static: "",AI30),JOIN("""",""Min: "",AI30, CHAR(10),""Max: "",AJ30)))"),"") | AI30: {=_xlfn.XLOOKUP(B30,'Up Min'!A:A,'Up Min'!I:I,)} | AJ30: {=_xlfn.XLOOKUP(B30,'Up Max'!A:A,'Up Max'!I:I,)} | AK30: {=_xlfn.XLOOKUP(B30,'Up Stats'!A:A,'Up Stats'!J:J,)} | AL30: =IFERROR(__xludf.DUMMYFUNCTION("if(AND(AM30=FALSE,AN30=FALSE),,if(AM30=AN30,JOIN("""",""Static: "",AM30),JOIN("""",""Min: "",AM30, CHAR(10),""Max: "",AN30)))"),"") | AM30: {=_xlfn.XLOOKUP(B30,'Up Min'!A:A,'Up Min'!J:J,)} | AN30: {=_xlfn.XLOOKUP(B30,'Up Max'!A:A,'Up Max'!J:J,)} | AO30: {=CONCATENATE(_xlfn.XLOOKUP(B30,'Up Cells'!A:A,'Up Cells'!B:B,))} -> 4 | AP30: {=CONCATENATE(_xlfn.XLOOKUP(B30,'Up Rarity'!A:A,'Up Rarity'!B:B,),CHAR(10),"-")} -> Rare -
A31: {=_xlfn.XLOOKUP(B31,'Up Icon'!A:A,'Up Icon'!B:B,)} | B31: {=HYPERLINK(_xlfn.XLOOKUP('Up Names'!A28,'Up Wiki'!A:A,'Up Wiki'!B:B,),'Up Names'!A28)} -> Smart Slide | C31: {=_xlfn.XLOOKUP(B31,'Up Desc'!A:A,'Up Desc'!B:B,)} -> Bullets auto-track to targets while sliding. | D31: {=_xlfn.XLOOKUP(B31,'Up Turbo'!A:A,'Up Turbo'!B:B,)} -> n/a | E31: {=_xlfn.XLOOKUP(B31,'Up Stats'!A:A,'Up Stats'!B:B,)} -> Tracking Radius | F31: =IFERROR(__xludf.DUMMYFUNCTION("if(AND(G31=FALSE,H31=FALSE),,if(G31=H31,JOIN("""",""Static: "",G31),JOIN("""",""Min: "",G31, CHAR(10),""Max: "",H31)))"),"Min: 17 Max: 23") -> Min: 17 Max: 23 | G31: {=_xlfn.XLOOKUP(B31,'Up Min'!A:A,'Up Min'!B:B,)} -> 17 | H31: {=_xlfn.XLOOKUP(B31,'Up Max'!A:A,'Up Max'!B:B,)} -> 23 | I31: {=_xlfn.XLOOKUP(B31,'Up Stats'!A:A,'Up Stats'!C:C,)} | J31: =IFERROR(__xludf.DUMMYFUNCTION("if(AND(K31=FALSE,L31=FALSE),,if(K31=L31,JOIN("""",""Static: "",K31),JOIN("""",""Min: "",K31, CHAR(10),""Max: "",L31)))"),"") | K31: {=_xlfn.XLOOKUP(B31,'Up Min'!A:A,'Up Min'!C:C,)} | L31: {=_xlfn.XLOOKUP(B31,'Up Max'!A:A,'Up Max'!C:C,)} | M31: {=_xlfn.XLOOKUP(B31,'Up Stats'!A:A,'Up Stats'!D:D,)} | N31: =IFERROR(__xludf.DUMMYFUNCTION("if(AND(O31=FALSE,P31=FALSE),,if(O31=P31,JOIN("""",""Static: "",O31),JOIN("""",""Min: "",O31, CHAR(10),""Max: "",P31)))"),"") | O31: {=_xlfn.XLOOKUP(B31,'Up Min'!A:A,'Up Min'!D:D,)} | P31: {=_xlfn.XLOOKUP(B31,'Up Max'!A:A,'Up Max'!D:D,)} | Q31: {=_xlfn.XLOOKUP(B31,'Up Stats'!A:A,'Up Stats'!E:E,)} | R31: =IFERROR(__xludf.DUMMYFUNCTION("if(AND(S31=FALSE,T31=FALSE),,if(S31=T31,JOIN("""",""Static: "",S31),JOIN("""",""Min: "",S31, CHAR(10),""Max: "",T31)))"),"") | S31: {=_xlfn.XLOOKUP(B31,'Up Min'!A:A,'Up Min'!E:E,)} | T31: {=_xlfn.XLOOKUP(B31,'Up Max'!A:A,'Up Max'!E:E,)} | U31: {=_xlfn.XLOOKUP(B31,'Up Stats'!A:A,'Up Stats'!F:F,)} | V31: =IFERROR(__xludf.DUMMYFUNCTION("if(AND(W31=FALSE,X31=FALSE),,if(W31=X31,JOIN("""",""Static: "",W31),JOIN("""",""Min: "",W31, CHAR(10),""Max: "",X31)))"),"") | W31: {=_xlfn.XLOOKUP(B31,'Up Min'!A:A,'Up Min'!F:F,)} | X31: {=_xlfn.XLOOKUP(B31,'Up Max'!A:A,'Up Max'!F:F,)} | Y31: {=_xlfn.XLOOKUP(B31,'Up Stats'!A:A,'Up Stats'!G:G,)} | Z31: =IFERROR(__xludf.DUMMYFUNCTION("if(AND(AA31=FALSE,AB31=FALSE),,if(AA31=AB31,JOIN("""",""Static: "",AA31),JOIN("""",""Min: "",AA31, CHAR(10),""Max: "",AB31)))"),"") | AA31: {=_xlfn.XLOOKUP(B31,'Up Min'!A:A,'Up Min'!G:G,)} | AB31: {=_xlfn.XLOOKUP(B31,'Up Max'!A:A,'Up Max'!G:G,)} | AC31: {=_xlfn.XLOOKUP(B31,'Up Stats'!A:A,'Up Stats'!H:H,)} | AD31: =IFERROR(__xludf.DUMMYFUNCTION("if(AND(AE31=FALSE,AF31=FALSE),,if(AE31=AF31,JOIN("""",""Static: "",AE31),JOIN("""",""Min: "",AE31, CHAR(10),""Max: "",AF31)))"),"") | AE31: {=_xlfn.XLOOKUP(B31,'Up Min'!A:A,'Up Min'!H:H,)} | AF31: {=_xlfn.XLOOKUP(B31,'Up Max'!A:A,'Up Max'!H:H,)} | AG31: {=_xlfn.XLOOKUP(B31,'Up Stats'!A:A,'Up Stats'!I:I,)} | AH31: =IFERROR(__xludf.DUMMYFUNCTION("if(AND(AI31=FALSE,AJ31=FALSE),,if(AI31=AJ31,JOIN("""",""Static: "",AI31),JOIN("""",""Min: "",AI31, CHAR(10),""Max: "",AJ31)))"),"") | AI31: {=_xlfn.XLOOKUP(B31,'Up Min'!A:A,'Up Min'!I:I,)} | AJ31: {=_xlfn.XLOOKUP(B31,'Up Max'!A:A,'Up Max'!I:I,)} | AK31: {=_xlfn.XLOOKUP(B31,'Up Stats'!A:A,'Up Stats'!J:J,)} | AL31: =IFERROR(__xludf.DUMMYFUNCTION("if(AND(AM31=FALSE,AN31=FALSE),,if(AM31=AN31,JOIN("""",""Static: "",AM31),JOIN("""",""Min: "",AM31, CHAR(10),""Max: "",AN31)))"),"") | AM31: {=_xlfn.XLOOKUP(B31,'Up Min'!A:A,'Up Min'!J:J,)} | AN31: {=_xlfn.XLOOKUP(B31,'Up Max'!A:A,'Up Max'!J:J,)} | AO31: {=CONCATENATE(_xlfn.XLOOKUP(B31,'Up Cells'!A:A,'Up Cells'!B:B,))} -> 5 | AP31: {=CONCATENATE(_xlfn.XLOOKUP(B31,'Up Rarity'!A:A,'Up Rarity'!B:B,),CHAR(10),"-")} -> Rare -
A32: {=_xlfn.XLOOKUP(B32,'Up Icon'!A:A,'Up Icon'!B:B,)} | B32: {=HYPERLINK(_xlfn.XLOOKUP('Up Names'!A29,'Up Wiki'!A:A,'Up Wiki'!B:B,),'Up Names'!A29)} -> Adrenaline Reload | C32: {=_xlfn.XLOOKUP(B32,'Up Desc'!A:A,'Up Desc'!B:B,)} -> Reload speed is briefly increased after killing a target. | D32: {=_xlfn.XLOOKUP(B32,'Up Turbo'!A:A,'Up Turbo'!B:B,)} -> n/a | E32: {=_xlfn.XLOOKUP(B32,'Up Stats'!A:A,'Up Stats'!B:B,)} -> Reload Speed | F32: =IFERROR(__xludf.DUMMYFUNCTION("if(AND(G32=FALSE,H32=FALSE),,if(G32=H32,JOIN("""",""Static: "",G32),JOIN("""",""Min: "",G32, CHAR(10),""Max: "",H32)))"),"Min: 42.45% Max: 30.72%") -> Min: 42.45% Max: 30.72% | G32: {=_xlfn.XLOOKUP(B32,'Up Min'!A:A,'Up Min'!B:B,)} -> 0.4245 | H32: {=_xlfn.XLOOKUP(B32,'Up Max'!A:A,'Up Max'!B:B,)} -> 0.3072 | I32: {=_xlfn.XLOOKUP(B32,'Up Stats'!A:A,'Up Stats'!C:C,)} | J32: =IFERROR(__xludf.DUMMYFUNCTION("if(AND(K32=FALSE,L32=FALSE),,if(K32=L32,JOIN("""",""Static: "",K32),JOIN("""",""Min: "",K32, CHAR(10),""Max: "",L32)))"),"") | K32: {=_xlfn.XLOOKUP(B32,'Up Min'!A:A,'Up Min'!C:C,)} | L32: {=_xlfn.XLOOKUP(B32,'Up Max'!A:A,'Up Max'!C:C,)} | M32: {=_xlfn.XLOOKUP(B32,'Up Stats'!A:A,'Up Stats'!D:D,)} | N32: =IFERROR(__xludf.DUMMYFUNCTION("if(AND(O32=FALSE,P32=FALSE),,if(O32=P32,JOIN("""",""Static: "",O32),JOIN("""",""Min: "",O32, CHAR(10),""Max: "",P32)))"),"") | O32: {=_xlfn.XLOOKUP(B32,'Up Min'!A:A,'Up Min'!D:D,)} | P32: {=_xlfn.XLOOKUP(B32,'Up Max'!A:A,'Up Max'!D:D,)} | Q32: {=_xlfn.XLOOKUP(B32,'Up Stats'!A:A,'Up Stats'!E:E,)} | R32: =IFERROR(__xludf.DUMMYFUNCTION("if(AND(S32=FALSE,T32=FALSE),,if(S32=T32,JOIN("""",""Static: "",S32),JOIN("""",""Min: "",S32, CHAR(10),""Max: "",T32)))"),"") | S32: {=_xlfn.XLOOKUP(B32,'Up Min'!A:A,'Up Min'!E:E,)} | T32: {=_xlfn.XLOOKUP(B32,'Up Max'!A:A,'Up Max'!E:E,)} | U32: {=_xlfn.XLOOKUP(B32,'Up Stats'!A:A,'Up Stats'!F:F,)} | V32: =IFERROR(__xludf.DUMMYFUNCTION("if(AND(W32=FALSE,X32=FALSE),,if(W32=X32,JOIN("""",""Static: "",W32),JOIN("""",""Min: "",W32, CHAR(10),""Max: "",X32)))"),"") | W32: {=_xlfn.XLOOKUP(B32,'Up Min'!A:A,'Up Min'!F:F,)} | X32: {=_xlfn.XLOOKUP(B32,'Up Max'!A:A,'Up Max'!F:F,)} | Y32: {=_xlfn.XLOOKUP(B32,'Up Stats'!A:A,'Up Stats'!G:G,)} | Z32: =IFERROR(__xludf.DUMMYFUNCTION("if(AND(AA32=FALSE,AB32=FALSE),,if(AA32=AB32,JOIN("""",""Static: "",AA32),JOIN("""",""Min: "",AA32, CHAR(10),""Max: "",AB32)))"),"") | AA32: {=_xlfn.XLOOKUP(B32,'Up Min'!A:A,'Up Min'!G:G,)} | AB32: {=_xlfn.XLOOKUP(B32,'Up Max'!A:A,'Up Max'!G:G,)} | AC32: {=_xlfn.XLOOKUP(B32,'Up Stats'!A:A,'Up Stats'!H:H,)} | AD32: =IFERROR(__xludf.DUMMYFUNCTION("if(AND(AE32=FALSE,AF32=FALSE),,if(AE32=AF32,JOIN("""",""Static: "",AE32),JOIN("""",""Min: "",AE32, CHAR(10),""Max: "",AF32)))"),"") | AE32: {=_xlfn.XLOOKUP(B32,'Up Min'!A:A,'Up Min'!H:H,)} | AF32: {=_xlfn.XLOOKUP(B32,'Up Max'!A:A,'Up Max'!H:H,)} | AG32: {=_xlfn.XLOOKUP(B32,'Up Stats'!A:A,'Up Stats'!I:I,)} | AH32: =IFERROR(__xludf.DUMMYFUNCTION("if(AND(AI32=FALSE,AJ32=FALSE),,if(AI32=AJ32,JOIN("""",""Static: "",AI32),JOIN("""",""Min: "",AI32, CHAR(10),""Max: "",AJ32)))"),"") | AI32: {=_xlfn.XLOOKUP(B32,'Up Min'!A:A,'Up Min'!I:I,)} | AJ32: {=_xlfn.XLOOKUP(B32,'Up Max'!A:A,'Up Max'!I:I,)} | AK32: {=_xlfn.XLOOKUP(B32,'Up Stats'!A:A,'Up Stats'!J:J,)} | AL32: =IFERROR(__xludf.DUMMYFUNCTION("if(AND(AM32=FALSE,AN32=FALSE),,if(AM32=AN32,JOIN("""",""Static: "",AM32),JOIN("""",""Min: "",AM32, CHAR(10),""Max: "",AN32)))"),"") | AM32: {=_xlfn.XLOOKUP(B32,'Up Min'!A:A,'Up Min'!J:J,)} | AN32: {=_xlfn.XLOOKUP(B32,'Up Max'!A:A,'Up Max'!J:J,)} | AO32: {=CONCATENATE(_xlfn.XLOOKUP(B32,'Up Cells'!A:A,'Up Cells'!B:B,))} -> 4 | AP32: {=CONCATENATE(_xlfn.XLOOKUP(B32,'Up Rarity'!A:A,'Up Rarity'!B:B,),CHAR(10),"-")} -> Standard -
A33: {=_xlfn.XLOOKUP(B33,'Up Icon'!A:A,'Up Icon'!B:B,)} | B33: {=HYPERLINK(_xlfn.XLOOKUP('Up Names'!A30,'Up Wiki'!A:A,'Up Wiki'!B:B,),'Up Names'!A30)} -> Bigazine | C33: {=_xlfn.XLOOKUP(B33,'Up Desc'!A:A,'Up Desc'!B:B,)} -> Magazine size is greatly increased. | D33: {=_xlfn.XLOOKUP(B33,'Up Turbo'!A:A,'Up Turbo'!B:B,)} -> n/a | E33: {=_xlfn.XLOOKUP(B33,'Up Stats'!A:A,'Up Stats'!B:B,)} -> Magazine Size | F33: =IFERROR(__xludf.DUMMYFUNCTION("if(AND(G33=FALSE,H33=FALSE),,if(G33=H33,JOIN("""",""Static: "",G33),JOIN("""",""Min: "",G33, CHAR(10),""Max: "",H33)))"),"Min: 90% Max: 115%") -> Min: 90% Max: 115% | G33: {=_xlfn.XLOOKUP(B33,'Up Min'!A:A,'Up Min'!B:B,)} -> 0.9 | H33: {=_xlfn.XLOOKUP(B33,'Up Max'!A:A,'Up Max'!B:B,)} -> 1.15 | I33: {=_xlfn.XLOOKUP(B33,'Up Stats'!A:A,'Up Stats'!C:C,)} | J33: =IFERROR(__xludf.DUMMYFUNCTION("if(AND(K33=FALSE,L33=FALSE),,if(K33=L33,JOIN("""",""Static: "",K33),JOIN("""",""Min: "",K33, CHAR(10),""Max: "",L33)))"),"") | K33: {=_xlfn.XLOOKUP(B33,'Up Min'!A:A,'Up Min'!C:C,)} | L33: {=_xlfn.XLOOKUP(B33,'Up Max'!A:A,'Up Max'!C:C,)} | M33: {=_xlfn.XLOOKUP(B33,'Up Stats'!A:A,'Up Stats'!D:D,)} | N33: =IFERROR(__xludf.DUMMYFUNCTION("if(AND(O33=FALSE,P33=FALSE),,if(O33=P33,JOIN("""",""Static: "",O33),JOIN("""",""Min: "",O33, CHAR(10),""Max: "",P33)))"),"") | O33: {=_xlfn.XLOOKUP(B33,'Up Min'!A:A,'Up Min'!D:D,)} | P33: {=_xlfn.XLOOKUP(B33,'Up Max'!A:A,'Up Max'!D:D,)} | Q33: {=_xlfn.XLOOKUP(B33,'Up Stats'!A:A,'Up Stats'!E:E,)} | R33: =IFERROR(__xludf.DUMMYFUNCTION("if(AND(S33=FALSE,T33=FALSE),,if(S33=T33,JOIN("""",""Static: "",S33),JOIN("""",""Min: "",S33, CHAR(10),""Max: "",T33)))"),"") | S33: {=_xlfn.XLOOKUP(B33,'Up Min'!A:A,'Up Min'!E:E,)} | T33: {=_xlfn.XLOOKUP(B33,'Up Max'!A:A,'Up Max'!E:E,)} | U33: {=_xlfn.XLOOKUP(B33,'Up Stats'!A:A,'Up Stats'!F:F,)} | V33: =IFERROR(__xludf.DUMMYFUNCTION("if(AND(W33=FALSE,X33=FALSE),,if(W33=X33,JOIN("""",""Static: "",W33),JOIN("""",""Min: "",W33, CHAR(10),""Max: "",X33)))"),"") | W33: {=_xlfn.XLOOKUP(B33,'Up Min'!A:A,'Up Min'!F:F,)} | X33: {=_xlfn.XLOOKUP(B33,'Up Max'!A:A,'Up Max'!F:F,)} | Y33: {=_xlfn.XLOOKUP(B33,'Up Stats'!A:A,'Up Stats'!G:G,)} | Z33: =IFERROR(__xludf.DUMMYFUNCTION("if(AND(AA33=FALSE,AB33=FALSE),,if(AA33=AB33,JOIN("""",""Static: "",AA33),JOIN("""",""Min: "",AA33, CHAR(10),""Max: "",AB33)))"),"") | AA33: {=_xlfn.XLOOKUP(B33,'Up Min'!A:A,'Up Min'!G:G,)} | AB33: {=_xlfn.XLOOKUP(B33,'Up Max'!A:A,'Up Max'!G:G,)} | AC33: {=_xlfn.XLOOKUP(B33,'Up Stats'!A:A,'Up Stats'!H:H,)} | AD33: =IFERROR(__xludf.DUMMYFUNCTION("if(AND(AE33=FALSE,AF33=FALSE),,if(AE33=AF33,JOIN("""",""Static: "",AE33),JOIN("""",""Min: "",AE33, CHAR(10),""Max: "",AF33)))"),"") | AE33: {=_xlfn.XLOOKUP(B33,'Up Min'!A:A,'Up Min'!H:H,)} | AF33: {=_xlfn.XLOOKUP(B33,'Up Max'!A:A,'Up Max'!H:H,)} | AG33: {=_xlfn.XLOOKUP(B33,'Up Stats'!A:A,'Up Stats'!I:I,)} | AH33: =IFERROR(__xludf.DUMMYFUNCTION("if(AND(AI33=FALSE,AJ33=FALSE),,if(AI33=AJ33,JOIN("""",""Static: "",AI33),JOIN("""",""Min: "",AI33, CHAR(10),""Max: "",AJ33)))"),"") | AI33: {=_xlfn.XLOOKUP(B33,'Up Min'!A:A,'Up Min'!I:I,)} | AJ33: {=_xlfn.XLOOKUP(B33,'Up Max'!A:A,'Up Max'!I:I,)} | AK33: {=_xlfn.XLOOKUP(B33,'Up Stats'!A:A,'Up Stats'!J:J,)} | AL33: =IFERROR(__xludf.DUMMYFUNCTION("if(AND(AM33=FALSE,AN33=FALSE),,if(AM33=AN33,JOIN("""",""Static: "",AM33),JOIN("""",""Min: "",AM33, CHAR(10),""Max: "",AN33)))"),"") | AM33: {=_xlfn.XLOOKUP(B33,'Up Min'!A:A,'Up Min'!J:J,)} | AN33: {=_xlfn.XLOOKUP(B33,'Up Max'!A:A,'Up Max'!J:J,)} | AO33: {=CONCATENATE(_xlfn.XLOOKUP(B33,'Up Cells'!A:A,'Up Cells'!B:B,))} -> 8 | AP33: {=CONCATENATE(_xlfn.XLOOKUP(B33,'Up Rarity'!A:A,'Up Rarity'!B:B,),CHAR(10),"-")} -> Standard -
A34: {=_xlfn.XLOOKUP(B34,'Up Icon'!A:A,'Up Icon'!B:B,)} | B34: {=HYPERLINK(_xlfn.XLOOKUP('Up Names'!A31,'Up Wiki'!A:A,'Up Wiki'!B:B,),'Up Names'!A31)} -> Bulging Cartridge | C34: {=_xlfn.XLOOKUP(B34,'Up Desc'!A:A,'Up Desc'!B:B,)} -> Magazine size is increased. | D34: {=_xlfn.XLOOKUP(B34,'Up Turbo'!A:A,'Up Turbo'!B:B,)} -> n/a | E34: {=_xlfn.XLOOKUP(B34,'Up Stats'!A:A,'Up Stats'!B:B,)} -> Magazine Size | F34: =IFERROR(__xludf.DUMMYFUNCTION("if(AND(G34=FALSE,H34=FALSE),,if(G34=H34,JOIN("""",""Static: "",G34),JOIN("""",""Min: "",G34, CHAR(10),""Max: "",H34)))"),"Min: 4 Max: 10") -> Min: 4 Max: 10 | G34: {=_xlfn.XLOOKUP(B34,'Up Min'!A:A,'Up Min'!B:B,)} -> 4 | H34: {=_xlfn.XLOOKUP(B34,'Up Max'!A:A,'Up Max'!B:B,)} -> 10 | I34: {=_xlfn.XLOOKUP(B34,'Up Stats'!A:A,'Up Stats'!C:C,)} | J34: =IFERROR(__xludf.DUMMYFUNCTION("if(AND(K34=FALSE,L34=FALSE),,if(K34=L34,JOIN("""",""Static: "",K34),JOIN("""",""Min: "",K34, CHAR(10),""Max: "",L34)))"),"") | K34: {=_xlfn.XLOOKUP(B34,'Up Min'!A:A,'Up Min'!C:C,)} | L34: {=_xlfn.XLOOKUP(B34,'Up Max'!A:A,'Up Max'!C:C,)} | M34: {=_xlfn.XLOOKUP(B34,'Up Stats'!A:A,'Up Stats'!D:D,)} | N34: =IFERROR(__xludf.DUMMYFUNCTION("if(AND(O34=FALSE,P34=FALSE),,if(O34=P34,JOIN("""",""Static: "",O34),JOIN("""",""Min: "",O34, CHAR(10),""Max: "",P34)))"),"") | O34: {=_xlfn.XLOOKUP(B34,'Up Min'!A:A,'Up Min'!D:D,)} | P34: {=_xlfn.XLOOKUP(B34,'Up Max'!A:A,'Up Max'!D:D,)} | Q34: {=_xlfn.XLOOKUP(B34,'Up Stats'!A:A,'Up Stats'!E:E,)} | R34: =IFERROR(__xludf.DUMMYFUNCTION("if(AND(S34=FALSE,T34=FALSE),,if(S34=T34,JOIN("""",""Static: "",S34),JOIN("""",""Min: "",S34, CHAR(10),""Max: "",T34)))"),"") | S34: {=_xlfn.XLOOKUP(B34,'Up Min'!A:A,'Up Min'!E:E,)} | T34: {=_xlfn.XLOOKUP(B34,'Up Max'!A:A,'Up Max'!E:E,)} | U34: {=_xlfn.XLOOKUP(B34,'Up Stats'!A:A,'Up Stats'!F:F,)} | V34: =IFERROR(__xludf.DUMMYFUNCTION("if(AND(W34=FALSE,X34=FALSE),,if(W34=X34,JOIN("""",""Static: "",W34),JOIN("""",""Min: "",W34, CHAR(10),""Max: "",X34)))"),"") | W34: {=_xlfn.XLOOKUP(B34,'Up Min'!A:A,'Up Min'!F:F,)} | X34: {=_xlfn.XLOOKUP(B34,'Up Max'!A:A,'Up Max'!F:F,)} | Y34: {=_xlfn.XLOOKUP(B34,'Up Stats'!A:A,'Up Stats'!G:G,)} | Z34: =IFERROR(__xludf.DUMMYFUNCTION("if(AND(AA34=FALSE,AB34=FALSE),,if(AA34=AB34,JOIN("""",""Static: "",AA34),JOIN("""",""Min: "",AA34, CHAR(10),""Max: "",AB34)))"),"") | AA34: {=_xlfn.XLOOKUP(B34,'Up Min'!A:A,'Up Min'!G:G,)} | AB34: {=_xlfn.XLOOKUP(B34,'Up Max'!A:A,'Up Max'!G:G,)} | AC34: {=_xlfn.XLOOKUP(B34,'Up Stats'!A:A,'Up Stats'!H:H,)} | AD34: =IFERROR(__xludf.DUMMYFUNCTION("if(AND(AE34=FALSE,AF34=FALSE),,if(AE34=AF34,JOIN("""",""Static: "",AE34),JOIN("""",""Min: "",AE34, CHAR(10),""Max: "",AF34)))"),"") | AE34: {=_xlfn.XLOOKUP(B34,'Up Min'!A:A,'Up Min'!H:H,)} | AF34: {=_xlfn.XLOOKUP(B34,'Up Max'!A:A,'Up Max'!H:H,)} | AG34: {=_xlfn.XLOOKUP(B34,'Up Stats'!A:A,'Up Stats'!I:I,)} | AH34: =IFERROR(__xludf.DUMMYFUNCTION("if(AND(AI34=FALSE,AJ34=FALSE),,if(AI34=AJ34,JOIN("""",""Static: "",AI34),JOIN("""",""Min: "",AI34, CHAR(10),""Max: "",AJ34)))"),"") | AI34: {=_xlfn.XLOOKUP(B34,'Up Min'!A:A,'Up Min'!I:I,)} | AJ34: {=_xlfn.XLOOKUP(B34,'Up Max'!A:A,'Up Max'!I:I,)} | AK34: {=_xlfn.XLOOKUP(B34,'Up Stats'!A:A,'Up Stats'!J:J,)} | AL34: =IFERROR(__xludf.DUMMYFUNCTION("if(AND(AM34=FALSE,AN34=FALSE),,if(AM34=AN34,JOIN("""",""Static: "",AM34),JOIN("""",""Min: "",AM34, CHAR(10),""Max: "",AN34)))"),"") | AM34: {=_xlfn.XLOOKUP(B34,'Up Min'!A:A,'Up Min'!J:J,)} | AN34: {=_xlfn.XLOOKUP(B34,'Up Max'!A:A,'Up Max'!J:J,)} | AO34: {=CONCATENATE(_xlfn.XLOOKUP(B34,'Up Cells'!A:A,'Up Cells'!B:B,))} -> 3 | AP34: {=CONCATENATE(_xlfn.XLOOKUP(B34,'Up Rarity'!A:A,'Up Rarity'!B:B,),CHAR(10),"-")} -> Standard -
A35: {=_xlfn.XLOOKUP(B35,'Up Icon'!A:A,'Up Icon'!B:B,)} | B35: {=HYPERLINK(_xlfn.XLOOKUP('Up Names'!A32,'Up Wiki'!A:A,'Up Wiki'!B:B,),'Up Names'!A32)} -> Compact Cartridge | C35: {=_xlfn.XLOOKUP(B35,'Up Desc'!A:A,'Up Desc'!B:B,)} -> Reload speed is increased but magazine size is decreased. | D35: {=_xlfn.XLOOKUP(B35,'Up Turbo'!A:A,'Up Turbo'!B:B,)} -> n/a | E35: {=_xlfn.XLOOKUP(B35,'Up Stats'!A:A,'Up Stats'!B:B,)} -> Magazine Size | F35: =IFERROR(__xludf.DUMMYFUNCTION("if(AND(G35=FALSE,H35=FALSE),,if(G35=H35,JOIN("""",""Static: "",G35),JOIN("""",""Min: "",G35, CHAR(10),""Max: "",H35)))"),"Min: -9 Max: -7") -> Min: -9 Max: -7 | G35: {=_xlfn.XLOOKUP(B35,'Up Min'!A:A,'Up Min'!B:B,)} -> -9 | H35: {=_xlfn.XLOOKUP(B35,'Up Max'!A:A,'Up Max'!B:B,)} -> -7 | I35: {=_xlfn.XLOOKUP(B35,'Up Stats'!A:A,'Up Stats'!C:C,)} -> Reload Speed | J35: =IFERROR(__xludf.DUMMYFUNCTION("if(AND(K35=FALSE,L35=FALSE),,if(K35=L35,JOIN("""",""Static: "",K35),JOIN("""",""Min: "",K35, CHAR(10),""Max: "",L35)))"),"Min: 33.93% Max: 25%") -> Min: 33.93% Max: 25% | K35: {=_xlfn.XLOOKUP(B35,'Up Min'!A:A,'Up Min'!C:C,)} -> 0.3393 | L35: {=_xlfn.XLOOKUP(B35,'Up Max'!A:A,'Up Max'!C:C,)} -> 0.25 | M35: {=_xlfn.XLOOKUP(B35,'Up Stats'!A:A,'Up Stats'!D:D,)} | N35: =IFERROR(__xludf.DUMMYFUNCTION("if(AND(O35=FALSE,P35=FALSE),,if(O35=P35,JOIN("""",""Static: "",O35),JOIN("""",""Min: "",O35, CHAR(10),""Max: "",P35)))"),"") | O35: {=_xlfn.XLOOKUP(B35,'Up Min'!A:A,'Up Min'!D:D,)} | P35: {=_xlfn.XLOOKUP(B35,'Up Max'!A:A,'Up Max'!D:D,)} | Q35: {=_xlfn.XLOOKUP(B35,'Up Stats'!A:A,'Up Stats'!E:E,)} | R35: =IFERROR(__xludf.DUMMYFUNCTION("if(AND(S35=FALSE,T35=FALSE),,if(S35=T35,JOIN("""",""Static: "",S35),JOIN("""",""Min: "",S35, CHAR(10),""Max: "",T35)))"),"") | S35: {=_xlfn.XLOOKUP(B35,'Up Min'!A:A,'Up Min'!E:E,)} | T35: {=_xlfn.XLOOKUP(B35,'Up Max'!A:A,'Up Max'!E:E,)} | U35: {=_xlfn.XLOOKUP(B35,'Up Stats'!A:A,'Up Stats'!F:F,)} | V35: =IFERROR(__xludf.DUMMYFUNCTION("if(AND(W35=FALSE,X35=FALSE),,if(W35=X35,JOIN("""",""Static: "",W35),JOIN("""",""Min: "",W35, CHAR(10),""Max: "",X35)))"),"") | W35: {=_xlfn.XLOOKUP(B35,'Up Min'!A:A,'Up Min'!F:F,)} | X35: {=_xlfn.XLOOKUP(B35,'Up Max'!A:A,'Up Max'!F:F,)} | Y35: {=_xlfn.XLOOKUP(B35,'Up Stats'!A:A,'Up Stats'!G:G,)} | Z35: =IFERROR(__xludf.DUMMYFUNCTION("if(AND(AA35=FALSE,AB35=FALSE),,if(AA35=AB35,JOIN("""",""Static: "",AA35),JOIN("""",""Min: "",AA35, CHAR(10),""Max: "",AB35)))"),"") | AA35: {=_xlfn.XLOOKUP(B35,'Up Min'!A:A,'Up Min'!G:G,)} | AB35: {=_xlfn.XLOOKUP(B35,'Up Max'!A:A,'Up Max'!G:G,)} | AC35: {=_xlfn.XLOOKUP(B35,'Up Stats'!A:A,'Up Stats'!H:H,)} | AD35: =IFERROR(__xludf.DUMMYFUNCTION("if(AND(AE35=FALSE,AF35=FALSE),,if(AE35=AF35,JOIN("""",""Static: "",AE35),JOIN("""",""Min: "",AE35, CHAR(10),""Max: "",AF35)))"),"") | AE35: {=_xlfn.XLOOKUP(B35,'Up Min'!A:A,'Up Min'!H:H,)} | AF35: {=_xlfn.XLOOKUP(B35,'Up Max'!A:A,'Up Max'!H:H,)} | AG35: {=_xlfn.XLOOKUP(B35,'Up Stats'!A:A,'Up Stats'!I:I,)} | AH35: =IFERROR(__xludf.DUMMYFUNCTION("if(AND(AI35=FALSE,AJ35=FALSE),,if(AI35=AJ35,JOIN("""",""Static: "",AI35),JOIN("""",""Min: "",AI35, CHAR(10),""Max: "",AJ35)))"),"") | AI35: {=_xlfn.XLOOKUP(B35,'Up Min'!A:A,'Up Min'!I:I,)} | AJ35: {=_xlfn.XLOOKUP(B35,'Up Max'!A:A,'Up Max'!I:I,)} | AK35: {=_xlfn.XLOOKUP(B35,'Up Stats'!A:A,'Up Stats'!J:J,)} | AL35: =IFERROR(__xludf.DUMMYFUNCTION("if(AND(AM35=FALSE,AN35=FALSE),,if(AM35=AN35,JOIN("""",""Static: "",AM35),JOIN("""",""Min: "",AM35, CHAR(10),""Max: "",AN35)))"),"") | AM35: {=_xlfn.XLOOKUP(B35,'Up Min'!A:A,'Up Min'!J:J,)} | AN35: {=_xlfn.XLOOKUP(B35,'Up Max'!A:A,'Up Max'!J:J,)} | AO35: {=CONCATENATE(_xlfn.XLOOKUP(B35,'Up Cells'!A:A,'Up Cells'!B:B,))} -> 3 | AP35: {=CONCATENATE(_xlfn.XLOOKUP(B35,'Up Rarity'!A:A,'Up Rarity'!B:B,),CHAR(10),"-")} -> Standard -
A36: {=_xlfn.XLOOKUP(B36,'Up Icon'!A:A,'Up Icon'!B:B,)} | B36: {=HYPERLINK(_xlfn.XLOOKUP('Up Names'!A33,'Up Wiki'!A:A,'Up Wiki'!B:B,),'Up Names'!A33)} -> Doublestack Cartridge | C36: {=_xlfn.XLOOKUP(B36,'Up Desc'!A:A,'Up Desc'!B:B,)} -> Magazine size is increased, but damage is slightly decreased. | D36: {=_xlfn.XLOOKUP(B36,'Up Turbo'!A:A,'Up Turbo'!B:B,)} -> n/a | E36: {=_xlfn.XLOOKUP(B36,'Up Stats'!A:A,'Up Stats'!B:B,)} -> Magazine Size | F36: =IFERROR(__xludf.DUMMYFUNCTION("if(AND(G36=FALSE,H36=FALSE),,if(G36=H36,JOIN("""",""Static: "",G36),JOIN("""",""Min: "",G36, CHAR(10),""Max: "",H36)))"),"Min: 20% Max: 40%") -> Min: 20% Max: 40% | G36: {=_xlfn.XLOOKUP(B36,'Up Min'!A:A,'Up Min'!B:B,)} -> 0.2 | H36: {=_xlfn.XLOOKUP(B36,'Up Max'!A:A,'Up Max'!B:B,)} -> 0.4 | I36: {=_xlfn.XLOOKUP(B36,'Up Stats'!A:A,'Up Stats'!C:C,)} -> Damage | J36: =IFERROR(__xludf.DUMMYFUNCTION("if(AND(K36=FALSE,L36=FALSE),,if(K36=L36,JOIN("""",""Static: "",K36),JOIN("""",""Min: "",K36, CHAR(10),""Max: "",L36)))"),"Min: -12% Max: -7%") -> Min: -12% Max: -7% | K36: {=_xlfn.XLOOKUP(B36,'Up Min'!A:A,'Up Min'!C:C,)} -> -0.12 | L36: {=_xlfn.XLOOKUP(B36,'Up Max'!A:A,'Up Max'!C:C,)} -> -0.07 | M36: {=_xlfn.XLOOKUP(B36,'Up Stats'!A:A,'Up Stats'!D:D,)} | N36: =IFERROR(__xludf.DUMMYFUNCTION("if(AND(O36=FALSE,P36=FALSE),,if(O36=P36,JOIN("""",""Static: "",O36),JOIN("""",""Min: "",O36, CHAR(10),""Max: "",P36)))"),"") | O36: {=_xlfn.XLOOKUP(B36,'Up Min'!A:A,'Up Min'!D:D,)} | P36: {=_xlfn.XLOOKUP(B36,'Up Max'!A:A,'Up Max'!D:D,)} | Q36: {=_xlfn.XLOOKUP(B36,'Up Stats'!A:A,'Up Stats'!E:E,)} | R36: =IFERROR(__xludf.DUMMYFUNCTION("if(AND(S36=FALSE,T36=FALSE),,if(S36=T36,JOIN("""",""Static: "",S36),JOIN("""",""Min: "",S36, CHAR(10),""Max: "",T36)))"),"") | S36: {=_xlfn.XLOOKUP(B36,'Up Min'!A:A,'Up Min'!E:E,)} | T36: {=_xlfn.XLOOKUP(B36,'Up Max'!A:A,'Up Max'!E:E,)} | U36: {=_xlfn.XLOOKUP(B36,'Up Stats'!A:A,'Up Stats'!F:F,)} | V36: =IFERROR(__xludf.DUMMYFUNCTION("if(AND(W36=FALSE,X36=FALSE),,if(W36=X36,JOIN("""",""Static: "",W36),JOIN("""",""Min: "",W36, CHAR(10),""Max: "",X36)))"),"") | W36: {=_xlfn.XLOOKUP(B36,'Up Min'!A:A,'Up Min'!F:F,)} | X36: {=_xlfn.XLOOKUP(B36,'Up Max'!A:A,'Up Max'!F:F,)} | Y36: {=_xlfn.XLOOKUP(B36,'Up Stats'!A:A,'Up Stats'!G:G,)} | Z36: =IFERROR(__xludf.DUMMYFUNCTION("if(AND(AA36=FALSE,AB36=FALSE),,if(AA36=AB36,JOIN("""",""Static: "",AA36),JOIN("""",""Min: "",AA36, CHAR(10),""Max: "",AB36)))"),"") | AA36: {=_xlfn.XLOOKUP(B36,'Up Min'!A:A,'Up Min'!G:G,)} | AB36: {=_xlfn.XLOOKUP(B36,'Up Max'!A:A,'Up Max'!G:G,)} | AC36: {=_xlfn.XLOOKUP(B36,'Up Stats'!A:A,'Up Stats'!H:H,)} | AD36: =IFERROR(__xludf.DUMMYFUNCTION("if(AND(AE36=FALSE,AF36=FALSE),,if(AE36=AF36,JOIN("""",""Static: "",AE36),JOIN("""",""Min: "",AE36, CHAR(10),""Max: "",AF36)))"),"") | AE36: {=_xlfn.XLOOKUP(B36,'Up Min'!A:A,'Up Min'!H:H,)} | AF36: {=_xlfn.XLOOKUP(B36,'Up Max'!A:A,'Up Max'!H:H,)} | AG36: {=_xlfn.XLOOKUP(B36,'Up Stats'!A:A,'Up Stats'!I:I,)} | AH36: =IFERROR(__xludf.DUMMYFUNCTION("if(AND(AI36=FALSE,AJ36=FALSE),,if(AI36=AJ36,JOIN("""",""Static: "",AI36),JOIN("""",""Min: "",AI36, CHAR(10),""Max: "",AJ36)))"),"") | AI36: {=_xlfn.XLOOKUP(B36,'Up Min'!A:A,'Up Min'!I:I,)} | AJ36: {=_xlfn.XLOOKUP(B36,'Up Max'!A:A,'Up Max'!I:I,)} | AK36: {=_xlfn.XLOOKUP(B36,'Up Stats'!A:A,'Up Stats'!J:J,)} | AL36: =IFERROR(__xludf.DUMMYFUNCTION("if(AND(AM36=FALSE,AN36=FALSE),,if(AM36=AN36,JOIN("""",""Static: "",AM36),JOIN("""",""Min: "",AM36, CHAR(10),""Max: "",AN36)))"),"") | AM36: {=_xlfn.XLOOKUP(B36,'Up Min'!A:A,'Up Min'!J:J,)} | AN36: {=_xlfn.XLOOKUP(B36,'Up Max'!A:A,'Up Max'!J:J,)} | AO36: {=CONCATENATE(_xlfn.XLOOKUP(B36,'Up Cells'!A:A,'Up Cells'!B:B,))} -> 3 | AP36: {=CONCATENATE(_xlfn.XLOOKUP(B36,'Up Rarity'!A:A,'Up Rarity'!B:B,),CHAR(10),"-")} -> Standard -
A37: {=_xlfn.XLOOKUP(B37,'Up Icon'!A:A,'Up Icon'!B:B,)} | B37: {=HYPERLINK(_xlfn.XLOOKUP('Up Names'!A34,'Up Wiki'!A:A,'Up Wiki'!B:B,),'Up Names'!A34)} -> Focused Lenses | C37: {=_xlfn.XLOOKUP(B37,'Up Desc'!A:A,'Up Desc'!B:B,)} -> Range is increased. | D37: {=_xlfn.XLOOKUP(B37,'Up Turbo'!A:A,'Up Turbo'!B:B,)} -> n/a | E37: {=_xlfn.XLOOKUP(B37,'Up Stats'!A:A,'Up Stats'!B:B,)} -> Range | F37: =IFERROR(__xludf.DUMMYFUNCTION("if(AND(G37=FALSE,H37=FALSE),,if(G37=H37,JOIN("""",""Static: "",G37),JOIN("""",""Min: "",G37, CHAR(10),""Max: "",H37)))"),"Min: 8 Max: 11") -> Min: 8 Max: 11 | G37: {=_xlfn.XLOOKUP(B37,'Up Min'!A:A,'Up Min'!B:B,)} -> 8 | H37: {=_xlfn.XLOOKUP(B37,'Up Max'!A:A,'Up Max'!B:B,)} -> 11 | I37: {=_xlfn.XLOOKUP(B37,'Up Stats'!A:A,'Up Stats'!C:C,)} | J37: =IFERROR(__xludf.DUMMYFUNCTION("if(AND(K37=FALSE,L37=FALSE),,if(K37=L37,JOIN("""",""Static: "",K37),JOIN("""",""Min: "",K37, CHAR(10),""Max: "",L37)))"),"") | K37: {=_xlfn.XLOOKUP(B37,'Up Min'!A:A,'Up Min'!C:C,)} | L37: {=_xlfn.XLOOKUP(B37,'Up Max'!A:A,'Up Max'!C:C,)} | M37: {=_xlfn.XLOOKUP(B37,'Up Stats'!A:A,'Up Stats'!D:D,)} | N37: =IFERROR(__xludf.DUMMYFUNCTION("if(AND(O37=FALSE,P37=FALSE),,if(O37=P37,JOIN("""",""Static: "",O37),JOIN("""",""Min: "",O37, CHAR(10),""Max: "",P37)))"),"") | O37: {=_xlfn.XLOOKUP(B37,'Up Min'!A:A,'Up Min'!D:D,)} | P37: {=_xlfn.XLOOKUP(B37,'Up Max'!A:A,'Up Max'!D:D,)} | Q37: {=_xlfn.XLOOKUP(B37,'Up Stats'!A:A,'Up Stats'!E:E,)} | R37: =IFERROR(__xludf.DUMMYFUNCTION("if(AND(S37=FALSE,T37=FALSE),,if(S37=T37,JOIN("""",""Static: "",S37),JOIN("""",""Min: "",S37, CHAR(10),""Max: "",T37)))"),"") | S37: {=_xlfn.XLOOKUP(B37,'Up Min'!A:A,'Up Min'!E:E,)} | T37: {=_xlfn.XLOOKUP(B37,'Up Max'!A:A,'Up Max'!E:E,)} | U37: {=_xlfn.XLOOKUP(B37,'Up Stats'!A:A,'Up Stats'!F:F,)} | V37: =IFERROR(__xludf.DUMMYFUNCTION("if(AND(W37=FALSE,X37=FALSE),,if(W37=X37,JOIN("""",""Static: "",W37),JOIN("""",""Min: "",W37, CHAR(10),""Max: "",X37)))"),"") | W37: {=_xlfn.XLOOKUP(B37,'Up Min'!A:A,'Up Min'!F:F,)} | X37: {=_xlfn.XLOOKUP(B37,'Up Max'!A:A,'Up Max'!F:F,)} | Y37: {=_xlfn.XLOOKUP(B37,'Up Stats'!A:A,'Up Stats'!G:G,)} | Z37: =IFERROR(__xludf.DUMMYFUNCTION("if(AND(AA37=FALSE,AB37=FALSE),,if(AA37=AB37,JOIN("""",""Static: "",AA37),JOIN("""",""Min: "",AA37, CHAR(10),""Max: "",AB37)))"),"") | AA37: {=_xlfn.XLOOKUP(B37,'Up Min'!A:A,'Up Min'!G:G,)} | AB37: {=_xlfn.XLOOKUP(B37,'Up Max'!A:A,'Up Max'!G:G,)} | AC37: {=_xlfn.XLOOKUP(B37,'Up Stats'!A:A,'Up Stats'!H:H,)} | AD37: =IFERROR(__xludf.DUMMYFUNCTION("if(AND(AE37=FALSE,AF37=FALSE),,if(AE37=AF37,JOIN("""",""Static: "",AE37),JOIN("""",""Min: "",AE37, CHAR(10),""Max: "",AF37)))"),"") | AE37: {=_xlfn.XLOOKUP(B37,'Up Min'!A:A,'Up Min'!H:H,)} | AF37: {=_xlfn.XLOOKUP(B37,'Up Max'!A:A,'Up Max'!H:H,)} | AG37: {=_xlfn.XLOOKUP(B37,'Up Stats'!A:A,'Up Stats'!I:I,)} | AH37: =IFERROR(__xludf.DUMMYFUNCTION("if(AND(AI37=FALSE,AJ37=FALSE),,if(AI37=AJ37,JOIN("""",""Static: "",AI37),JOIN("""",""Min: "",AI37, CHAR(10),""Max: "",AJ37)))"),"") | AI37: {=_xlfn.XLOOKUP(B37,'Up Min'!A:A,'Up Min'!I:I,)} | AJ37: {=_xlfn.XLOOKUP(B37,'Up Max'!A:A,'Up Max'!I:I,)} | AK37: {=_xlfn.XLOOKUP(B37,'Up Stats'!A:A,'Up Stats'!J:J,)} | AL37: =IFERROR(__xludf.DUMMYFUNCTION("if(AND(AM37=FALSE,AN37=FALSE),,if(AM37=AN37,JOIN("""",""Static: "",AM37),JOIN("""",""Min: "",AM37, CHAR(10),""Max: "",AN37)))"),"") | AM37: {=_xlfn.XLOOKUP(B37,'Up Min'!A:A,'Up Min'!J:J,)} | AN37: {=_xlfn.XLOOKUP(B37,'Up Max'!A:A,'Up Max'!J:J,)} | AO37: {=CONCATENATE(_xlfn.XLOOKUP(B37,'Up Cells'!A:A,'Up Cells'!B:B,))} -> 3 | AP37: {=CONCATENATE(_xlfn.XLOOKUP(B37,'Up Rarity'!A:A,'Up Rarity'!B:B,),CHAR(10),"-")} -> Standard -
A38: {=_xlfn.XLOOKUP(B38,'Up Icon'!A:A,'Up Icon'!B:B,)} | B38: {=HYPERLINK(_xlfn.XLOOKUP('Up Names'!A35,'Up Wiki'!A:A,'Up Wiki'!B:B,),'Up Names'!A35)} -> Precision Fire | C38: {=_xlfn.XLOOKUP(B38,'Up Desc'!A:A,'Up Desc'!B:B,)} -> Fire slower with more accuracy. | D38: {=_xlfn.XLOOKUP(B38,'Up Turbo'!A:A,'Up Turbo'!B:B,)} -> n/a | E38: {=_xlfn.XLOOKUP(B38,'Up Stats'!A:A,'Up Stats'!B:B,)} -> Horizontal Spread | F38: =IFERROR(__xludf.DUMMYFUNCTION("if(AND(G38=FALSE,H38=FALSE),,if(G38=H38,JOIN("""",""Static: "",G38),JOIN("""",""Min: "",G38, CHAR(10),""Max: "",H38)))"),"Min: -80% Max: -70%") -> Min: -80% Max: -70% | G38: {=_xlfn.XLOOKUP(B38,'Up Min'!A:A,'Up Min'!B:B,)} -> -0.8 | H38: {=_xlfn.XLOOKUP(B38,'Up Max'!A:A,'Up Max'!B:B,)} -> -0.7 | I38: {=_xlfn.XLOOKUP(B38,'Up Stats'!A:A,'Up Stats'!C:C,)} -> Vertical Spread | J38: =IFERROR(__xludf.DUMMYFUNCTION("if(AND(K38=FALSE,L38=FALSE),,if(K38=L38,JOIN("""",""Static: "",K38),JOIN("""",""Min: "",K38, CHAR(10),""Max: "",L38)))"),"Min: -80% Max: -70%") -> Min: -80% Max: -70% | K38: {=_xlfn.XLOOKUP(B38,'Up Min'!A:A,'Up Min'!C:C,)} -> -0.8 | L38: {=_xlfn.XLOOKUP(B38,'Up Max'!A:A,'Up Max'!C:C,)} -> -0.7 | M38: {=_xlfn.XLOOKUP(B38,'Up Stats'!A:A,'Up Stats'!D:D,)} -> Fire Rate | N38: =IFERROR(__xludf.DUMMYFUNCTION("if(AND(O38=FALSE,P38=FALSE),,if(O38=P38,JOIN("""",""Static: "",O38),JOIN("""",""Min: "",O38, CHAR(10),""Max: "",P38)))"),"Min: -18.70% Max: -21.26%") -> Min: -18.70% Max: -21.26% | O38: {=_xlfn.XLOOKUP(B38,'Up Min'!A:A,'Up Min'!D:D,)} -> -0.187 | P38: {=_xlfn.XLOOKUP(B38,'Up Max'!A:A,'Up Max'!D:D,)} -> -0.2126 | Q38: {=_xlfn.XLOOKUP(B38,'Up Stats'!A:A,'Up Stats'!E:E,)} | R38: =IFERROR(__xludf.DUMMYFUNCTION("if(AND(S38=FALSE,T38=FALSE),,if(S38=T38,JOIN("""",""Static: "",S38),JOIN("""",""Min: "",S38, CHAR(10),""Max: "",T38)))"),"") | S38: {=_xlfn.XLOOKUP(B38,'Up Min'!A:A,'Up Min'!E:E,)} | T38: {=_xlfn.XLOOKUP(B38,'Up Max'!A:A,'Up Max'!E:E,)} | U38: {=_xlfn.XLOOKUP(B38,'Up Stats'!A:A,'Up Stats'!F:F,)} | V38: =IFERROR(__xludf.DUMMYFUNCTION("if(AND(W38=FALSE,X38=FALSE),,if(W38=X38,JOIN("""",""Static: "",W38),JOIN("""",""Min: "",W38, CHAR(10),""Max: "",X38)))"),"") | W38: {=_xlfn.XLOOKUP(B38,'Up Min'!A:A,'Up Min'!F:F,)} | X38: {=_xlfn.XLOOKUP(B38,'Up Max'!A:A,'Up Max'!F:F,)} | Y38: {=_xlfn.XLOOKUP(B38,'Up Stats'!A:A,'Up Stats'!G:G,)} | Z38: =IFERROR(__xludf.DUMMYFUNCTION("if(AND(AA38=FALSE,AB38=FALSE),,if(AA38=AB38,JOIN("""",""Static: "",AA38),JOIN("""",""Min: "",AA38, CHAR(10),""Max: "",AB38)))"),"") | AA38: {=_xlfn.XLOOKUP(B38,'Up Min'!A:A,'Up Min'!G:G,)} | AB38: {=_xlfn.XLOOKUP(B38,'Up Max'!A:A,'Up Max'!G:G,)} | AC38: {=_xlfn.XLOOKUP(B38,'Up Stats'!A:A,'Up Stats'!H:H,)} | AD38: =IFERROR(__xludf.DUMMYFUNCTION("if(AND(AE38=FALSE,AF38=FALSE),,if(AE38=AF38,JOIN("""",""Static: "",AE38),JOIN("""",""Min: "",AE38, CHAR(10),""Max: "",AF38)))"),"") | AE38: {=_xlfn.XLOOKUP(B38,'Up Min'!A:A,'Up Min'!H:H,)} | AF38: {=_xlfn.XLOOKUP(B38,'Up Max'!A:A,'Up Max'!H:H,)} | AG38: {=_xlfn.XLOOKUP(B38,'Up Stats'!A:A,'Up Stats'!I:I,)} | AH38: =IFERROR(__xludf.DUMMYFUNCTION("if(AND(AI38=FALSE,AJ38=FALSE),,if(AI38=AJ38,JOIN("""",""Static: "",AI38),JOIN("""",""Min: "",AI38, CHAR(10),""Max: "",AJ38)))"),"") | AI38: {=_xlfn.XLOOKUP(B38,'Up Min'!A:A,'Up Min'!I:I,)} | AJ38: {=_xlfn.XLOOKUP(B38,'Up Max'!A:A,'Up Max'!I:I,)} | AK38: {=_xlfn.XLOOKUP(B38,'Up Stats'!A:A,'Up Stats'!J:J,)} | AL38: =IFERROR(__xludf.DUMMYFUNCTION("if(AND(AM38=FALSE,AN38=FALSE),,if(AM38=AN38,JOIN("""",""Static: "",AM38),JOIN("""",""Min: "",AM38, CHAR(10),""Max: "",AN38)))"),"") | AM38: {=_xlfn.XLOOKUP(B38,'Up Min'!A:A,'Up Min'!J:J,)} | AN38: {=_xlfn.XLOOKUP(B38,'Up Max'!A:A,'Up Max'!J:J,)} | AO38: {=CONCATENATE(_xlfn.XLOOKUP(B38,'Up Cells'!A:A,'Up Cells'!B:B,))} -> 3 | AP38: {=CONCATENATE(_xlfn.XLOOKUP(B38,'Up Rarity'!A:A,'Up Rarity'!B:B,),CHAR(10),"-")} -> Standard -
A39: {=_xlfn.XLOOKUP(B39,'Up Icon'!A:A,'Up Icon'!B:B,)} | B39: {=HYPERLINK(_xlfn.XLOOKUP('Up Names'!A36,'Up Wiki'!A:A,'Up Wiki'!B:B,),'Up Names'!A36)} -> Ricochet | C39: {=_xlfn.XLOOKUP(B39,'Up Desc'!A:A,'Up Desc'!B:B,)} -> Bullets ricochet. | D39: {=_xlfn.XLOOKUP(B39,'Up Turbo'!A:A,'Up Turbo'!B:B,)} -> n/a | E39: {=_xlfn.XLOOKUP(B39,'Up Stats'!A:A,'Up Stats'!B:B,)} -> Bounces | F39: =IFERROR(__xludf.DUMMYFUNCTION("if(AND(G39=FALSE,H39=FALSE),,if(G39=H39,JOIN("""",""Static: "",G39),JOIN("""",""Min: "",G39, CHAR(10),""Max: "",H39)))"),"Static: 1") -> Static: 1 | G39: {=_xlfn.XLOOKUP(B39,'Up Min'!A:A,'Up Min'!B:B,)} -> 1 | H39: {=_xlfn.XLOOKUP(B39,'Up Max'!A:A,'Up Max'!B:B,)} -> 1 | I39: {=_xlfn.XLOOKUP(B39,'Up Stats'!A:A,'Up Stats'!C:C,)} | J39: =IFERROR(__xludf.DUMMYFUNCTION("if(AND(K39=FALSE,L39=FALSE),,if(K39=L39,JOIN("""",""Static: "",K39),JOIN("""",""Min: "",K39, CHAR(10),""Max: "",L39)))"),"") | K39: {=_xlfn.XLOOKUP(B39,'Up Min'!A:A,'Up Min'!C:C,)} | L39: {=_xlfn.XLOOKUP(B39,'Up Max'!A:A,'Up Max'!C:C,)} | M39: {=_xlfn.XLOOKUP(B39,'Up Stats'!A:A,'Up Stats'!D:D,)} | N39: =IFERROR(__xludf.DUMMYFUNCTION("if(AND(O39=FALSE,P39=FALSE),,if(O39=P39,JOIN("""",""Static: "",O39),JOIN("""",""Min: "",O39, CHAR(10),""Max: "",P39)))"),"") | O39: {=_xlfn.XLOOKUP(B39,'Up Min'!A:A,'Up Min'!D:D,)} | P39: {=_xlfn.XLOOKUP(B39,'Up Max'!A:A,'Up Max'!D:D,)} | Q39: {=_xlfn.XLOOKUP(B39,'Up Stats'!A:A,'Up Stats'!E:E,)} | R39: =IFERROR(__xludf.DUMMYFUNCTION("if(AND(S39=FALSE,T39=FALSE),,if(S39=T39,JOIN("""",""Static: "",S39),JOIN("""",""Min: "",S39, CHAR(10),""Max: "",T39)))"),"") | S39: {=_xlfn.XLOOKUP(B39,'Up Min'!A:A,'Up Min'!E:E,)} | T39: {=_xlfn.XLOOKUP(B39,'Up Max'!A:A,'Up Max'!E:E,)} | U39: {=_xlfn.XLOOKUP(B39,'Up Stats'!A:A,'Up Stats'!F:F,)} | V39: =IFERROR(__xludf.DUMMYFUNCTION("if(AND(W39=FALSE,X39=FALSE),,if(W39=X39,JOIN("""",""Static: "",W39),JOIN("""",""Min: "",W39, CHAR(10),""Max: "",X39)))"),"") | W39: {=_xlfn.XLOOKUP(B39,'Up Min'!A:A,'Up Min'!F:F,)} | X39: {=_xlfn.XLOOKUP(B39,'Up Max'!A:A,'Up Max'!F:F,)} | Y39: {=_xlfn.XLOOKUP(B39,'Up Stats'!A:A,'Up Stats'!G:G,)} | Z39: =IFERROR(__xludf.DUMMYFUNCTION("if(AND(AA39=FALSE,AB39=FALSE),,if(AA39=AB39,JOIN("""",""Static: "",AA39),JOIN("""",""Min: "",AA39, CHAR(10),""Max: "",AB39)))"),"") | AA39: {=_xlfn.XLOOKUP(B39,'Up Min'!A:A,'Up Min'!G:G,)} | AB39: {=_xlfn.XLOOKUP(B39,'Up Max'!A:A,'Up Max'!G:G,)} | AC39: {=_xlfn.XLOOKUP(B39,'Up Stats'!A:A,'Up Stats'!H:H,)} | AD39: =IFERROR(__xludf.DUMMYFUNCTION("if(AND(AE39=FALSE,AF39=FALSE),,if(AE39=AF39,JOIN("""",""Static: "",AE39),JOIN("""",""Min: "",AE39, CHAR(10),""Max: "",AF39)))"),"") | AE39: {=_xlfn.XLOOKUP(B39,'Up Min'!A:A,'Up Min'!H:H,)} | AF39: {=_xlfn.XLOOKUP(B39,'Up Max'!A:A,'Up Max'!H:H,)} | AG39: {=_xlfn.XLOOKUP(B39,'Up Stats'!A:A,'Up Stats'!I:I,)} | AH39: =IFERROR(__xludf.DUMMYFUNCTION("if(AND(AI39=FALSE,AJ39=FALSE),,if(AI39=AJ39,JOIN("""",""Static: "",AI39),JOIN("""",""Min: "",AI39, CHAR(10),""Max: "",AJ39)))"),"") | AI39: {=_xlfn.XLOOKUP(B39,'Up Min'!A:A,'Up Min'!I:I,)} | AJ39: {=_xlfn.XLOOKUP(B39,'Up Max'!A:A,'Up Max'!I:I,)} | AK39: {=_xlfn.XLOOKUP(B39,'Up Stats'!A:A,'Up Stats'!J:J,)} | AL39: =IFERROR(__xludf.DUMMYFUNCTION("if(AND(AM39=FALSE,AN39=FALSE),,if(AM39=AN39,JOIN("""",""Static: "",AM39),JOIN("""",""Min: "",AM39, CHAR(10),""Max: "",AN39)))"),"") | AM39: {=_xlfn.XLOOKUP(B39,'Up Min'!A:A,'Up Min'!J:J,)} | AN39: {=_xlfn.XLOOKUP(B39,'Up Max'!A:A,'Up Max'!J:J,)} | AO39: {=CONCATENATE(_xlfn.XLOOKUP(B39,'Up Cells'!A:A,'Up Cells'!B:B,))} -> 4 | AP39: {=CONCATENATE(_xlfn.XLOOKUP(B39,'Up Rarity'!A:A,'Up Rarity'!B:B,),CHAR(10),"-")} -> Standard -
A40: {=_xlfn.XLOOKUP(B40,'Up Icon'!A:A,'Up Icon'!B:B,)} | B40: {=HYPERLINK(_xlfn.XLOOKUP('Up Names'!A37,'Up Wiki'!A:A,'Up Wiki'!B:B,),'Up Names'!A37)} -> Stability Module | C40: {=_xlfn.XLOOKUP(B40,'Up Desc'!A:A,'Up Desc'!B:B,)} -> Recoil is reduced while aiming. | D40: {=_xlfn.XLOOKUP(B40,'Up Turbo'!A:A,'Up Turbo'!B:B,)} -> n/a | E40: {=_xlfn.XLOOKUP(B40,'Up Stats'!A:A,'Up Stats'!B:B,)} -> Aim Recoil | F40: =IFERROR(__xludf.DUMMYFUNCTION("if(AND(G40=FALSE,H40=FALSE),,if(G40=H40,JOIN("""",""Static: "",G40),JOIN("""",""Min: "",G40, CHAR(10),""Max: "",H40)))"),"Min: -42% Max: -30%") -> Min: -42% Max: -30% | G40: {=_xlfn.XLOOKUP(B40,'Up Min'!A:A,'Up Min'!B:B,)} -> -0.42 | H40: {=_xlfn.XLOOKUP(B40,'Up Max'!A:A,'Up Max'!B:B,)} -> -0.3 | I40: {=_xlfn.XLOOKUP(B40,'Up Stats'!A:A,'Up Stats'!C:C,)} | J40: =IFERROR(__xludf.DUMMYFUNCTION("if(AND(K40=FALSE,L40=FALSE),,if(K40=L40,JOIN("""",""Static: "",K40),JOIN("""",""Min: "",K40, CHAR(10),""Max: "",L40)))"),"") | K40: {=_xlfn.XLOOKUP(B40,'Up Min'!A:A,'Up Min'!C:C,)} | L40: {=_xlfn.XLOOKUP(B40,'Up Max'!A:A,'Up Max'!C:C,)} | M40: {=_xlfn.XLOOKUP(B40,'Up Stats'!A:A,'Up Stats'!D:D,)} | N40: =IFERROR(__xludf.DUMMYFUNCTION("if(AND(O40=FALSE,P40=FALSE),,if(O40=P40,JOIN("""",""Static: "",O40),JOIN("""",""Min: "",O40, CHAR(10),""Max: "",P40)))"),"") | O40: {=_xlfn.XLOOKUP(B40,'Up Min'!A:A,'Up Min'!D:D,)} | P40: {=_xlfn.XLOOKUP(B40,'Up Max'!A:A,'Up Max'!D:D,)} | Q40: {=_xlfn.XLOOKUP(B40,'Up Stats'!A:A,'Up Stats'!E:E,)} | R40: =IFERROR(__xludf.DUMMYFUNCTION("if(AND(S40=FALSE,T40=FALSE),,if(S40=T40,JOIN("""",""Static: "",S40),JOIN("""",""Min: "",S40, CHAR(10),""Max: "",T40)))"),"") | S40: {=_xlfn.XLOOKUP(B40,'Up Min'!A:A,'Up Min'!E:E,)} | T40: {=_xlfn.XLOOKUP(B40,'Up Max'!A:A,'Up Max'!E:E,)} | U40: {=_xlfn.XLOOKUP(B40,'Up Stats'!A:A,'Up Stats'!F:F,)} | V40: =IFERROR(__xludf.DUMMYFUNCTION("if(AND(W40=FALSE,X40=FALSE),,if(W40=X40,JOIN("""",""Static: "",W40),JOIN("""",""Min: "",W40, CHAR(10),""Max: "",X40)))"),"") | W40: {=_xlfn.XLOOKUP(B40,'Up Min'!A:A,'Up Min'!F:F,)} | X40: {=_xlfn.XLOOKUP(B40,'Up Max'!A:A,'Up Max'!F:F,)} | Y40: {=_xlfn.XLOOKUP(B40,'Up Stats'!A:A,'Up Stats'!G:G,)} | Z40: =IFERROR(__xludf.DUMMYFUNCTION("if(AND(AA40=FALSE,AB40=FALSE),,if(AA40=AB40,JOIN("""",""Static: "",AA40),JOIN("""",""Min: "",AA40, CHAR(10),""Max: "",AB40)))"),"") | AA40: {=_xlfn.XLOOKUP(B40,'Up Min'!A:A,'Up Min'!G:G,)} | AB40: {=_xlfn.XLOOKUP(B40,'Up Max'!A:A,'Up Max'!G:G,)} | AC40: {=_xlfn.XLOOKUP(B40,'Up Stats'!A:A,'Up Stats'!H:H,)} | AD40: =IFERROR(__xludf.DUMMYFUNCTION("if(AND(AE40=FALSE,AF40=FALSE),,if(AE40=AF40,JOIN("""",""Static: "",AE40),JOIN("""",""Min: "",AE40, CHAR(10),""Max: "",AF40)))"),"") | AE40: {=_xlfn.XLOOKUP(B40,'Up Min'!A:A,'Up Min'!H:H,)} | AF40: {=_xlfn.XLOOKUP(B40,'Up Max'!A:A,'Up Max'!H:H,)} | AG40: {=_xlfn.XLOOKUP(B40,'Up Stats'!A:A,'Up Stats'!I:I,)} | AH40: =IFERROR(__xludf.DUMMYFUNCTION("if(AND(AI40=FALSE,AJ40=FALSE),,if(AI40=AJ40,JOIN("""",""Static: "",AI40),JOIN("""",""Min: "",AI40, CHAR(10),""Max: "",AJ40)))"),"") | AI40: {=_xlfn.XLOOKUP(B40,'Up Min'!A:A,'Up Min'!I:I,)} | AJ40: {=_xlfn.XLOOKUP(B40,'Up Max'!A:A,'Up Max'!I:I,)} | AK40: {=_xlfn.XLOOKUP(B40,'Up Stats'!A:A,'Up Stats'!J:J,)} | AL40: =IFERROR(__xludf.DUMMYFUNCTION("if(AND(AM40=FALSE,AN40=FALSE),,if(AM40=AN40,JOIN("""",""Static: "",AM40),JOIN("""",""Min: "",AM40, CHAR(10),""Max: "",AN40)))"),"") | AM40: {=_xlfn.XLOOKUP(B40,'Up Min'!A:A,'Up Min'!J:J,)} | AN40: {=_xlfn.XLOOKUP(B40,'Up Max'!A:A,'Up Max'!J:J,)} | AO40: {=CONCATENATE(_xlfn.XLOOKUP(B40,'Up Cells'!A:A,'Up Cells'!B:B,))} -> 3 | AP40: {=CONCATENATE(_xlfn.XLOOKUP(B40,'Up Rarity'!A:A,'Up Rarity'!B:B,),CHAR(10),"-")} -> Standard -
A41: {=_xlfn.XLOOKUP(B41,'Up Icon'!A:A,'Up Icon'!B:B,)} | B41: {=HYPERLINK(_xlfn.XLOOKUP('Up Names'!A41,'Up Wiki'!A:A,'Up Wiki'!B:B,),'Up Names'!A41)} | C41: {=_xlfn.XLOOKUP(B41,'Up Desc'!A:A,'Up Desc'!B:B,)} | D41: {=_xlfn.XLOOKUP(B41,'Up Turbo'!A:A,'Up Turbo'!B:B,)} | E41: {=_xlfn.XLOOKUP(B41,'Up Stats'!A:A,'Up Stats'!B:B,)} | F41: =IFERROR(__xludf.DUMMYFUNCTION("if(AND(G41=FALSE,H41=FALSE),,if(G41=H41,JOIN("""",""Static: "",G41),JOIN("""",""Min: "",G41, CHAR(10),""Max: "",H41)))"),"") | G41: {=_xlfn.XLOOKUP(B41,'Up Min'!A:A,'Up Min'!B:B,)} | H41: {=_xlfn.XLOOKUP(B41,'Up Max'!A:A,'Up Max'!B:B,)} | I41: {=_xlfn.XLOOKUP(B41,'Up Stats'!A:A,'Up Stats'!C:C,)} | J41: =IFERROR(__xludf.DUMMYFUNCTION("if(AND(K41=FALSE,L41=FALSE),,if(K41=L41,JOIN("""",""Static: "",K41),JOIN("""",""Min: "",K41, CHAR(10),""Max: "",L41)))"),"") | K41: {=_xlfn.XLOOKUP(B41,'Up Min'!A:A,'Up Min'!C:C,)} | L41: {=_xlfn.XLOOKUP(B41,'Up Max'!A:A,'Up Max'!C:C,)} | M41: {=_xlfn.XLOOKUP(B41,'Up Stats'!A:A,'Up Stats'!D:D,)} | N41: =IFERROR(__xludf.DUMMYFUNCTION("if(AND(O41=FALSE,P41=FALSE),,if(O41=P41,JOIN("""",""Static: "",O41),JOIN("""",""Min: "",O41, CHAR(10),""Max: "",P41)))"),"") | O41: {=_xlfn.XLOOKUP(B41,'Up Min'!A:A,'Up Min'!D:D,)} | P41: {=_xlfn.XLOOKUP(B41,'Up Max'!A:A,'Up Max'!D:D,)} | Q41: {=_xlfn.XLOOKUP(B41,'Up Stats'!A:A,'Up Stats'!E:E,)} | R41: =IFERROR(__xludf.DUMMYFUNCTION("if(AND(S41=FALSE,T41=FALSE),,if(S41=T41,JOIN("""",""Static: "",S41),JOIN("""",""Min: "",S41, CHAR(10),""Max: "",T41)))"),"") | S41: {=_xlfn.XLOOKUP(B41,'Up Min'!A:A,'Up Min'!E:E,)} | T41: {=_xlfn.XLOOKUP(B41,'Up Max'!A:A,'Up Max'!E:E,)} | U41: {=_xlfn.XLOOKUP(B41,'Up Stats'!A:A,'Up Stats'!F:F,)} | V41: =IFERROR(__xludf.DUMMYFUNCTION("if(AND(W41=FALSE,X41=FALSE),,if(W41=X41,JOIN("""",""Static: "",W41),JOIN("""",""Min: "",W41, CHAR(10),""Max: "",X41)))"),"") | W41: {=_xlfn.XLOOKUP(B41,'Up Min'!A:A,'Up Min'!F:F,)} | X41: {=_xlfn.XLOOKUP(B41,'Up Max'!A:A,'Up Max'!F:F,)} | Y41: {=_xlfn.XLOOKUP(B41,'Up Stats'!A:A,'Up Stats'!G:G,)} | Z41: =IFERROR(__xludf.DUMMYFUNCTION("if(AND(AA41=FALSE,AB41=FALSE),,if(AA41=AB41,JOIN("""",""Static: "",AA41),JOIN("""",""Min: "",AA41, CHAR(10),""Max: "",AB41)))"),"") | AA41: {=_xlfn.XLOOKUP(B41,'Up Min'!A:A,'Up Min'!G:G,)} | AB41: {=_xlfn.XLOOKUP(B41,'Up Max'!A:A,'Up Max'!G:G,)} | AC41: {=_xlfn.XLOOKUP(B41,'Up Stats'!A:A,'Up Stats'!H:H,)} | AD41: =IFERROR(__xludf.DUMMYFUNCTION("if(AND(AE41=FALSE,AF41=FALSE),,if(AE41=AF41,JOIN("""",""Static: "",AE41),JOIN("""",""Min: "",AE41, CHAR(10),""Max: "",AF41)))"),"") | AE41: {=_xlfn.XLOOKUP(B41,'Up Min'!A:A,'Up Min'!H:H,)} | AF41: {=_xlfn.XLOOKUP(B41,'Up Max'!A:A,'Up Max'!H:H,)} | AG41: {=_xlfn.XLOOKUP(B41,'Up Stats'!A:A,'Up Stats'!I:I,)} | AH41: =IFERROR(__xludf.DUMMYFUNCTION("if(AND(AI41=FALSE,AJ41=FALSE),,if(AI41=AJ41,JOIN("""",""Static: "",AI41),JOIN("""",""Min: "",AI41, CHAR(10),""Max: "",AJ41)))"),"") | AI41: {=_xlfn.XLOOKUP(B41,'Up Min'!A:A,'Up Min'!I:I,)} | AJ41: {=_xlfn.XLOOKUP(B41,'Up Max'!A:A,'Up Max'!I:I,)} | AK41: {=_xlfn.XLOOKUP(B41,'Up Stats'!A:A,'Up Stats'!J:J,)} | AL41: =IFERROR(__xludf.DUMMYFUNCTION("if(AND(AM41=FALSE,AN41=FALSE),,if(AM41=AN41,JOIN("""",""Static: "",AM41),JOIN("""",""Min: "",AM41, CHAR(10),""Max: "",AN41)))"),"") | AM41: {=_xlfn.XLOOKUP(B41,'Up Min'!A:A,'Up Min'!J:J,)} | AN41: {=_xlfn.XLOOKUP(B41,'Up Max'!A:A,'Up Max'!J:J,)} | AO41: {=CONCATENATE(_xlfn.XLOOKUP(B41,'Up Cells'!A:A,'Up Cells'!B:B,))} | AP41: {=CONCATENATE(_xlfn.XLOOKUP(B41,'Up Rarity'!A:A,'Up Rarity'!B:B,),CHAR(10),"-")} -> -
A42: {=_xlfn.XLOOKUP(B42,'Up Icon'!A:A,'Up Icon'!B:B,)} | B42: {=HYPERLINK(_xlfn.XLOOKUP('Up Names'!A42,'Up Wiki'!A:A,'Up Wiki'!B:B,),'Up Names'!A42)} | C42: {=_xlfn.XLOOKUP(B42,'Up Desc'!A:A,'Up Desc'!B:B,)} | D42: {=_xlfn.XLOOKUP(B42,'Up Turbo'!A:A,'Up Turbo'!B:B,)} | E42: {=_xlfn.XLOOKUP(B42,'Up Stats'!A:A,'Up Stats'!B:B,)} | F42: =IFERROR(__xludf.DUMMYFUNCTION("if(AND(G42=FALSE,H42=FALSE),,if(G42=H42,JOIN("""",""Static: "",G42),JOIN("""",""Min: "",G42, CHAR(10),""Max: "",H42)))"),"") | G42: {=_xlfn.XLOOKUP(B42,'Up Min'!A:A,'Up Min'!B:B,)} | H42: {=_xlfn.XLOOKUP(B42,'Up Max'!A:A,'Up Max'!B:B,)} | I42: {=_xlfn.XLOOKUP(B42,'Up Stats'!A:A,'Up Stats'!C:C,)} | J42: =IFERROR(__xludf.DUMMYFUNCTION("if(AND(K42=FALSE,L42=FALSE),,if(K42=L42,JOIN("""",""Static: "",K42),JOIN("""",""Min: "",K42, CHAR(10),""Max: "",L42)))"),"") | K42: {=_xlfn.XLOOKUP(B42,'Up Min'!A:A,'Up Min'!C:C,)} | L42: {=_xlfn.XLOOKUP(B42,'Up Max'!A:A,'Up Max'!C:C,)} | M42: {=_xlfn.XLOOKUP(B42,'Up Stats'!A:A,'Up Stats'!D:D,)} | N42: =IFERROR(__xludf.DUMMYFUNCTION("if(AND(O42=FALSE,P42=FALSE),,if(O42=P42,JOIN("""",""Static: "",O42),JOIN("""",""Min: "",O42, CHAR(10),""Max: "",P42)))"),"") | O42: {=_xlfn.XLOOKUP(B42,'Up Min'!A:A,'Up Min'!D:D,)} | P42: {=_xlfn.XLOOKUP(B42,'Up Max'!A:A,'Up Max'!D:D,)} | Q42: {=_xlfn.XLOOKUP(B42,'Up Stats'!A:A,'Up Stats'!E:E,)} | R42: =IFERROR(__xludf.DUMMYFUNCTION("if(AND(S42=FALSE,T42=FALSE),,if(S42=T42,JOIN("""",""Static: "",S42),JOIN("""",""Min: "",S42, CHAR(10),""Max: "",T42)))"),"") | S42: {=_xlfn.XLOOKUP(B42,'Up Min'!A:A,'Up Min'!E:E,)} | T42: {=_xlfn.XLOOKUP(B42,'Up Max'!A:A,'Up Max'!E:E,)} | U42: {=_xlfn.XLOOKUP(B42,'Up Stats'!A:A,'Up Stats'!F:F,)} | V42: =IFERROR(__xludf.DUMMYFUNCTION("if(AND(W42=FALSE,X42=FALSE),,if(W42=X42,JOIN("""",""Static: "",W42),JOIN("""",""Min: "",W42, CHAR(10),""Max: "",X42)))"),"") | W42: {=_xlfn.XLOOKUP(B42,'Up Min'!A:A,'Up Min'!F:F,)} | X42: {=_xlfn.XLOOKUP(B42,'Up Max'!A:A,'Up Max'!F:F,)} | Y42: {=_xlfn.XLOOKUP(B42,'Up Stats'!A:A,'Up Stats'!G:G,)} | Z42: =IFERROR(__xludf.DUMMYFUNCTION("if(AND(AA42=FALSE,AB42=FALSE),,if(AA42=AB42,JOIN("""",""Static: "",AA42),JOIN("""",""Min: "",AA42, CHAR(10),""Max: "",AB42)))"),"") | AA42: {=_xlfn.XLOOKUP(B42,'Up Min'!A:A,'Up Min'!G:G,)} | AB42: {=_xlfn.XLOOKUP(B42,'Up Max'!A:A,'Up Max'!G:G,)} | AC42: {=_xlfn.XLOOKUP(B42,'Up Stats'!A:A,'Up Stats'!H:H,)} | AD42: =IFERROR(__xludf.DUMMYFUNCTION("if(AND(AE42=FALSE,AF42=FALSE),,if(AE42=AF42,JOIN("""",""Static: "",AE42),JOIN("""",""Min: "",AE42, CHAR(10),""Max: "",AF42)))"),"") | AE42: {=_xlfn.XLOOKUP(B42,'Up Min'!A:A,'Up Min'!H:H,)} | AF42: {=_xlfn.XLOOKUP(B42,'Up Max'!A:A,'Up Max'!H:H,)} | AG42: {=_xlfn.XLOOKUP(B42,'Up Stats'!A:A,'Up Stats'!I:I,)} | AH42: =IFERROR(__xludf.DUMMYFUNCTION("if(AND(AI42=FALSE,AJ42=FALSE),,if(AI42=AJ42,JOIN("""",""Static: "",AI42),JOIN("""",""Min: "",AI42, CHAR(10),""Max: "",AJ42)))"),"") | AI42: {=_xlfn.XLOOKUP(B42,'Up Min'!A:A,'Up Min'!I:I,)} | AJ42: {=_xlfn.XLOOKUP(B42,'Up Max'!A:A,'Up Max'!I:I,)} | AK42: {=_xlfn.XLOOKUP(B42,'Up Stats'!A:A,'Up Stats'!J:J,)} | AL42: =IFERROR(__xludf.DUMMYFUNCTION("if(AND(AM42=FALSE,AN42=FALSE),,if(AM42=AN42,JOIN("""",""Static: "",AM42),JOIN("""",""Min: "",AM42, CHAR(10),""Max: "",AN42)))"),"") | AM42: {=_xlfn.XLOOKUP(B42,'Up Min'!A:A,'Up Min'!J:J,)} | AN42: {=_xlfn.XLOOKUP(B42,'Up Max'!A:A,'Up Max'!J:J,)} | AO42: {=CONCATENATE(_xlfn.XLOOKUP(B42,'Up Cells'!A:A,'Up Cells'!B:B,))} | AP42: {=CONCATENATE(_xlfn.XLOOKUP(B42,'Up Rarity'!A:A,'Up Rarity'!B:B,),CHAR(10),"-")} -> -
A43: {=_xlfn.XLOOKUP(B43,'Up Icon'!A:A,'Up Icon'!B:B,)} | B43: {=HYPERLINK(_xlfn.XLOOKUP('Up Names'!A43,'Up Wiki'!A:A,'Up Wiki'!B:B,),'Up Names'!A43)} | C43: {=_xlfn.XLOOKUP(B43,'Up Desc'!A:A,'Up Desc'!B:B,)} | D43: {=_xlfn.XLOOKUP(B43,'Up Turbo'!A:A,'Up Turbo'!B:B,)} | E43: {=_xlfn.XLOOKUP(B43,'Up Stats'!A:A,'Up Stats'!B:B,)} | F43: =IFERROR(__xludf.DUMMYFUNCTION("if(AND(G43=FALSE,H43=FALSE),,if(G43=H43,JOIN("""",""Static: "",G43),JOIN("""",""Min: "",G43, CHAR(10),""Max: "",H43)))"),"") | G43: {=_xlfn.XLOOKUP(B43,'Up Min'!A:A,'Up Min'!B:B,)} | H43: {=_xlfn.XLOOKUP(B43,'Up Max'!A:A,'Up Max'!B:B,)} | I43: {=_xlfn.XLOOKUP(B43,'Up Stats'!A:A,'Up Stats'!C:C,)} | J43: =IFERROR(__xludf.DUMMYFUNCTION("if(AND(K43=FALSE,L43=FALSE),,if(K43=L43,JOIN("""",""Static: "",K43),JOIN("""",""Min: "",K43, CHAR(10),""Max: "",L43)))"),"") | K43: {=_xlfn.XLOOKUP(B43,'Up Min'!A:A,'Up Min'!C:C,)} | L43: {=_xlfn.XLOOKUP(B43,'Up Max'!A:A,'Up Max'!C:C,)} | M43: {=_xlfn.XLOOKUP(B43,'Up Stats'!A:A,'Up Stats'!D:D,)} | N43: =IFERROR(__xludf.DUMMYFUNCTION("if(AND(O43=FALSE,P43=FALSE),,if(O43=P43,JOIN("""",""Static: "",O43),JOIN("""",""Min: "",O43, CHAR(10),""Max: "",P43)))"),"") | O43: {=_xlfn.XLOOKUP(B43,'Up Min'!A:A,'Up Min'!D:D,)} | P43: {=_xlfn.XLOOKUP(B43,'Up Max'!A:A,'Up Max'!D:D,)} | Q43: {=_xlfn.XLOOKUP(B43,'Up Stats'!A:A,'Up Stats'!E:E,)} | R43: =IFERROR(__xludf.DUMMYFUNCTION("if(AND(S43=FALSE,T43=FALSE),,if(S43=T43,JOIN("""",""Static: "",S43),JOIN("""",""Min: "",S43, CHAR(10),""Max: "",T43)))"),"") | S43: {=_xlfn.XLOOKUP(B43,'Up Min'!A:A,'Up Min'!E:E,)} | T43: {=_xlfn.XLOOKUP(B43,'Up Max'!A:A,'Up Max'!E:E,)} | U43: {=_xlfn.XLOOKUP(B43,'Up Stats'!A:A,'Up Stats'!F:F,)} | V43: =IFERROR(__xludf.DUMMYFUNCTION("if(AND(W43=FALSE,X43=FALSE),,if(W43=X43,JOIN("""",""Static: "",W43),JOIN("""",""Min: "",W43, CHAR(10),""Max: "",X43)))"),"") | W43: {=_xlfn.XLOOKUP(B43,'Up Min'!A:A,'Up Min'!F:F,)} | X43: {=_xlfn.XLOOKUP(B43,'Up Max'!A:A,'Up Max'!F:F,)} | Y43: {=_xlfn.XLOOKUP(B43,'Up Stats'!A:A,'Up Stats'!G:G,)} | Z43: =IFERROR(__xludf.DUMMYFUNCTION("if(AND(AA43=FALSE,AB43=FALSE),,if(AA43=AB43,JOIN("""",""Static: "",AA43),JOIN("""",""Min: "",AA43, CHAR(10),""Max: "",AB43)))"),"") | AA43: {=_xlfn.XLOOKUP(B43,'Up Min'!A:A,'Up Min'!G:G,)} | AB43: {=_xlfn.XLOOKUP(B43,'Up Max'!A:A,'Up Max'!G:G,)} | AC43: {=_xlfn.XLOOKUP(B43,'Up Stats'!A:A,'Up Stats'!H:H,)} | AD43: =IFERROR(__xludf.DUMMYFUNCTION("if(AND(AE43=FALSE,AF43=FALSE),,if(AE43=AF43,JOIN("""",""Static: "",AE43),JOIN("""",""Min: "",AE43, CHAR(10),""Max: "",AF43)))"),"") | AE43: {=_xlfn.XLOOKUP(B43,'Up Min'!A:A,'Up Min'!H:H,)} | AF43: {=_xlfn.XLOOKUP(B43,'Up Max'!A:A,'Up Max'!H:H,)} | AG43: {=_xlfn.XLOOKUP(B43,'Up Stats'!A:A,'Up Stats'!I:I,)} | AH43: =IFERROR(__xludf.DUMMYFUNCTION("if(AND(AI43=FALSE,AJ43=FALSE),,if(AI43=AJ43,JOIN("""",""Static: "",AI43),JOIN("""",""Min: "",AI43, CHAR(10),""Max: "",AJ43)))"),"") | AI43: {=_xlfn.XLOOKUP(B43,'Up Min'!A:A,'Up Min'!I:I,)} | AJ43: {=_xlfn.XLOOKUP(B43,'Up Max'!A:A,'Up Max'!I:I,)} | AK43: {=_xlfn.XLOOKUP(B43,'Up Stats'!A:A,'Up Stats'!J:J,)} | AL43: =IFERROR(__xludf.DUMMYFUNCTION("if(AND(AM43=FALSE,AN43=FALSE),,if(AM43=AN43,JOIN("""",""Static: "",AM43),JOIN("""",""Min: "",AM43, CHAR(10),""Max: "",AN43)))"),"") | AM43: {=_xlfn.XLOOKUP(B43,'Up Min'!A:A,'Up Min'!J:J,)} | AN43: {=_xlfn.XLOOKUP(B43,'Up Max'!A:A,'Up Max'!J:J,)} | AO43: {=CONCATENATE(_xlfn.XLOOKUP(B43,'Up Cells'!A:A,'Up Cells'!B:B,))} | AP43: {=CONCATENATE(_xlfn.XLOOKUP(B43,'Up Rarity'!A:A,'Up Rarity'!B:B,),CHAR(10),"-")} -> -
A44: {=_xlfn.XLOOKUP(B44,'Up Icon'!A:A,'Up Icon'!B:B,)} | B44: {=HYPERLINK(_xlfn.XLOOKUP('Up Names'!A44,'Up Wiki'!A:A,'Up Wiki'!B:B,),'Up Names'!A44)} | C44: {=_xlfn.XLOOKUP(B44,'Up Desc'!A:A,'Up Desc'!B:B,)} | D44: {=_xlfn.XLOOKUP(B44,'Up Turbo'!A:A,'Up Turbo'!B:B,)} | E44: {=_xlfn.XLOOKUP(B44,'Up Stats'!A:A,'Up Stats'!B:B,)} | F44: =IFERROR(__xludf.DUMMYFUNCTION("if(AND(G44=FALSE,H44=FALSE),,if(G44=H44,JOIN("""",""Static: "",G44),JOIN("""",""Min: "",G44, CHAR(10),""Max: "",H44)))"),"") | G44: {=_xlfn.XLOOKUP(B44,'Up Min'!A:A,'Up Min'!B:B,)} | H44: {=_xlfn.XLOOKUP(B44,'Up Max'!A:A,'Up Max'!B:B,)} | I44: {=_xlfn.XLOOKUP(B44,'Up Stats'!A:A,'Up Stats'!C:C,)} | J44: =IFERROR(__xludf.DUMMYFUNCTION("if(AND(K44=FALSE,L44=FALSE),,if(K44=L44,JOIN("""",""Static: "",K44),JOIN("""",""Min: "",K44, CHAR(10),""Max: "",L44)))"),"") | K44: {=_xlfn.XLOOKUP(B44,'Up Min'!A:A,'Up Min'!C:C,)} | L44: {=_xlfn.XLOOKUP(B44,'Up Max'!A:A,'Up Max'!C:C,)} | M44: {=_xlfn.XLOOKUP(B44,'Up Stats'!A:A,'Up Stats'!D:D,)} | N44: =IFERROR(__xludf.DUMMYFUNCTION("if(AND(O44=FALSE,P44=FALSE),,if(O44=P44,JOIN("""",""Static: "",O44),JOIN("""",""Min: "",O44, CHAR(10),""Max: "",P44)))"),"") | O44: {=_xlfn.XLOOKUP(B44,'Up Min'!A:A,'Up Min'!D:D,)} | P44: {=_xlfn.XLOOKUP(B44,'Up Max'!A:A,'Up Max'!D:D,)} | Q44: {=_xlfn.XLOOKUP(B44,'Up Stats'!A:A,'Up Stats'!E:E,)} | R44: =IFERROR(__xludf.DUMMYFUNCTION("if(AND(S44=FALSE,T44=FALSE),,if(S44=T44,JOIN("""",""Static: "",S44),JOIN("""",""Min: "",S44, CHAR(10),""Max: "",T44)))"),"") | S44: {=_xlfn.XLOOKUP(B44,'Up Min'!A:A,'Up Min'!E:E,)} | T44: {=_xlfn.XLOOKUP(B44,'Up Max'!A:A,'Up Max'!E:E,)} | U44: {=_xlfn.XLOOKUP(B44,'Up Stats'!A:A,'Up Stats'!F:F,)} | V44: =IFERROR(__xludf.DUMMYFUNCTION("if(AND(W44=FALSE,X44=FALSE),,if(W44=X44,JOIN("""",""Static: "",W44),JOIN("""",""Min: "",W44, CHAR(10),""Max: "",X44)))"),"") | W44: {=_xlfn.XLOOKUP(B44,'Up Min'!A:A,'Up Min'!F:F,)} | X44: {=_xlfn.XLOOKUP(B44,'Up Max'!A:A,'Up Max'!F:F,)} | Y44: {=_xlfn.XLOOKUP(B44,'Up Stats'!A:A,'Up Stats'!G:G,)} | Z44: =IFERROR(__xludf.DUMMYFUNCTION("if(AND(AA44=FALSE,AB44=FALSE),,if(AA44=AB44,JOIN("""",""Static: "",AA44),JOIN("""",""Min: "",AA44, CHAR(10),""Max: "",AB44)))"),"") | AA44: {=_xlfn.XLOOKUP(B44,'Up Min'!A:A,'Up Min'!G:G,)} | AB44: {=_xlfn.XLOOKUP(B44,'Up Max'!A:A,'Up Max'!G:G,)} | AC44: {=_xlfn.XLOOKUP(B44,'Up Stats'!A:A,'Up Stats'!H:H,)} | AD44: =IFERROR(__xludf.DUMMYFUNCTION("if(AND(AE44=FALSE,AF44=FALSE),,if(AE44=AF44,JOIN("""",""Static: "",AE44),JOIN("""",""Min: "",AE44, CHAR(10),""Max: "",AF44)))"),"") | AE44: {=_xlfn.XLOOKUP(B44,'Up Min'!A:A,'Up Min'!H:H,)} | AF44: {=_xlfn.XLOOKUP(B44,'Up Max'!A:A,'Up Max'!H:H,)} | AG44: {=_xlfn.XLOOKUP(B44,'Up Stats'!A:A,'Up Stats'!I:I,)} | AH44: =IFERROR(__xludf.DUMMYFUNCTION("if(AND(AI44=FALSE,AJ44=FALSE),,if(AI44=AJ44,JOIN("""",""Static: "",AI44),JOIN("""",""Min: "",AI44, CHAR(10),""Max: "",AJ44)))"),"") | AI44: {=_xlfn.XLOOKUP(B44,'Up Min'!A:A,'Up Min'!I:I,)} | AJ44: {=_xlfn.XLOOKUP(B44,'Up Max'!A:A,'Up Max'!I:I,)} | AK44: {=_xlfn.XLOOKUP(B44,'Up Stats'!A:A,'Up Stats'!J:J,)} | AL44: =IFERROR(__xludf.DUMMYFUNCTION("if(AND(AM44=FALSE,AN44=FALSE),,if(AM44=AN44,JOIN("""",""Static: "",AM44),JOIN("""",""Min: "",AM44, CHAR(10),""Max: "",AN44)))"),"") | AM44: {=_xlfn.XLOOKUP(B44,'Up Min'!A:A,'Up Min'!J:J,)} | AN44: {=_xlfn.XLOOKUP(B44,'Up Max'!A:A,'Up Max'!J:J,)} | AO44: {=CONCATENATE(_xlfn.XLOOKUP(B44,'Up Cells'!A:A,'Up Cells'!B:B,))} | AP44: {=CONCATENATE(_xlfn.XLOOKUP(B44,'Up Rarity'!A:A,'Up Rarity'!B:B,),CHAR(10),"-")} -> -
A45: {=_xlfn.XLOOKUP(B45,'Up Icon'!A:A,'Up Icon'!B:B,)} | B45: {=HYPERLINK(_xlfn.XLOOKUP('Up Names'!A45,'Up Wiki'!A:A,'Up Wiki'!B:B,),'Up Names'!A45)} | C45: {=_xlfn.XLOOKUP(B45,'Up Desc'!A:A,'Up Desc'!B:B,)} | D45: {=_xlfn.XLOOKUP(B45,'Up Turbo'!A:A,'Up Turbo'!B:B,)} | E45: {=_xlfn.XLOOKUP(B45,'Up Stats'!A:A,'Up Stats'!B:B,)} | F45: =IFERROR(__xludf.DUMMYFUNCTION("if(AND(G45=FALSE,H45=FALSE),,if(G45=H45,JOIN("""",""Static: "",G45),JOIN("""",""Min: "",G45, CHAR(10),""Max: "",H45)))"),"") | G45: {=_xlfn.XLOOKUP(B45,'Up Min'!A:A,'Up Min'!B:B,)} | H45: {=_xlfn.XLOOKUP(B45,'Up Max'!A:A,'Up Max'!B:B,)} | I45: {=_xlfn.XLOOKUP(B45,'Up Stats'!A:A,'Up Stats'!C:C,)} | J45: =IFERROR(__xludf.DUMMYFUNCTION("if(AND(K45=FALSE,L45=FALSE),,if(K45=L45,JOIN("""",""Static: "",K45),JOIN("""",""Min: "",K45, CHAR(10),""Max: "",L45)))"),"") | K45: {=_xlfn.XLOOKUP(B45,'Up Min'!A:A,'Up Min'!C:C,)} | L45: {=_xlfn.XLOOKUP(B45,'Up Max'!A:A,'Up Max'!C:C,)} | M45: {=_xlfn.XLOOKUP(B45,'Up Stats'!A:A,'Up Stats'!D:D,)} | N45: =IFERROR(__xludf.DUMMYFUNCTION("if(AND(O45=FALSE,P45=FALSE),,if(O45=P45,JOIN("""",""Static: "",O45),JOIN("""",""Min: "",O45, CHAR(10),""Max: "",P45)))"),"") | O45: {=_xlfn.XLOOKUP(B45,'Up Min'!A:A,'Up Min'!D:D,)} | P45: {=_xlfn.XLOOKUP(B45,'Up Max'!A:A,'Up Max'!D:D,)} | Q45: {=_xlfn.XLOOKUP(B45,'Up Stats'!A:A,'Up Stats'!E:E,)} | R45: =IFERROR(__xludf.DUMMYFUNCTION("if(AND(S45=FALSE,T45=FALSE),,if(S45=T45,JOIN("""",""Static: "",S45),JOIN("""",""Min: "",S45, CHAR(10),""Max: "",T45)))"),"") | S45: {=_xlfn.XLOOKUP(B45,'Up Min'!A:A,'Up Min'!E:E,)} | T45: {=_xlfn.XLOOKUP(B45,'Up Max'!A:A,'Up Max'!E:E,)} | U45: {=_xlfn.XLOOKUP(B45,'Up Stats'!A:A,'Up Stats'!F:F,)} | V45: =IFERROR(__xludf.DUMMYFUNCTION("if(AND(W45=FALSE,X45=FALSE),,if(W45=X45,JOIN("""",""Static: "",W45),JOIN("""",""Min: "",W45, CHAR(10),""Max: "",X45)))"),"") | W45: {=_xlfn.XLOOKUP(B45,'Up Min'!A:A,'Up Min'!F:F,)} | X45: {=_xlfn.XLOOKUP(B45,'Up Max'!A:A,'Up Max'!F:F,)} | Y45: {=_xlfn.XLOOKUP(B45,'Up Stats'!A:A,'Up Stats'!G:G,)} | Z45: =IFERROR(__xludf.DUMMYFUNCTION("if(AND(AA45=FALSE,AB45=FALSE),,if(AA45=AB45,JOIN("""",""Static: "",AA45),JOIN("""",""Min: "",AA45, CHAR(10),""Max: "",AB45)))"),"") | AA45: {=_xlfn.XLOOKUP(B45,'Up Min'!A:A,'Up Min'!G:G,)} | AB45: {=_xlfn.XLOOKUP(B45,'Up Max'!A:A,'Up Max'!G:G,)} | AC45: {=_xlfn.XLOOKUP(B45,'Up Stats'!A:A,'Up Stats'!H:H,)} | AD45: =IFERROR(__xludf.DUMMYFUNCTION("if(AND(AE45=FALSE,AF45=FALSE),,if(AE45=AF45,JOIN("""",""Static: "",AE45),JOIN("""",""Min: "",AE45, CHAR(10),""Max: "",AF45)))"),"") | AE45: {=_xlfn.XLOOKUP(B45,'Up Min'!A:A,'Up Min'!H:H,)} | AF45: {=_xlfn.XLOOKUP(B45,'Up Max'!A:A,'Up Max'!H:H,)} | AG45: {=_xlfn.XLOOKUP(B45,'Up Stats'!A:A,'Up Stats'!I:I,)} | AH45: =IFERROR(__xludf.DUMMYFUNCTION("if(AND(AI45=FALSE,AJ45=FALSE),,if(AI45=AJ45,JOIN("""",""Static: "",AI45),JOIN("""",""Min: "",AI45, CHAR(10),""Max: "",AJ45)))"),"") | AI45: {=_xlfn.XLOOKUP(B45,'Up Min'!A:A,'Up Min'!I:I,)} | AJ45: {=_xlfn.XLOOKUP(B45,'Up Max'!A:A,'Up Max'!I:I,)} | AK45: {=_xlfn.XLOOKUP(B45,'Up Stats'!A:A,'Up Stats'!J:J,)} | AL45: =IFERROR(__xludf.DUMMYFUNCTION("if(AND(AM45=FALSE,AN45=FALSE),,if(AM45=AN45,JOIN("""",""Static: "",AM45),JOIN("""",""Min: "",AM45, CHAR(10),""Max: "",AN45)))"),"") | AM45: {=_xlfn.XLOOKUP(B45,'Up Min'!A:A,'Up Min'!J:J,)} | AN45: {=_xlfn.XLOOKUP(B45,'Up Max'!A:A,'Up Max'!J:J,)} | AO45: {=CONCATENATE(_xlfn.XLOOKUP(B45,'Up Cells'!A:A,'Up Cells'!B:B,))} | AP45: {=CONCATENATE(_xlfn.XLOOKUP(B45,'Up Rarity'!A:A,'Up Rarity'!B:B,),CHAR(10),"-")} -> -
A46: {=_xlfn.XLOOKUP(B46,'Up Icon'!A:A,'Up Icon'!B:B,)} | B46: {=HYPERLINK(_xlfn.XLOOKUP('Up Names'!A46,'Up Wiki'!A:A,'Up Wiki'!B:B,),'Up Names'!A46)} | C46: {=_xlfn.XLOOKUP(B46,'Up Desc'!A:A,'Up Desc'!B:B,)} | D46: {=_xlfn.XLOOKUP(B46,'Up Turbo'!A:A,'Up Turbo'!B:B,)} | E46: {=_xlfn.XLOOKUP(B46,'Up Stats'!A:A,'Up Stats'!B:B,)} | F46: =IFERROR(__xludf.DUMMYFUNCTION("if(AND(G46=FALSE,H46=FALSE),,if(G46=H46,JOIN("""",""Static: "",G46),JOIN("""",""Min: "",G46, CHAR(10),""Max: "",H46)))"),"") | G46: {=_xlfn.XLOOKUP(B46,'Up Min'!A:A,'Up Min'!B:B,)} | H46: {=_xlfn.XLOOKUP(B46,'Up Max'!A:A,'Up Max'!B:B,)} | I46: {=_xlfn.XLOOKUP(B46,'Up Stats'!A:A,'Up Stats'!C:C,)} | J46: =IFERROR(__xludf.DUMMYFUNCTION("if(AND(K46=FALSE,L46=FALSE),,if(K46=L46,JOIN("""",""Static: "",K46),JOIN("""",""Min: "",K46, CHAR(10),""Max: "",L46)))"),"") | K46: {=_xlfn.XLOOKUP(B46,'Up Min'!A:A,'Up Min'!C:C,)} | L46: {=_xlfn.XLOOKUP(B46,'Up Max'!A:A,'Up Max'!C:C,)} | M46: {=_xlfn.XLOOKUP(B46,'Up Stats'!A:A,'Up Stats'!D:D,)} | N46: =IFERROR(__xludf.DUMMYFUNCTION("if(AND(O46=FALSE,P46=FALSE),,if(O46=P46,JOIN("""",""Static: "",O46),JOIN("""",""Min: "",O46, CHAR(10),""Max: "",P46)))"),"") | O46: {=_xlfn.XLOOKUP(B46,'Up Min'!A:A,'Up Min'!D:D,)} | P46: {=_xlfn.XLOOKUP(B46,'Up Max'!A:A,'Up Max'!D:D,)} | Q46: {=_xlfn.XLOOKUP(B46,'Up Stats'!A:A,'Up Stats'!E:E,)} | R46: =IFERROR(__xludf.DUMMYFUNCTION("if(AND(S46=FALSE,T46=FALSE),,if(S46=T46,JOIN("""",""Static: "",S46),JOIN("""",""Min: "",S46, CHAR(10),""Max: "",T46)))"),"") | S46: {=_xlfn.XLOOKUP(B46,'Up Min'!A:A,'Up Min'!E:E,)} | T46: {=_xlfn.XLOOKUP(B46,'Up Max'!A:A,'Up Max'!E:E,)} | U46: {=_xlfn.XLOOKUP(B46,'Up Stats'!A:A,'Up Stats'!F:F,)} | V46: =IFERROR(__xludf.DUMMYFUNCTION("if(AND(W46=FALSE,X46=FALSE),,if(W46=X46,JOIN("""",""Static: "",W46),JOIN("""",""Min: "",W46, CHAR(10),""Max: "",X46)))"),"") | W46: {=_xlfn.XLOOKUP(B46,'Up Min'!A:A,'Up Min'!F:F,)} | X46: {=_xlfn.XLOOKUP(B46,'Up Max'!A:A,'Up Max'!F:F,)} | Y46: {=_xlfn.XLOOKUP(B46,'Up Stats'!A:A,'Up Stats'!G:G,)} | Z46: =IFERROR(__xludf.DUMMYFUNCTION("if(AND(AA46=FALSE,AB46=FALSE),,if(AA46=AB46,JOIN("""",""Static: "",AA46),JOIN("""",""Min: "",AA46, CHAR(10),""Max: "",AB46)))"),"") | AA46: {=_xlfn.XLOOKUP(B46,'Up Min'!A:A,'Up Min'!G:G,)} | AB46: {=_xlfn.XLOOKUP(B46,'Up Max'!A:A,'Up Max'!G:G,)} | AC46: {=_xlfn.XLOOKUP(B46,'Up Stats'!A:A,'Up Stats'!H:H,)} | AD46: =IFERROR(__xludf.DUMMYFUNCTION("if(AND(AE46=FALSE,AF46=FALSE),,if(AE46=AF46,JOIN("""",""Static: "",AE46),JOIN("""",""Min: "",AE46, CHAR(10),""Max: "",AF46)))"),"") | AE46: {=_xlfn.XLOOKUP(B46,'Up Min'!A:A,'Up Min'!H:H,)} | AF46: {=_xlfn.XLOOKUP(B46,'Up Max'!A:A,'Up Max'!H:H,)} | AG46: {=_xlfn.XLOOKUP(B46,'Up Stats'!A:A,'Up Stats'!I:I,)} | AH46: =IFERROR(__xludf.DUMMYFUNCTION("if(AND(AI46=FALSE,AJ46=FALSE),,if(AI46=AJ46,JOIN("""",""Static: "",AI46),JOIN("""",""Min: "",AI46, CHAR(10),""Max: "",AJ46)))"),"") | AI46: {=_xlfn.XLOOKUP(B46,'Up Min'!A:A,'Up Min'!I:I,)} | AJ46: {=_xlfn.XLOOKUP(B46,'Up Max'!A:A,'Up Max'!I:I,)} | AK46: {=_xlfn.XLOOKUP(B46,'Up Stats'!A:A,'Up Stats'!J:J,)} | AL46: =IFERROR(__xludf.DUMMYFUNCTION("if(AND(AM46=FALSE,AN46=FALSE),,if(AM46=AN46,JOIN("""",""Static: "",AM46),JOIN("""",""Min: "",AM46, CHAR(10),""Max: "",AN46)))"),"") | AM46: {=_xlfn.XLOOKUP(B46,'Up Min'!A:A,'Up Min'!J:J,)} | AN46: {=_xlfn.XLOOKUP(B46,'Up Max'!A:A,'Up Max'!J:J,)} | AO46: {=CONCATENATE(_xlfn.XLOOKUP(B46,'Up Cells'!A:A,'Up Cells'!B:B,))} | AP46: {=CONCATENATE(_xlfn.XLOOKUP(B46,'Up Rarity'!A:A,'Up Rarity'!B:B,),CHAR(10),"-")} -> -
A47: {=_xlfn.XLOOKUP(B47,'Up Icon'!A:A,'Up Icon'!B:B,)} | B47: {=HYPERLINK(_xlfn.XLOOKUP('Up Names'!A47,'Up Wiki'!A:A,'Up Wiki'!B:B,),'Up Names'!A47)} | C47: {=_xlfn.XLOOKUP(B47,'Up Desc'!A:A,'Up Desc'!B:B,)} | D47: {=_xlfn.XLOOKUP(B47,'Up Turbo'!A:A,'Up Turbo'!B:B,)} | E47: {=_xlfn.XLOOKUP(B47,'Up Stats'!A:A,'Up Stats'!B:B,)} | F47: =IFERROR(__xludf.DUMMYFUNCTION("if(AND(G47=FALSE,H47=FALSE),,if(G47=H47,JOIN("""",""Static: "",G47),JOIN("""",""Min: "",G47, CHAR(10),""Max: "",H47)))"),"") | G47: {=_xlfn.XLOOKUP(B47,'Up Min'!A:A,'Up Min'!B:B,)} | H47: {=_xlfn.XLOOKUP(B47,'Up Max'!A:A,'Up Max'!B:B,)} | I47: {=_xlfn.XLOOKUP(B47,'Up Stats'!A:A,'Up Stats'!C:C,)} | J47: =IFERROR(__xludf.DUMMYFUNCTION("if(AND(K47=FALSE,L47=FALSE),,if(K47=L47,JOIN("""",""Static: "",K47),JOIN("""",""Min: "",K47, CHAR(10),""Max: "",L47)))"),"") | K47: {=_xlfn.XLOOKUP(B47,'Up Min'!A:A,'Up Min'!C:C,)} | L47: {=_xlfn.XLOOKUP(B47,'Up Max'!A:A,'Up Max'!C:C,)} | M47: {=_xlfn.XLOOKUP(B47,'Up Stats'!A:A,'Up Stats'!D:D,)} | N47: =IFERROR(__xludf.DUMMYFUNCTION("if(AND(O47=FALSE,P47=FALSE),,if(O47=P47,JOIN("""",""Static: "",O47),JOIN("""",""Min: "",O47, CHAR(10),""Max: "",P47)))"),"") | O47: {=_xlfn.XLOOKUP(B47,'Up Min'!A:A,'Up Min'!D:D,)} | P47: {=_xlfn.XLOOKUP(B47,'Up Max'!A:A,'Up Max'!D:D,)} | Q47: {=_xlfn.XLOOKUP(B47,'Up Stats'!A:A,'Up Stats'!E:E,)} | R47: =IFERROR(__xludf.DUMMYFUNCTION("if(AND(S47=FALSE,T47=FALSE),,if(S47=T47,JOIN("""",""Static: "",S47),JOIN("""",""Min: "",S47, CHAR(10),""Max: "",T47)))"),"") | S47: {=_xlfn.XLOOKUP(B47,'Up Min'!A:A,'Up Min'!E:E,)} | T47: {=_xlfn.XLOOKUP(B47,'Up Max'!A:A,'Up Max'!E:E,)} | U47: {=_xlfn.XLOOKUP(B47,'Up Stats'!A:A,'Up Stats'!F:F,)} | V47: =IFERROR(__xludf.DUMMYFUNCTION("if(AND(W47=FALSE,X47=FALSE),,if(W47=X47,JOIN("""",""Static: "",W47),JOIN("""",""Min: "",W47, CHAR(10),""Max: "",X47)))"),"") | W47: {=_xlfn.XLOOKUP(B47,'Up Min'!A:A,'Up Min'!F:F,)} | X47: {=_xlfn.XLOOKUP(B47,'Up Max'!A:A,'Up Max'!F:F,)} | Y47: {=_xlfn.XLOOKUP(B47,'Up Stats'!A:A,'Up Stats'!G:G,)} | Z47: =IFERROR(__xludf.DUMMYFUNCTION("if(AND(AA47=FALSE,AB47=FALSE),,if(AA47=AB47,JOIN("""",""Static: "",AA47),JOIN("""",""Min: "",AA47, CHAR(10),""Max: "",AB47)))"),"") | AA47: {=_xlfn.XLOOKUP(B47,'Up Min'!A:A,'Up Min'!G:G,)} | AB47: {=_xlfn.XLOOKUP(B47,'Up Max'!A:A,'Up Max'!G:G,)} | AC47: {=_xlfn.XLOOKUP(B47,'Up Stats'!A:A,'Up Stats'!H:H,)} | AD47: =IFERROR(__xludf.DUMMYFUNCTION("if(AND(AE47=FALSE,AF47=FALSE),,if(AE47=AF47,JOIN("""",""Static: "",AE47),JOIN("""",""Min: "",AE47, CHAR(10),""Max: "",AF47)))"),"") | AE47: {=_xlfn.XLOOKUP(B47,'Up Min'!A:A,'Up Min'!H:H,)} | AF47: {=_xlfn.XLOOKUP(B47,'Up Max'!A:A,'Up Max'!H:H,)} | AG47: {=_xlfn.XLOOKUP(B47,'Up Stats'!A:A,'Up Stats'!I:I,)} | AH47: =IFERROR(__xludf.DUMMYFUNCTION("if(AND(AI47=FALSE,AJ47=FALSE),,if(AI47=AJ47,JOIN("""",""Static: "",AI47),JOIN("""",""Min: "",AI47, CHAR(10),""Max: "",AJ47)))"),"") | AI47: {=_xlfn.XLOOKUP(B47,'Up Min'!A:A,'Up Min'!I:I,)} | AJ47: {=_xlfn.XLOOKUP(B47,'Up Max'!A:A,'Up Max'!I:I,)} | AK47: {=_xlfn.XLOOKUP(B47,'Up Stats'!A:A,'Up Stats'!J:J,)} | AL47: =IFERROR(__xludf.DUMMYFUNCTION("if(AND(AM47=FALSE,AN47=FALSE),,if(AM47=AN47,JOIN("""",""Static: "",AM47),JOIN("""",""Min: "",AM47, CHAR(10),""Max: "",AN47)))"),"") | AM47: {=_xlfn.XLOOKUP(B47,'Up Min'!A:A,'Up Min'!J:J,)} | AN47: {=_xlfn.XLOOKUP(B47,'Up Max'!A:A,'Up Max'!J:J,)} | AO47: {=CONCATENATE(_xlfn.XLOOKUP(B47,'Up Cells'!A:A,'Up Cells'!B:B,))} | AP47: {=CONCATENATE(_xlfn.XLOOKUP(B47,'Up Rarity'!A:A,'Up Rarity'!B:B,),CHAR(10),"-")} -> -

Sheet Jackrabbit
A1: Icon | B1: Name | C1: Description | D1: Turbocharge | E1: Statistic | F1: Value | G1: Min | H1: Max | I1: Statistic | J1: Value | K1: Min | L1: Max | M1: Statistic | N1: Value | O1: Min | P1: Max | Q1: Statistic | R1: Value | S1: Min | T1: Max | U1: Statistic | V1: Value | W1: Min | X1: Max | Y1: Statistic | Z1: Value | AA1: Min | AB1: Max | AC1: Statistic | AD1: Value | AE1: Min | AF1: Max | AG1: Statistic | AH1: Value | AI1: Min | AJ1: Max | AK1: Statistic | AL1: Value | AM1: Min | AN1: Max | AO1: Size | AP1: Tier
A2: {=_xlfn.XLOOKUP(B2,'Up Icon'!A:A,'Up Icon'!B:B,)} | B2: {=HYPERLINK(_xlfn.XLOOKUP('Up Names'!B32,'Up Wiki'!A:A,'Up Wiki'!B:B,),'Up Names'!B32)} -> Edge Fault | C2: {=_xlfn.XLOOKUP(B2,'Up Desc'!A:A,'Up Desc'!B:B,)} -> Increases the size of your upgrade grid. | D2: {=_xlfn.XLOOKUP(B2,'Up Turbo'!A:A,'Up Turbo'!B:B,)} -> n/a | E2: {=_xlfn.XLOOKUP(B2,'Up Stats'!A:A,'Up Stats'!B:B,)} | F2: =IFERROR(__xludf.DUMMYFUNCTION("if(AND(G2=FALSE,H2=FALSE),,if(G2=H2,JOIN("""",""Static: "",G2),JOIN("""",""Min: "",G2, CHAR(10),""Max: "",H2)))"),"") | G2: {=_xlfn.XLOOKUP(B2,'Up Min'!A:A,'Up Min'!B:B,)} | H2: {=_xlfn.XLOOKUP(B2,'Up Max'!A:A,'Up Max'!B:B,)} | I2: {=_xlfn.XLOOKUP(B2,'Up Stats'!A:A,'Up Stats'!C:C,)} | J2: =IFERROR(__xludf.DUMMYFUNCTION("if(AND(K2=FALSE,L2=FALSE),,if(K2=L2,JOIN("""",""Static: "",K2),JOIN("""",""Min: "",K2, CHAR(10),""Max: "",L2)))"),"") | K2: {=_xlfn.XLOOKUP(B2,'Up Min'!A:A,'Up Min'!C:C,)} | L2: {=_xlfn.XLOOKUP(B2,'Up Max'!A:A,'Up Max'!C:C,)} | M2: {=_xlfn.XLOOKUP(B2,'Up Stats'!A:A,'Up Stats'!D:D,)} | N2: =IFERROR(__xludf.DUMMYFUNCTION("if(AND(O2=FALSE,P2=FALSE),,if(O2=P2,JOIN("""",""Static: "",O2),JOIN("""",""Min: "",O2, CHAR(10),""Max: "",P2)))"),"") | O2: {=_xlfn.XLOOKUP(B2,'Up Min'!A:A,'Up Min'!D:D,)} | P2: {=_xlfn.XLOOKUP(B2,'Up Max'!A:A,'Up Max'!D:D,)} | Q2: {=_xlfn.XLOOKUP(B2,'Up Stats'!A:A,'Up Stats'!E:E,)} | R2: =IFERROR(__xludf.DUMMYFUNCTION("if(AND(S2=FALSE,T2=FALSE),,if(S2=T2,JOIN("""",""Static: "",S2),JOIN("""",""Min: "",S2, CHAR(10),""Max: "",T2)))"),"") | S2: {=_xlfn.XLOOKUP(B2,'Up Min'!A:A,'Up Min'!E:E,)} | T2: {=_xlfn.XLOOKUP(B2,'Up Max'!A:A,'Up Max'!E:E,)} | U2: {=_xlfn.XLOOKUP(B2,'Up Stats'!A:A,'Up Stats'!F:F,)} | V2: =IFERROR(__xludf.DUMMYFUNCTION("if(AND(W2=FALSE,X2=FALSE),,if(W2=X2,JOIN("""",""Static: "",W2),JOIN("""",""Min: "",W2, CHAR(10),""Max: "",X2)))"),"") | W2: {=_xlfn.XLOOKUP(B2,'Up Min'!A:A,'Up Min'!F:F,)} | X2: {=_xlfn.XLOOKUP(B2,'Up Max'!A:A,'Up Max'!F:F,)} | Y2: {=_xlfn.XLOOKUP(B2,'Up Stats'!A:A,'Up Stats'!G:G,)} | Z2: =IFERROR(__xludf.DUMMYFUNCTION("if(AND(AA2=FALSE,AB2=FALSE),,if(AA2=AB2,JOIN("""",""Static: "",AA2),JOIN("""",""Min: "",AA2, CHAR(10),""Max: "",AB2)))"),"") | AA2: {=_xlfn.XLOOKUP(B2,'Up Min'!A:A,'Up Min'!G:G,)} | AB2: {=_xlfn.XLOOKUP(B2,'Up Max'!A:A,'Up Max'!G:G,)} | AC2: {=_xlfn.XLOOKUP(B2,'Up Stats'!A:A,'Up Stats'!H:H,)} | AD2: =IFERROR(__xludf.DUMMYFUNCTION("if(AND(AE2=FALSE,AF2=FALSE),,if(AE2=AF2,JOIN("""",""Static: "",AE2),JOIN("""",""Min: "",AE2, CHAR(10),""Max: "",AF2)))"),"") | AE2: {=_xlfn.XLOOKUP(B2,'Up Min'!A:A,'Up Min'!H:H,)} | AF2: {=_xlfn.XLOOKUP(B2,'Up Max'!A:A,'Up Max'!H:H,)} | AG2: {=_xlfn.XLOOKUP(B2,'Up Stats'!A:A,'Up Stats'!I:I,)} | AH2: =IFERROR(__xludf.DUMMYFUNCTION("if(AND(AI2=FALSE,AJ2=FALSE),,if(AI2=AJ2,JOIN("""",""Static: "",AI2),JOIN("""",""Min: "",AI2, CHAR(10),""Max: "",AJ2)))"),"") | AI2: {=_xlfn.XLOOKUP(B2,'Up Min'!A:A,'Up Min'!I:I,)} | AJ2: {=_xlfn.XLOOKUP(B2,'Up Max'!A:A,'Up Max'!I:I,)} | AK2: {=_xlfn.XLOOKUP(B2,'Up Stats'!A:A,'Up Stats'!J:J,)} | AL2: =IFERROR(__xludf.DUMMYFUNCTION("if(AND(AM2=FALSE,AN2=FALSE),,if(AM2=AN2,JOIN("""",""Static: "",AM2),JOIN("""",""Min: "",AM2, CHAR(10),""Max: "",AN2)))"),"") | AM2: {=_xlfn.XLOOKUP(B2,'Up Min'!A:A,'Up Min'!J:J,)} | AN2: {=_xlfn.XLOOKUP(B2,'Up Max'!A:A,'Up Max'!J:J,)} | AO2: {=CONCATENATE(_xlfn.XLOOKUP(B2,'Up Cells'!A:A,'Up Cells'!B:B,))} -> 1 | AP2: {=CONCATENATE(_xlfn.XLOOKUP(B2,'Up Rarity'!A:A,'Up Rarity'!B:B,),CHAR(10),"-")} -> Contraband -
A3: {=_xlfn.XLOOKUP(B3,'Up Icon'!A:A,'Up Icon'!B:B,)} | B3: {=HYPERLINK(_xlfn.XLOOKUP('Up Names'!B33,'Up Wiki'!A:A,'Up Wiki'!B:B,),'Up Names'!B33)} -> Multiversal Thievery | C3: {=_xlfn.XLOOKUP(B3,'Up Desc'!A:A,'Up Desc'!B:B,)} -> Commandeers 1 column from each of your other upgrade grids. | D3: {=_xlfn.XLOOKUP(B3,'Up Turbo'!A:A,'Up Turbo'!B:B,)} -> n/a | E3: {=_xlfn.XLOOKUP(B3,'Up Stats'!A:A,'Up Stats'!B:B,)} | F3: =IFERROR(__xludf.DUMMYFUNCTION("if(AND(G3=FALSE,H3=FALSE),,if(G3=H3,JOIN("""",""Static: "",G3),JOIN("""",""Min: "",G3, CHAR(10),""Max: "",H3)))"),"") | G3: {=_xlfn.XLOOKUP(B3,'Up Min'!A:A,'Up Min'!B:B,)} | H3: {=_xlfn.XLOOKUP(B3,'Up Max'!A:A,'Up Max'!B:B,)} | I3: {=_xlfn.XLOOKUP(B3,'Up Stats'!A:A,'Up Stats'!C:C,)} | J3: =IFERROR(__xludf.DUMMYFUNCTION("if(AND(K3=FALSE,L3=FALSE),,if(K3=L3,JOIN("""",""Static: "",K3),JOIN("""",""Min: "",K3, CHAR(10),""Max: "",L3)))"),"") | K3: {=_xlfn.XLOOKUP(B3,'Up Min'!A:A,'Up Min'!C:C,)} | L3: {=_xlfn.XLOOKUP(B3,'Up Max'!A:A,'Up Max'!C:C,)} | M3: {=_xlfn.XLOOKUP(B3,'Up Stats'!A:A,'Up Stats'!D:D,)} | N3: =IFERROR(__xludf.DUMMYFUNCTION("if(AND(O3=FALSE,P3=FALSE),,if(O3=P3,JOIN("""",""Static: "",O3),JOIN("""",""Min: "",O3, CHAR(10),""Max: "",P3)))"),"") | O3: {=_xlfn.XLOOKUP(B3,'Up Min'!A:A,'Up Min'!D:D,)} | P3: {=_xlfn.XLOOKUP(B3,'Up Max'!A:A,'Up Max'!D:D,)} | Q3: {=_xlfn.XLOOKUP(B3,'Up Stats'!A:A,'Up Stats'!E:E,)} | R3: =IFERROR(__xludf.DUMMYFUNCTION("if(AND(S3=FALSE,T3=FALSE),,if(S3=T3,JOIN("""",""Static: "",S3),JOIN("""",""Min: "",S3, CHAR(10),""Max: "",T3)))"),"") | S3: {=_xlfn.XLOOKUP(B3,'Up Min'!A:A,'Up Min'!E:E,)} | T3: {=_xlfn.XLOOKUP(B3,'Up Max'!A:A,'Up Max'!E:E,)} | U3: {=_xlfn.XLOOKUP(B3,'Up Stats'!A:A,'Up Stats'!F:F,)} | V3: =IFERROR(__xludf.DUMMYFUNCTION("if(AND(W3=FALSE,X3=FALSE),,if(W3=X3,JOIN("""",""Static: "",W3),JOIN("""",""Min: "",W3, CHAR(10),""Max: "",X3)))"),"") | W3: {=_xlfn.XLOOKUP(B3,'Up Min'!A:A,'Up Min'!F:F,)} | X3: {=_xlfn.XLOOKUP(B3,'Up Max'!A:A,'Up Max'!F:F,)} | Y3: {=_xlfn.XLOOKUP(B3,'Up Stats'!A:A,'Up Stats'!G:G,)} | Z3: =IFERROR(__xludf.DUMMYFUNCTION("if(AND(AA3=FALSE,AB3=FALSE),,if(AA3=AB3,JOIN("""",""Static: "",AA3),JOIN("""",""Min: "",AA3, CHAR(10),""Max: "",AB3)))"),"") | AA3: {=_xlfn.XLOOKUP(B3,'Up Min'!A:A,'Up Min'!G:G,)} | AB3: {=_xlfn.XLOOKUP(B3,'Up Max'!A:A,'Up Max'!G:G,)} | AC3: {=_xlfn.XLOOKUP(B3,'Up Stats'!A:A,'Up Stats'!H:H,)} | AD3: =IFERROR(__xludf.DUMMYFUNCTION("if(AND(AE3=FALSE,AF3=FALSE),,if(AE3=AF3,JOIN("""",""Static: "",AE3),JOIN("""",""Min: "",AE3, CHAR(10),""Max: "",AF3)))"),"") | AE3: {=_xlfn.XLOOKUP(B3,'Up Min'!A:A,'Up Min'!H:H,)} | AF3: {=_xlfn.XLOOKUP(B3,'Up Max'!A:A,'Up Max'!H:H,)} | AG3: {=_xlfn.XLOOKUP(B3,'Up Stats'!A:A,'Up Stats'!I:I,)} | AH3: =IFERROR(__xludf.DUMMYFUNCTION("if(AND(AI3=FALSE,AJ3=FALSE),,if(AI3=AJ3,JOIN("""",""Static: "",AI3),JOIN("""",""Min: "",AI3, CHAR(10),""Max: "",AJ3)))"),"") | AI3: {=_xlfn.XLOOKUP(B3,'Up Min'!A:A,'Up Min'!I:I,)} | AJ3: {=_xlfn.XLOOKUP(B3,'Up Max'!A:A,'Up Max'!I:I,)} | AK3: {=_xlfn.XLOOKUP(B3,'Up Stats'!A:A,'Up Stats'!J:J,)} | AL3: =IFERROR(__xludf.DUMMYFUNCTION("if(AND(AM3=FALSE,AN3=FALSE),,if(AM3=AN3,JOIN("""",""Static: "",AM3),JOIN("""",""Min: "",AM3, CHAR(10),""Max: "",AN3)))"),"") | AM3: {=_xlfn.XLOOKUP(B3,'Up Min'!A:A,'Up Min'!J:J,)} | AN3: {=_xlfn.XLOOKUP(B3,'Up Max'!A:A,'Up Max'!J:J,)} | AO3: {=CONCATENATE(_xlfn.XLOOKUP(B3,'Up Cells'!A:A,'Up Cells'!B:B,))} -> 1 | AP3: {=CONCATENATE(_xlfn.XLOOKUP(B3,'Up Rarity'!A:A,'Up Rarity'!B:B,),CHAR(10),"-")} -> Contraband -
A4: {=_xlfn.XLOOKUP(B4,'Up Icon'!A:A,'Up Icon'!B:B,)} | B4: {=HYPERLINK(_xlfn.XLOOKUP('Up Names'!B34,'Up Wiki'!A:A,'Up Wiki'!B:B,),'Up Names'!B34)} -> Boundary Incursion | C4: {=_xlfn.XLOOKUP(B4,'Up Desc'!A:A,'Up Desc'!B:B,)} -> Increases the size of your upgrade grid. | D4: {=_xlfn.XLOOKUP(B4,'Up Turbo'!A:A,'Up Turbo'!B:B,)} -> n/a | E4: {=_xlfn.XLOOKUP(B4,'Up Stats'!A:A,'Up Stats'!B:B,)} | F4: =IFERROR(__xludf.DUMMYFUNCTION("if(AND(G4=FALSE,H4=FALSE),,if(G4=H4,JOIN("""",""Static: "",G4),JOIN("""",""Min: "",G4, CHAR(10),""Max: "",H4)))"),"") | G4: {=_xlfn.XLOOKUP(B4,'Up Min'!A:A,'Up Min'!B:B,)} | H4: {=_xlfn.XLOOKUP(B4,'Up Max'!A:A,'Up Max'!B:B,)} | I4: {=_xlfn.XLOOKUP(B4,'Up Stats'!A:A,'Up Stats'!C:C,)} | J4: =IFERROR(__xludf.DUMMYFUNCTION("if(AND(K4=FALSE,L4=FALSE),,if(K4=L4,JOIN("""",""Static: "",K4),JOIN("""",""Min: "",K4, CHAR(10),""Max: "",L4)))"),"") | K4: {=_xlfn.XLOOKUP(B4,'Up Min'!A:A,'Up Min'!C:C,)} | L4: {=_xlfn.XLOOKUP(B4,'Up Max'!A:A,'Up Max'!C:C,)} | M4: {=_xlfn.XLOOKUP(B4,'Up Stats'!A:A,'Up Stats'!D:D,)} | N4: =IFERROR(__xludf.DUMMYFUNCTION("if(AND(O4=FALSE,P4=FALSE),,if(O4=P4,JOIN("""",""Static: "",O4),JOIN("""",""Min: "",O4, CHAR(10),""Max: "",P4)))"),"") | O4: {=_xlfn.XLOOKUP(B4,'Up Min'!A:A,'Up Min'!D:D,)} | P4: {=_xlfn.XLOOKUP(B4,'Up Max'!A:A,'Up Max'!D:D,)} | Q4: {=_xlfn.XLOOKUP(B4,'Up Stats'!A:A,'Up Stats'!E:E,)} | R4: =IFERROR(__xludf.DUMMYFUNCTION("if(AND(S4=FALSE,T4=FALSE),,if(S4=T4,JOIN("""",""Static: "",S4),JOIN("""",""Min: "",S4, CHAR(10),""Max: "",T4)))"),"") | S4: {=_xlfn.XLOOKUP(B4,'Up Min'!A:A,'Up Min'!E:E,)} | T4: {=_xlfn.XLOOKUP(B4,'Up Max'!A:A,'Up Max'!E:E,)} | U4: {=_xlfn.XLOOKUP(B4,'Up Stats'!A:A,'Up Stats'!F:F,)} | V4: =IFERROR(__xludf.DUMMYFUNCTION("if(AND(W4=FALSE,X4=FALSE),,if(W4=X4,JOIN("""",""Static: "",W4),JOIN("""",""Min: "",W4, CHAR(10),""Max: "",X4)))"),"") | W4: {=_xlfn.XLOOKUP(B4,'Up Min'!A:A,'Up Min'!F:F,)} | X4: {=_xlfn.XLOOKUP(B4,'Up Max'!A:A,'Up Max'!F:F,)} | Y4: {=_xlfn.XLOOKUP(B4,'Up Stats'!A:A,'Up Stats'!G:G,)} | Z4: =IFERROR(__xludf.DUMMYFUNCTION("if(AND(AA4=FALSE,AB4=FALSE),,if(AA4=AB4,JOIN("""",""Static: "",AA4),JOIN("""",""Min: "",AA4, CHAR(10),""Max: "",AB4)))"),"") | AA4: {=_xlfn.XLOOKUP(B4,'Up Min'!A:A,'Up Min'!G:G,)} | AB4: {=_xlfn.XLOOKUP(B4,'Up Max'!A:A,'Up Max'!G:G,)} | AC4: {=_xlfn.XLOOKUP(B4,'Up Stats'!A:A,'Up Stats'!H:H,)} | AD4: =IFERROR(__xludf.DUMMYFUNCTION("if(AND(AE4=FALSE,AF4=FALSE),,if(AE4=AF4,JOIN("""",""Static: "",AE4),JOIN("""",""Min: "",AE4, CHAR(10),""Max: "",AF4)))"),"") | AE4: {=_xlfn.XLOOKUP(B4,'Up Min'!A:A,'Up Min'!H:H,)} | AF4: {=_xlfn.XLOOKUP(B4,'Up Max'!A:A,'Up Max'!H:H,)} | AG4: {=_xlfn.XLOOKUP(B4,'Up Stats'!A:A,'Up Stats'!I:I,)} | AH4: =IFERROR(__xludf.DUMMYFUNCTION("if(AND(AI4=FALSE,AJ4=FALSE),,if(AI4=AJ4,JOIN("""",""Static: "",AI4),JOIN("""",""Min: "",AI4, CHAR(10),""Max: "",AJ4)))"),"") | AI4: {=_xlfn.XLOOKUP(B4,'Up Min'!A:A,'Up Min'!I:I,)} | AJ4: {=_xlfn.XLOOKUP(B4,'Up Max'!A:A,'Up Max'!I:I,)} | AK4: {=_xlfn.XLOOKUP(B4,'Up Stats'!A:A,'Up Stats'!J:J,)} | AL4: =IFERROR(__xludf.DUMMYFUNCTION("if(AND(AM4=FALSE,AN4=FALSE),,if(AM4=AN4,JOIN("""",""Static: "",AM4),JOIN("""",""Min: "",AM4, CHAR(10),""Max: "",AN4)))"),"") | AM4: {=_xlfn.XLOOKUP(B4,'Up Min'!A:A,'Up Min'!J:J,)} | AN4: {=_xlfn.XLOOKUP(B4,'Up Max'!A:A,'Up Max'!J:J,)} | AO4: {=CONCATENATE(_xlfn.XLOOKUP(B4,'Up Cells'!A:A,'Up Cells'!B:B,))} -> 1 | AP4: {=CONCATENATE(_xlfn.XLOOKUP(B4,'Up Rarity'!A:A,'Up Rarity'!B:B,),CHAR(10),"-")} -> Oddity -
A5: {=_xlfn.XLOOKUP(B5,'Up Icon'!A:A,'Up Icon'!B:B,)} | B5: {=HYPERLINK(_xlfn.XLOOKUP('Up Names'!B2,'Up Wiki'!A:A,'Up Wiki'!B:B,),'Up Names'!B2)} -> All Powdered Up | C5: {=_xlfn.XLOOKUP(B5,'Up Desc'!A:A,'Up Desc'!B:B,)} -> While airborne, firing a shot pushes you backwards. Force increases as mag size decreases. | D5: {=_xlfn.XLOOKUP(B5,'Up Turbo'!A:A,'Up Turbo'!B:B,)} -> [Redacted] | E5: {=_xlfn.XLOOKUP(B5,'Up Stats'!A:A,'Up Stats'!B:B,)} -> Force | F5: =IFERROR(__xludf.DUMMYFUNCTION("if(AND(G5=FALSE,H5=FALSE),,if(G5=H5,JOIN("""",""Static: "",G5),JOIN("""",""Min: "",G5, CHAR(10),""Max: "",H5)))"),"Min: 49.2 Max: 60") -> Min: 49.2 Max: 60 | G5: {=_xlfn.XLOOKUP(B5,'Up Min'!A:A,'Up Min'!B:B,)} -> 49.2 | H5: {=_xlfn.XLOOKUP(B5,'Up Max'!A:A,'Up Max'!B:B,)} -> 60 | I5: {=_xlfn.XLOOKUP(B5,'Up Stats'!A:A,'Up Stats'!C:C,)} -> Range | J5: =IFERROR(__xludf.DUMMYFUNCTION("if(AND(K5=FALSE,L5=FALSE),,if(K5=L5,JOIN("""",""Static: "",K5),JOIN("""",""Min: "",K5, CHAR(10),""Max: "",L5)))"),"Min: 4.5 Max: 6.5") -> Min: 4.5 Max: 6.5 | K5: {=_xlfn.XLOOKUP(B5,'Up Min'!A:A,'Up Min'!C:C,)} -> 4.5 | L5: {=_xlfn.XLOOKUP(B5,'Up Max'!A:A,'Up Max'!C:C,)} -> 6.5 | M5: {=_xlfn.XLOOKUP(B5,'Up Stats'!A:A,'Up Stats'!D:D,)} | N5: =IFERROR(__xludf.DUMMYFUNCTION("if(AND(O5=FALSE,P5=FALSE),,if(O5=P5,JOIN("""",""Static: "",O5),JOIN("""",""Min: "",O5, CHAR(10),""Max: "",P5)))"),"") | O5: {=_xlfn.XLOOKUP(B5,'Up Min'!A:A,'Up Min'!D:D,)} | P5: {=_xlfn.XLOOKUP(B5,'Up Max'!A:A,'Up Max'!D:D,)} | Q5: {=_xlfn.XLOOKUP(B5,'Up Stats'!A:A,'Up Stats'!E:E,)} | R5: =IFERROR(__xludf.DUMMYFUNCTION("if(AND(S5=FALSE,T5=FALSE),,if(S5=T5,JOIN("""",""Static: "",S5),JOIN("""",""Min: "",S5, CHAR(10),""Max: "",T5)))"),"") | S5: {=_xlfn.XLOOKUP(B5,'Up Min'!A:A,'Up Min'!E:E,)} | T5: {=_xlfn.XLOOKUP(B5,'Up Max'!A:A,'Up Max'!E:E,)} | U5: {=_xlfn.XLOOKUP(B5,'Up Stats'!A:A,'Up Stats'!F:F,)} | V5: =IFERROR(__xludf.DUMMYFUNCTION("if(AND(W5=FALSE,X5=FALSE),,if(W5=X5,JOIN("""",""Static: "",W5),JOIN("""",""Min: "",W5, CHAR(10),""Max: "",X5)))"),"") | W5: {=_xlfn.XLOOKUP(B5,'Up Min'!A:A,'Up Min'!F:F,)} | X5: {=_xlfn.XLOOKUP(B5,'Up Max'!A:A,'Up Max'!F:F,)} | Y5: {=_xlfn.XLOOKUP(B5,'Up Stats'!A:A,'Up Stats'!G:G,)} | Z5: =IFERROR(__xludf.DUMMYFUNCTION("if(AND(AA5=FALSE,AB5=FALSE),,if(AA5=AB5,JOIN("""",""Static: "",AA5),JOIN("""",""Min: "",AA5, CHAR(10),""Max: "",AB5)))"),"") | AA5: {=_xlfn.XLOOKUP(B5,'Up Min'!A:A,'Up Min'!G:G,)} | AB5: {=_xlfn.XLOOKUP(B5,'Up Max'!A:A,'Up Max'!G:G,)} | AC5: {=_xlfn.XLOOKUP(B5,'Up Stats'!A:A,'Up Stats'!H:H,)} | AD5: =IFERROR(__xludf.DUMMYFUNCTION("if(AND(AE5=FALSE,AF5=FALSE),,if(AE5=AF5,JOIN("""",""Static: "",AE5),JOIN("""",""Min: "",AE5, CHAR(10),""Max: "",AF5)))"),"") | AE5: {=_xlfn.XLOOKUP(B5,'Up Min'!A:A,'Up Min'!H:H,)} | AF5: {=_xlfn.XLOOKUP(B5,'Up Max'!A:A,'Up Max'!H:H,)} | AG5: {=_xlfn.XLOOKUP(B5,'Up Stats'!A:A,'Up Stats'!I:I,)} | AH5: =IFERROR(__xludf.DUMMYFUNCTION("if(AND(AI5=FALSE,AJ5=FALSE),,if(AI5=AJ5,JOIN("""",""Static: "",AI5),JOIN("""",""Min: "",AI5, CHAR(10),""Max: "",AJ5)))"),"") | AI5: {=_xlfn.XLOOKUP(B5,'Up Min'!A:A,'Up Min'!I:I,)} | AJ5: {=_xlfn.XLOOKUP(B5,'Up Max'!A:A,'Up Max'!I:I,)} | AK5: {=_xlfn.XLOOKUP(B5,'Up Stats'!A:A,'Up Stats'!J:J,)} | AL5: =IFERROR(__xludf.DUMMYFUNCTION("if(AND(AM5=FALSE,AN5=FALSE),,if(AM5=AN5,JOIN("""",""Static: "",AM5),JOIN("""",""Min: "",AM5, CHAR(10),""Max: "",AN5)))"),"") | AM5: {=_xlfn.XLOOKUP(B5,'Up Min'!A:A,'Up Min'!J:J,)} | AN5: {=_xlfn.XLOOKUP(B5,'Up Max'!A:A,'Up Max'!J:J,)} | AO5: {=CONCATENATE(_xlfn.XLOOKUP(B5,'Up Cells'!A:A,'Up Cells'!B:B,))} -> 6 | AP5: {=CONCATENATE(_xlfn.XLOOKUP(B5,'Up Rarity'!A:A,'Up Rarity'!B:B,),CHAR(10),"-")} -> Exotic -
A6: {=_xlfn.XLOOKUP(B6,'Up Icon'!A:A,'Up Icon'!B:B,)} | B6: {=HYPERLINK(_xlfn.XLOOKUP('Up Names'!B3,'Up Wiki'!A:A,'Up Wiki'!B:B,),'Up Names'!B3)} -> Immolator | C6: {=_xlfn.XLOOKUP(B6,'Up Desc'!A:A,'Up Desc'!B:B,)} -> Applying fire to a target also applies it to you. When you ignite yourself, you gain immolation for 6.5 seconds. | D6: {=_xlfn.XLOOKUP(B6,'Up Turbo'!A:A,'Up Turbo'!B:B,)} | E6: {=_xlfn.XLOOKUP(B6,'Up Stats'!A:A,'Up Stats'!B:B,)} -> Self Fire | F6: =IFERROR(__xludf.DUMMYFUNCTION("if(AND(G6=FALSE,H6=FALSE),,if(G6=H6,JOIN("""",""Static: "",G6),JOIN("""",""Min: "",G6, CHAR(10),""Max: "",H6)))"),"Min: 0.1 Max: 0.2") -> Min: 0.1 Max: 0.2 | G6: {=_xlfn.XLOOKUP(B6,'Up Min'!A:A,'Up Min'!B:B,)} -> 0.1 | H6: {=_xlfn.XLOOKUP(B6,'Up Max'!A:A,'Up Max'!B:B,)} -> 0.2 | I6: {=_xlfn.XLOOKUP(B6,'Up Stats'!A:A,'Up Stats'!C:C,)} | J6: =IFERROR(__xludf.DUMMYFUNCTION("if(AND(K6=FALSE,L6=FALSE),,if(K6=L6,JOIN("""",""Static: "",K6),JOIN("""",""Min: "",K6, CHAR(10),""Max: "",L6)))"),"") | K6: {=_xlfn.XLOOKUP(B6,'Up Min'!A:A,'Up Min'!C:C,)} | L6: {=_xlfn.XLOOKUP(B6,'Up Max'!A:A,'Up Max'!C:C,)} | M6: {=_xlfn.XLOOKUP(B6,'Up Stats'!A:A,'Up Stats'!D:D,)} | N6: =IFERROR(__xludf.DUMMYFUNCTION("if(AND(O6=FALSE,P6=FALSE),,if(O6=P6,JOIN("""",""Static: "",O6),JOIN("""",""Min: "",O6, CHAR(10),""Max: "",P6)))"),"") | O6: {=_xlfn.XLOOKUP(B6,'Up Min'!A:A,'Up Min'!D:D,)} | P6: {=_xlfn.XLOOKUP(B6,'Up Max'!A:A,'Up Max'!D:D,)} | Q6: {=_xlfn.XLOOKUP(B6,'Up Stats'!A:A,'Up Stats'!E:E,)} | R6: =IFERROR(__xludf.DUMMYFUNCTION("if(AND(S6=FALSE,T6=FALSE),,if(S6=T6,JOIN("""",""Static: "",S6),JOIN("""",""Min: "",S6, CHAR(10),""Max: "",T6)))"),"") | S6: {=_xlfn.XLOOKUP(B6,'Up Min'!A:A,'Up Min'!E:E,)} | T6: {=_xlfn.XLOOKUP(B6,'Up Max'!A:A,'Up Max'!E:E,)} | U6: {=_xlfn.XLOOKUP(B6,'Up Stats'!A:A,'Up Stats'!F:F,)} | V6: =IFERROR(__xludf.DUMMYFUNCTION("if(AND(W6=FALSE,X6=FALSE),,if(W6=X6,JOIN("""",""Static: "",W6),JOIN("""",""Min: "",W6, CHAR(10),""Max: "",X6)))"),"") | W6: {=_xlfn.XLOOKUP(B6,'Up Min'!A:A,'Up Min'!F:F,)} | X6: {=_xlfn.XLOOKUP(B6,'Up Max'!A:A,'Up Max'!F:F,)} | Y6: {=_xlfn.XLOOKUP(B6,'Up Stats'!A:A,'Up Stats'!G:G,)} | Z6: =IFERROR(__xludf.DUMMYFUNCTION("if(AND(AA6=FALSE,AB6=FALSE),,if(AA6=AB6,JOIN("""",""Static: "",AA6),JOIN("""",""Min: "",AA6, CHAR(10),""Max: "",AB6)))"),"") | AA6: {=_xlfn.XLOOKUP(B6,'Up Min'!A:A,'Up Min'!G:G,)} | AB6: {=_xlfn.XLOOKUP(B6,'Up Max'!A:A,'Up Max'!G:G,)} | AC6: {=_xlfn.XLOOKUP(B6,'Up Stats'!A:A,'Up Stats'!H:H,)} | AD6: =IFERROR(__xludf.DUMMYFUNCTION("if(AND(AE6=FALSE,AF6=FALSE),,if(AE6=AF6,JOIN("""",""Static: "",AE6),JOIN("""",""Min: "",AE6, CHAR(10),""Max: "",AF6)))"),"") | AE6: {=_xlfn.XLOOKUP(B6,'Up Min'!A:A,'Up Min'!H:H,)} | AF6: {=_xlfn.XLOOKUP(B6,'Up Max'!A:A,'Up Max'!H:H,)} | AG6: {=_xlfn.XLOOKUP(B6,'Up Stats'!A:A,'Up Stats'!I:I,)} | AH6: =IFERROR(__xludf.DUMMYFUNCTION("if(AND(AI6=FALSE,AJ6=FALSE),,if(AI6=AJ6,JOIN("""",""Static: "",AI6),JOIN("""",""Min: "",AI6, CHAR(10),""Max: "",AJ6)))"),"") | AI6: {=_xlfn.XLOOKUP(B6,'Up Min'!A:A,'Up Min'!I:I,)} | AJ6: {=_xlfn.XLOOKUP(B6,'Up Max'!A:A,'Up Max'!I:I,)} | AK6: {=_xlfn.XLOOKUP(B6,'Up Stats'!A:A,'Up Stats'!J:J,)} | AL6: =IFERROR(__xludf.DUMMYFUNCTION("if(AND(AM6=FALSE,AN6=FALSE),,if(AM6=AN6,JOIN("""",""Static: "",AM6),JOIN("""",""Min: "",AM6, CHAR(10),""Max: "",AN6)))"),"") | AM6: {=_xlfn.XLOOKUP(B6,'Up Min'!A:A,'Up Min'!J:J,)} | AN6: {=_xlfn.XLOOKUP(B6,'Up Max'!A:A,'Up Max'!J:J,)} | AO6: {=CONCATENATE(_xlfn.XLOOKUP(B6,'Up Cells'!A:A,'Up Cells'!B:B,))} -> 8 | AP6: {=CONCATENATE(_xlfn.XLOOKUP(B6,'Up Rarity'!A:A,'Up Rarity'!B:B,),CHAR(10),"-")} -> Exotic -
A7: {=_xlfn.XLOOKUP(B7,'Up Icon'!A:A,'Up Icon'!B:B,)} | B7: {=HYPERLINK(_xlfn.XLOOKUP('Up Names'!B4,'Up Wiki'!A:A,'Up Wiki'!B:B,),'Up Names'!B4)} -> Pesticide | C7: {=_xlfn.XLOOKUP(B7,'Up Desc'!A:A,'Up Desc'!B:B,)} -> Hold AIM to fire a flamethrower. | D7: {=_xlfn.XLOOKUP(B7,'Up Turbo'!A:A,'Up Turbo'!B:B,)} | E7: {=_xlfn.XLOOKUP(B7,'Up Stats'!A:A,'Up Stats'!B:B,)} -> Damage | F7: =IFERROR(__xludf.DUMMYFUNCTION("if(AND(G7=FALSE,H7=FALSE),,if(G7=H7,JOIN("""",""Static: "",G7),JOIN("""",""Min: "",G7, CHAR(10),""Max: "",H7)))"),"Min: 100 Max: 140") -> Min: 100 Max: 140 | G7: {=_xlfn.XLOOKUP(B7,'Up Min'!A:A,'Up Min'!B:B,)} -> 100 | H7: {=_xlfn.XLOOKUP(B7,'Up Max'!A:A,'Up Max'!B:B,)} -> 140 | I7: {=_xlfn.XLOOKUP(B7,'Up Stats'!A:A,'Up Stats'!C:C,)} -> Fire | J7: =IFERROR(__xludf.DUMMYFUNCTION("if(AND(K7=FALSE,L7=FALSE),,if(K7=L7,JOIN("""",""Static: "",K7),JOIN("""",""Min: "",K7, CHAR(10),""Max: "",L7)))"),"Min: 10 Max: 20") -> Min: 10 Max: 20 | K7: {=_xlfn.XLOOKUP(B7,'Up Min'!A:A,'Up Min'!C:C,)} -> 10 | L7: {=_xlfn.XLOOKUP(B7,'Up Max'!A:A,'Up Max'!C:C,)} -> 20 | M7: {=_xlfn.XLOOKUP(B7,'Up Stats'!A:A,'Up Stats'!D:D,)} -> Range | N7: =IFERROR(__xludf.DUMMYFUNCTION("if(AND(O7=FALSE,P7=FALSE),,if(O7=P7,JOIN("""",""Static: "",O7),JOIN("""",""Min: "",O7, CHAR(10),""Max: "",P7)))"),"Min: 4.8 Max: 7") -> Min: 4.8 Max: 7 | O7: {=_xlfn.XLOOKUP(B7,'Up Min'!A:A,'Up Min'!D:D,)} -> 4.8 | P7: {=_xlfn.XLOOKUP(B7,'Up Max'!A:A,'Up Max'!D:D,)} -> 7 | Q7: {=_xlfn.XLOOKUP(B7,'Up Stats'!A:A,'Up Stats'!E:E,)} -> Radius | R7: =IFERROR(__xludf.DUMMYFUNCTION("if(AND(S7=FALSE,T7=FALSE),,if(S7=T7,JOIN("""",""Static: "",S7),JOIN("""",""Min: "",S7, CHAR(10),""Max: "",T7)))"),"Static: 1") -> Static: 1 | S7: {=_xlfn.XLOOKUP(B7,'Up Min'!A:A,'Up Min'!E:E,)} -> 1 | T7: {=_xlfn.XLOOKUP(B7,'Up Max'!A:A,'Up Max'!E:E,)} -> 1 | U7: {=_xlfn.XLOOKUP(B7,'Up Stats'!A:A,'Up Stats'!F:F,)} | V7: =IFERROR(__xludf.DUMMYFUNCTION("if(AND(W7=FALSE,X7=FALSE),,if(W7=X7,JOIN("""",""Static: "",W7),JOIN("""",""Min: "",W7, CHAR(10),""Max: "",X7)))"),"") | W7: {=_xlfn.XLOOKUP(B7,'Up Min'!A:A,'Up Min'!F:F,)} | X7: {=_xlfn.XLOOKUP(B7,'Up Max'!A:A,'Up Max'!F:F,)} | Y7: {=_xlfn.XLOOKUP(B7,'Up Stats'!A:A,'Up Stats'!G:G,)} | Z7: =IFERROR(__xludf.DUMMYFUNCTION("if(AND(AA7=FALSE,AB7=FALSE),,if(AA7=AB7,JOIN("""",""Static: "",AA7),JOIN("""",""Min: "",AA7, CHAR(10),""Max: "",AB7)))"),"") | AA7: {=_xlfn.XLOOKUP(B7,'Up Min'!A:A,'Up Min'!G:G,)} | AB7: {=_xlfn.XLOOKUP(B7,'Up Max'!A:A,'Up Max'!G:G,)} | AC7: {=_xlfn.XLOOKUP(B7,'Up Stats'!A:A,'Up Stats'!H:H,)} | AD7: =IFERROR(__xludf.DUMMYFUNCTION("if(AND(AE7=FALSE,AF7=FALSE),,if(AE7=AF7,JOIN("""",""Static: "",AE7),JOIN("""",""Min: "",AE7, CHAR(10),""Max: "",AF7)))"),"") | AE7: {=_xlfn.XLOOKUP(B7,'Up Min'!A:A,'Up Min'!H:H,)} | AF7: {=_xlfn.XLOOKUP(B7,'Up Max'!A:A,'Up Max'!H:H,)} | AG7: {=_xlfn.XLOOKUP(B7,'Up Stats'!A:A,'Up Stats'!I:I,)} | AH7: =IFERROR(__xludf.DUMMYFUNCTION("if(AND(AI7=FALSE,AJ7=FALSE),,if(AI7=AJ7,JOIN("""",""Static: "",AI7),JOIN("""",""Min: "",AI7, CHAR(10),""Max: "",AJ7)))"),"") | AI7: {=_xlfn.XLOOKUP(B7,'Up Min'!A:A,'Up Min'!I:I,)} | AJ7: {=_xlfn.XLOOKUP(B7,'Up Max'!A:A,'Up Max'!I:I,)} | AK7: {=_xlfn.XLOOKUP(B7,'Up Stats'!A:A,'Up Stats'!J:J,)} | AL7: =IFERROR(__xludf.DUMMYFUNCTION("if(AND(AM7=FALSE,AN7=FALSE),,if(AM7=AN7,JOIN("""",""Static: "",AM7),JOIN("""",""Min: "",AM7, CHAR(10),""Max: "",AN7)))"),"") | AM7: {=_xlfn.XLOOKUP(B7,'Up Min'!A:A,'Up Min'!J:J,)} | AN7: {=_xlfn.XLOOKUP(B7,'Up Max'!A:A,'Up Max'!J:J,)} | AO7: {=CONCATENATE(_xlfn.XLOOKUP(B7,'Up Cells'!A:A,'Up Cells'!B:B,))} -> 6 | AP7: {=CONCATENATE(_xlfn.XLOOKUP(B7,'Up Rarity'!A:A,'Up Rarity'!B:B,),CHAR(10),"-")} -> Exotic -
A8: {=_xlfn.XLOOKUP(B8,'Up Icon'!A:A,'Up Icon'!B:B,)} | B8: {=HYPERLINK(_xlfn.XLOOKUP('Up Names'!B5,'Up Wiki'!A:A,'Up Wiki'!B:B,),'Up Names'!B5)} -> Pummeler | C8: {=_xlfn.XLOOKUP(B8,'Up Desc'!A:A,'Up Desc'!B:B,)} -> Hold RELOAD to charge up bullets. Release to fire all charged bullets in a rapid burst. | D8: {=_xlfn.XLOOKUP(B8,'Up Turbo'!A:A,'Up Turbo'!B:B,)} | E8: {=_xlfn.XLOOKUP(B8,'Up Stats'!A:A,'Up Stats'!B:B,)} -> Charge Speed | F8: =IFERROR(__xludf.DUMMYFUNCTION("if(AND(G8=FALSE,H8=FALSE),,if(G8=H8,JOIN("""",""Static: "",G8),JOIN("""",""Min: "",G8, CHAR(10),""Max: "",H8)))"),"Min: 9.74 Max: 11.76") -> Min: 9.74 Max: 11.76 | G8: {=_xlfn.XLOOKUP(B8,'Up Min'!A:A,'Up Min'!B:B,)} -> 9.74 | H8: {=_xlfn.XLOOKUP(B8,'Up Max'!A:A,'Up Max'!B:B,)} -> 11.76 | I8: {=_xlfn.XLOOKUP(B8,'Up Stats'!A:A,'Up Stats'!C:C,)} -> Fire Rate | J8: =IFERROR(__xludf.DUMMYFUNCTION("if(AND(K8=FALSE,L8=FALSE),,if(K8=L8,JOIN("""",""Static: "",K8),JOIN("""",""Min: "",K8, CHAR(10),""Max: "",L8)))"),"Min: 122.22% Max: 112.77%") -> Min: 122.22% Max: 112.77% | K8: {=_xlfn.XLOOKUP(B8,'Up Min'!A:A,'Up Min'!C:C,)} -> 1.2222 | L8: {=_xlfn.XLOOKUP(B8,'Up Max'!A:A,'Up Max'!C:C,)} -> 1.1277 | M8: {=_xlfn.XLOOKUP(B8,'Up Stats'!A:A,'Up Stats'!D:D,)} -> Magazine Size | N8: =IFERROR(__xludf.DUMMYFUNCTION("if(AND(O8=FALSE,P8=FALSE),,if(O8=P8,JOIN("""",""Static: "",O8),JOIN("""",""Min: "",O8, CHAR(10),""Max: "",P8)))"),"Min: 3 Max: 5") -> Min: 3 Max: 5 | O8: {=_xlfn.XLOOKUP(B8,'Up Min'!A:A,'Up Min'!D:D,)} -> 3 | P8: {=_xlfn.XLOOKUP(B8,'Up Max'!A:A,'Up Max'!D:D,)} -> 5 | Q8: {=_xlfn.XLOOKUP(B8,'Up Stats'!A:A,'Up Stats'!E:E,)} | R8: =IFERROR(__xludf.DUMMYFUNCTION("if(AND(S8=FALSE,T8=FALSE),,if(S8=T8,JOIN("""",""Static: "",S8),JOIN("""",""Min: "",S8, CHAR(10),""Max: "",T8)))"),"") | S8: {=_xlfn.XLOOKUP(B8,'Up Min'!A:A,'Up Min'!E:E,)} | T8: {=_xlfn.XLOOKUP(B8,'Up Max'!A:A,'Up Max'!E:E,)} | U8: {=_xlfn.XLOOKUP(B8,'Up Stats'!A:A,'Up Stats'!F:F,)} | V8: =IFERROR(__xludf.DUMMYFUNCTION("if(AND(W8=FALSE,X8=FALSE),,if(W8=X8,JOIN("""",""Static: "",W8),JOIN("""",""Min: "",W8, CHAR(10),""Max: "",X8)))"),"") | W8: {=_xlfn.XLOOKUP(B8,'Up Min'!A:A,'Up Min'!F:F,)} | X8: {=_xlfn.XLOOKUP(B8,'Up Max'!A:A,'Up Max'!F:F,)} | Y8: {=_xlfn.XLOOKUP(B8,'Up Stats'!A:A,'Up Stats'!G:G,)} | Z8: =IFERROR(__xludf.DUMMYFUNCTION("if(AND(AA8=FALSE,AB8=FALSE),,if(AA8=AB8,JOIN("""",""Static: "",AA8),JOIN("""",""Min: "",AA8, CHAR(10),""Max: "",AB8)))"),"") | AA8: {=_xlfn.XLOOKUP(B8,'Up Min'!A:A,'Up Min'!G:G,)} | AB8: {=_xlfn.XLOOKUP(B8,'Up Max'!A:A,'Up Max'!G:G,)} | AC8: {=_xlfn.XLOOKUP(B8,'Up Stats'!A:A,'Up Stats'!H:H,)} | AD8: =IFERROR(__xludf.DUMMYFUNCTION("if(AND(AE8=FALSE,AF8=FALSE),,if(AE8=AF8,JOIN("""",""Static: "",AE8),JOIN("""",""Min: "",AE8, CHAR(10),""Max: "",AF8)))"),"") | AE8: {=_xlfn.XLOOKUP(B8,'Up Min'!A:A,'Up Min'!H:H,)} | AF8: {=_xlfn.XLOOKUP(B8,'Up Max'!A:A,'Up Max'!H:H,)} | AG8: {=_xlfn.XLOOKUP(B8,'Up Stats'!A:A,'Up Stats'!I:I,)} | AH8: =IFERROR(__xludf.DUMMYFUNCTION("if(AND(AI8=FALSE,AJ8=FALSE),,if(AI8=AJ8,JOIN("""",""Static: "",AI8),JOIN("""",""Min: "",AI8, CHAR(10),""Max: "",AJ8)))"),"") | AI8: {=_xlfn.XLOOKUP(B8,'Up Min'!A:A,'Up Min'!I:I,)} | AJ8: {=_xlfn.XLOOKUP(B8,'Up Max'!A:A,'Up Max'!I:I,)} | AK8: {=_xlfn.XLOOKUP(B8,'Up Stats'!A:A,'Up Stats'!J:J,)} | AL8: =IFERROR(__xludf.DUMMYFUNCTION("if(AND(AM8=FALSE,AN8=FALSE),,if(AM8=AN8,JOIN("""",""Static: "",AM8),JOIN("""",""Min: "",AM8, CHAR(10),""Max: "",AN8)))"),"") | AM8: {=_xlfn.XLOOKUP(B8,'Up Min'!A:A,'Up Min'!J:J,)} | AN8: {=_xlfn.XLOOKUP(B8,'Up Max'!A:A,'Up Max'!J:J,)} | AO8: {=CONCATENATE(_xlfn.XLOOKUP(B8,'Up Cells'!A:A,'Up Cells'!B:B,))} -> 5 | AP8: {=CONCATENATE(_xlfn.XLOOKUP(B8,'Up Rarity'!A:A,'Up Rarity'!B:B,),CHAR(10),"-")} -> Exotic -
